Workbook

Sheet 无任命人员话费福利
A1: 2026年内蒙古准格尔旗力量煤业有限公司 无任命人员话费及燃油费报销台账
A2: 序号 | B2: 类别 | C2: 姓名 | D2: 身份证号 | E2: 工作部门 | F2: 岗位 | G2: 话费报销情况 | L2: 燃油报销情况 | P2: 备注 | S2: 电话费 | AE2: 探亲地 | AF2: 第一次探亲 | AI2: 第二次探亲 | AL2: 第三次探亲 | AO2: 第四次探亲 | AR2: 第五次探亲 | AU2: 第六次探亲 | AX2: 探亲费 总金额 | AY2: 报销合计 金额 | AZ2: 备案日期 | BA2: 经办人 | BB2: 备注
C3: 姓名 | D3: 身份证号 | E3: 工作部门 | F3: 岗位 | G3: 话费开始报销月份 | H3: 报销依据 | I3: 话费申请标准（元/月） | J3: 已执行标准（元/月） | K3: 建议调整标准 （元/月） | L3: 燃油标准（元/月） | M3: 最终审批人 | N3: 是否有扫描件 | O3: 审批时间 | S3: 1月 | T3: 2月 | U3: 3月 | V3: 4月 | W3: 5月 | X3: 6月 | Y3: 7月 | Z3: 8月 | AA3: 9月 | AB3: 10月 | AC3: 11月 | AD3: 12月 | AF3: 开始时间 | AG3: 结束时间 | AH3: 金额 | AI3: 开始时间 | AJ3: 结束时间 | AK3: 金额 | AL3: 开始时间 | AM3: 结束时间 | AN3: 金额 | AO3: 开始时间 | AP3: 结束时间 | AQ3: 金额 | AR3: 开始时间 | AS3: 结束时间 | AT3: 金额 | AU3: 开始时间 | AV3: 结束时间 | AW3: 金额
A4: 1 | C4: 许燕 | D4: =VLOOKUP(C4,[2]在职人员信息表!$F:$U,16,FALSE) -> 152723199105241520 | E4: =VLOOKUP(C4,[1]在职人员信息表!$F:$G,2,FALSE) -> 总调度室 | F4: =VLOOKUP(C4,[1]在职人员信息表!$F:$H,3,FALSE) -> 办事员 | G4: 44378 | H4: 请示审批报销 | I4: 100 | M4: 李波 | N4: 有 | O4: 44424 | R4: =_xlfn.XLOOKUP(C4,'[4]20250916话费报销调整'!$B:$B,'[4]20250916话费报销调整'!$D:$D,0,0) -> 0 | S4: 100 | T4: 100 | U4: 100
A5: 2 | C5: 白晶晶 | D5: =VLOOKUP(C5,[2]在职人员信息表!$F:$U,16,FALSE) -> 150422198502193949 | E5: =VLOOKUP(C5,[1]在职人员信息表!$F:$G,2,FALSE) -> 安全监察科 | F5: =VLOOKUP(C5,[1]在职人员信息表!$F:$H,3,FALSE) -> 资料员 | G5: 44378 | H5: 请示审批报销 | I5: 100 | M5: 李运成 | N5: 有 | O5: 44305 | Q5: =_xlfn.XLOOKUP(C5,[3]调动人员明细表!$D:$D,[3]调动人员明细表!$F:$F,0,0) -> 44261 | R5: =_xlfn.XLOOKUP(C5,'[4]20250916话费报销调整'!$B:$B,'[4]20250916话费报销调整'!$D:$D,0,0) -> 0 | S5: 99.6 | T5: 99 | U5: 99.2
A6: 3 | C6: 张娜 | D6: =VLOOKUP(C6,[2]在职人员信息表!$F:$U,16,FALSE) -> 150207198702241023 | E6: =VLOOKUP(C6,[1]在职人员信息表!$F:$G,2,FALSE) -> 机运队 | F6: =VLOOKUP(C6,[1]在职人员信息表!$F:$H,3,FALSE) -> 办事员 | G6: 43466 | H6: 请示审批报销 | I6: 100 | M6: 李波 | N6: 有 | O6: 45182 | R6: =_xlfn.XLOOKUP(C6,'[4]20250916话费报销调整'!$B:$B,'[4]20250916话费报销调整'!$D:$D,0,0) -> 0 | S6: 100 | T6: 100 | U6: 100
A7: 4 | C7: 张衡 | D7: =VLOOKUP(C7,[2]在职人员信息表!$F:$U,16,FALSE) -> 152633197402282714 | E7: =VLOOKUP(C7,[1]在职人员信息表!$F:$G,2,FALSE) -> 生产机修科 | F7: =VLOOKUP(C7,[1]在职人员信息表!$F:$H,3,FALSE) -> 专员 | G7: 44348 | H7: 请示审批报销 | I7: 100 | M7: 李波 | N7: 有 | O7: 44432 | P7: 2025年8月调动，调动后无审批 | Q7: =_xlfn.XLOOKUP(C7,[3]调动人员明细表!$D:$D,[3]调动人员明细表!$F:$F,0,0) -> 45884 | R7: =_xlfn.XLOOKUP(C7,'[4]20250916话费报销调整'!$B:$B,'[4]20250916话费报销调整'!$D:$D,0,0) -> 原请示对应标准（未明确具体金额） | S7: 100 | T7: 100 | U7: 100
A8: 5 | C8: 高文豹 | D8: 152723198909051234 | E8: 开发部 | F8: 主管 | G8: 45170 | H8: 请示审批报销 | I8: 150 | J8: 150 | K8: 200 | L8: 1000 | M8: 李波 | O8: 45149 | P8: 面试审批岗位为主管 | R8: =_xlfn.XLOOKUP(C8,'[4]20250916话费报销调整'!$B:$B,'[4]20250916话费报销调整'!$D:$D,0,0) -> 0 | S8: 150 | T8: 150 | U8: 150
A9: 6 | C9: 田海霞 | D9: =VLOOKUP(C9,[2]在职人员信息表!$F:$U,16,FALSE) -> 15272319900930152X | E9: =VLOOKUP(C9,[1]在职人员信息表!$F:$G,2,FALSE) -> 开发部 | F9: =VLOOKUP(C9,[1]在职人员信息表!$F:$H,3,FALSE) -> 专员 | G9: 43525 | H9: 请示审批报销 | I9: 200 | L9: 1000 | M9: 具文忠 | N9: 有 | O9: 43525 | R9: =_xlfn.XLOOKUP(C9,'[4]20250916话费报销调整'!$B:$B,'[4]20250916话费报销调整'!$D:$D,0,0) -> 0 | S9: 158 | T9: 158 | U9: 168.5
A10: 7 | C10: 王鸿 | D10: =VLOOKUP(C10,[2]在职人员信息表!$F:$U,16,FALSE) -> 152723198512064512 | E10: =VLOOKUP(C10,[1]在职人员信息表!$F:$G,2,FALSE) -> 开发部 | F10: =VLOOKUP(C10,[1]在职人员信息表!$F:$H,3,FALSE) -> 专员 | G10: 44378 | H10: 请示审批报销 | I10: 200 | L10: 1000 | M10: 李波 | N10: 有 | O10: 44411 | R10: =_xlfn.XLOOKUP(C10,'[4]20250916话费报销调整'!$B:$B,'[4]20250916话费报销调整'!$D:$D,0,0) -> 0 | S10: 145.2 | T10: 144.4 | U10: 176.5
A11: 8 | C11: 张雄 | D11: =VLOOKUP(C11,[2]在职人员信息表!$F:$U,16,FALSE) -> 152723199111250618 | E11: =VLOOKUP(C11,[1]在职人员信息表!$F:$G,2,FALSE) -> 采购部 | F11: =VLOOKUP(C11,[1]在职人员信息表!$F:$H,3,FALSE) -> 采购专员 | G11: 44743 | H11: 请示审批报销 | I11: 200 | J11: 200 | K11: 200 | M11: 李波 | N11: 有 | O11: 44753 | P11: 2025年6月调动，调动后有审批 | Q11: =_xlfn.XLOOKUP(C11,[3]调动人员明细表!$D:$D,[3]调动人员明细表!$F:$F,0,0) -> 44738 | R11: =_xlfn.XLOOKUP(C11,'[4]20250916话费报销调整'!$B:$B,'[4]20250916话费报销调整'!$D:$D,0,0) -> 100-150元/月
A12: 9 | C12: 周瑞峰 | D12: =VLOOKUP(C12,[2]在职人员信息表!$F:$U,16,FALSE) -> 152723198911160915 | E12: =VLOOKUP(C12,[1]在职人员信息表!$F:$G,2,FALSE) -> 采购部 | F12: =VLOOKUP(C12,[1]在职人员信息表!$F:$H,3,FALSE) -> 采购专员 | G12: 44317 | H12: 请示审批报销 | I12: 200 | J12: 200 | M12: 李波 | N12: 有 | O12: 45791 | Q12: =_xlfn.XLOOKUP(C12,[3]调动人员明细表!$D:$D,[3]调动人员明细表!$F:$F,0,0) -> 44317 | R12: =_xlfn.XLOOKUP(C12,'[4]20250916话费报销调整'!$B:$B,'[4]20250916话费报销调整'!$D:$D,0,0) -> 0
A13: 10 | C13: 白杰铭 | D13: =VLOOKUP(C13,[2]在职人员信息表!$F:$U,16,FALSE) -> 15272319921116811X | E13: =VLOOKUP(C13,[1]在职人员信息表!$F:$G,2,FALSE) -> 采购部 | F13: =VLOOKUP(C13,[1]在职人员信息表!$F:$H,3,FALSE) -> 采购专员 | G13: 44013 | H13: 请示审批报销 | I13: 200 | J13: 200 | M13: 李波 | N13: 有 | O13: 44033 | R13: =_xlfn.XLOOKUP(C13,'[4]20250916话费报销调整'!$B:$B,'[4]20250916话费报销调整'!$D:$D,0,0) -> 0
A14: 11 | C14: 武丽婷 | D14: =VLOOKUP(C14,[2]在职人员信息表!$F:$U,16,FALSE) -> 142229199307233122 | E14: =VLOOKUP(C14,[1]在职人员信息表!$F:$G,2,FALSE) -> 采购部 | F14: =VLOOKUP(C14,[1]在职人员信息表!$F:$H,3,FALSE) -> 供应商管理员 | G14: 43709 | H14: 请示审批报销 | I14: 150 | J14: 200 | K14: 200 | M14: 具文忠 | N14: 有 | O14: 43009 | R14: =_xlfn.XLOOKUP(C14,'[4]20250916话费报销调整'!$B:$B,'[4]20250916话费报销调整'!$D:$D,0,0) -> 100-150元/月
A15: 12 | C15: 鲁佩琴 | D15: =VLOOKUP(C15,[2]在职人员信息表!$F:$U,16,FALSE) -> 15272319920602092X | E15: =VLOOKUP(C15,[1]在职人员信息表!$F:$G,2,FALSE) -> 采购部 | F15: 专员 | G15: 44228 | H15: 请示审批报销 | I15: 100 | J15: 200 | K15: 200 | M15: 李波 | N15: 有 | O15: 44235 | P15: 2024年12月调动，调动后无审批 | Q15: =_xlfn.XLOOKUP(C15,[3]调动人员明细表!$D:$D,[3]调动人员明细表!$F:$F,0,0) -> 45636 | R15: =_xlfn.XLOOKUP(C15,'[4]20250916话费报销调整'!$B:$B,'[4]20250916话费报销调整'!$D:$D,0,0) -> 100-150元/月
A16: 13 | C16: 蔺昱恺 | D16: =VLOOKUP(C16,[2]在职人员信息表!$F:$U,16,FALSE) -> 152722200001226114 | E16: =VLOOKUP(C16,[1]在职人员信息表!$F:$G,2,FALSE) -> 人力行政中心 | F16: =VLOOKUP(C16,[1]在职人员信息表!$F:$H,3,FALSE) -> 专员 | G16: 45078 | H16: 请示审批报销 | I16: 200 | M16: 李波 | O16: 45230 | Q16: =_xlfn.XLOOKUP(C16,[3]调动人员明细表!$D:$D,[3]调动人员明细表!$F:$F,0,0) -> 45054 | R16: =_xlfn.XLOOKUP(C16,'[4]20250916话费报销调整'!$B:$B,'[4]20250916话费报销调整'!$D:$D,0,0) -> 0
A17: 14 | C17: 王强 | D17: =VLOOKUP(C17,[2]在职人员信息表!$F:$U,16,FALSE) -> 140224198310217811 | E17: 人力行政中心 | F17: 工程师 | G17: 44470 | H17: 请示审批报销 | I17: 150 | M17: 李波 | N17: 有 | O17: 44544 | R17: =_xlfn.XLOOKUP(C17,'[4]20250916话费报销调整'!$B:$B,'[4]20250916话费报销调整'!$D:$D,0,0) -> 0
A18: 15 | C18: 杨钰珍 | D18: =VLOOKUP(C18,[2]在职人员信息表!$F:$U,16,FALSE) -> 130426199702100328 | E18: =VLOOKUP(C18,[1]在职人员信息表!$F:$G,2,FALSE) -> 人力行政中心 | F18: =VLOOKUP(C18,[1]在职人员信息表!$F:$H,3,FALSE) -> 专员 | G18: 43647 | H18: 请示审批报销 | I18: 100 | J18: 100 | K18: 150 | M18: 具文忠 | N18: 有 | O18: 43650 | P18: 2024年4月调动，调动后无审批 | Q18: =_xlfn.XLOOKUP(C18,[3]调动人员明细表!$D:$D,[3]调动人员明细表!$F:$F,0,0) -> 45385 | R18: =_xlfn.XLOOKUP(C18,'[4]20250916话费报销调整'!$B:$B,'[4]20250916话费报销调整'!$D:$D,0,0) -> 0
A19: 16 | C19: 胡建广 | D19: =VLOOKUP(C19,[2]在职人员信息表!$F:$U,16,FALSE) -> 142625198209092110 | E19: =VLOOKUP(C19,[1]在职人员信息表!$F:$G,2,FALSE) -> 经营管理部 | F19: =VLOOKUP(C19,[1]在职人员信息表!$F:$H,3,FALSE) -> 预算员 | G19: 44835 | H19: 请示审批报销 | I19: 150 | M19: 李运成 | N19: 有 | O19: 44875 | R19: =_xlfn.XLOOKUP(C19,'[4]20250916话费报销调整'!$B:$B,'[4]20250916话费报销调整'!$D:$D,0,0) -> 0 | S19: 150 | T19: 150 | U19: 150
A20: 17 | C20: 李山山 | D20: =VLOOKUP(C20,[2]在职人员信息表!$F:$U,16,FALSE) -> 130427199006082775 | E20: =VLOOKUP(C20,[1]在职人员信息表!$F:$G,2,FALSE) -> 生产机修科 | F20: =VLOOKUP(C20,[1]在职人员信息表!$F:$H,3,FALSE) -> 专员 | G20: 44835 | H20: 请示审批报销 | I20: 150 | M20: 李波 | N20: 有 | O20: 44669 | P20: 2024年10月调动，调动后无审批 | Q20: =_xlfn.XLOOKUP(C20,[3]调动人员明细表!$D:$D,[3]调动人员明细表!$F:$F,0,0) -> 45580 | R20: =_xlfn.XLOOKUP(C20,'[4]20250916话费报销调整'!$B:$B,'[4]20250916话费报销调整'!$D:$D,0,0) -> 原请示对应标准（未明确具体金额）
A21: 18 | C21: 蔺向龙 | D21: =VLOOKUP(C21,[2]在职人员信息表!$F:$U,16,FALSE) -> 152723198703235716 | E21: =VLOOKUP(C21,[1]在职人员信息表!$F:$G,2,FALSE) -> 复垦绿化队 | F21: =VLOOKUP(C21,[1]在职人员信息表!$F:$H,3,FALSE) -> 专员 | G21: 44835 | H21: 请示审批报销 | I21: 100 | M21: 李运成 | N21: 有 | O21: 45040 | R21: =_xlfn.XLOOKUP(C21,'[4]20250916话费报销调整'!$B:$B,'[4]20250916话费报销调整'!$D:$D,0,0) -> 100元/月 | S21: 100 | T21: 100 | U21: 100
A22: 19 | C22: 白龙 | D22: =VLOOKUP(C22,[2]在职人员信息表!$F:$U,16,FALSE) -> 152723199609112415 | E22: =VLOOKUP(C22,[1]在职人员信息表!$F:$G,2,FALSE) -> 经营管理部 | F22: =VLOOKUP(C22,[1]在职人员信息表!$F:$H,3,FALSE) -> 专员 | G22: 45597 | H22: 请示审批报销 | I22: 200 | M22: 李波 | N22: 有 | O22: 45630 | P22: 2024年11月调动，调动后有审批 | Q22: =_xlfn.XLOOKUP(C22,[3]调动人员明细表!$D:$D,[3]调动人员明细表!$F:$F,0,0) -> 45608 | R22: =_xlfn.XLOOKUP(C22,'[4]20250916话费报销调整'!$B:$B,'[4]20250916话费报销调整'!$D:$D,0,0) -> 0 | S22: 175.85 | T22: 178.58 | U22: 175.12
A23: 20 | C23: 朱彦飞 | D23: =VLOOKUP(C23,[2]在职人员信息表!$F:$U,16,FALSE) -> 152723199705152118 | E23: =VLOOKUP(C23,[1]在职人员信息表!$F:$G,2,FALSE) -> 复垦绿化队 | F23: =VLOOKUP(C23,[1]在职人员信息表!$F:$H,3,FALSE) -> 专员 | G23: 44378 | H23: 请示审批报销 | I23: 200 | K23: 0 | L23: 1000 | M23: 李波 | N23: 有 | O23: 44385 | P23: 2025年8月调动，调动后建议取消 | Q23: =_xlfn.XLOOKUP(C23,[3]调动人员明细表!$D:$D,[3]调动人员明细表!$F:$F,0,0) -> 45887 | R23: =_xlfn.XLOOKUP(C23,'[4]20250916话费报销调整'!$B:$B,'[4]20250916话费报销调整'!$D:$D,0,0) -> 原请示对应标准（未明确具体金额）
A24: 21 | C24: 刘向龙 | D24: =VLOOKUP(C24,[2]在职人员信息表!$F:$U,16,FALSE) -> 152723199505197215 | E24: =VLOOKUP(C24,[1]在职人员信息表!$F:$G,2,FALSE) -> 人力行政中心 | F24: =VLOOKUP(C24,[1]在职人员信息表!$F:$H,3,FALSE) -> 司机班长 | G24: 44287 | H24: 司机限额200 | I24: 200 | M24: 司机无请示 | R24: =_xlfn.XLOOKUP(C24,'[4]20250916话费报销调整'!$B:$B,'[4]20250916话费报销调整'!$D:$D,0,0) -> 0
A25: 22 | C25: 张志光 | D25: =VLOOKUP(C25,[2]在职人员信息表!$F:$U,16,FALSE) -> 150124198403191717 | E25: =VLOOKUP(C25,[1]在职人员信息表!$F:$G,2,FALSE) -> 人力行政中心 | F25: =VLOOKUP(C25,[1]在职人员信息表!$F:$H,3,FALSE) -> 司机 | G25: 44197 | H25: 司机限额200 | I25: 200 | M25: 司机无请示 | R25: =_xlfn.XLOOKUP(C25,'[4]20250916话费报销调整'!$B:$B,'[4]20250916话费报销调整'!$D:$D,0,0) -> 0
A26: 23 | C26: 张志强 | D26: =VLOOKUP(C26,[2]在职人员信息表!$F:$U,16,FALSE) -> 152723198504262711 | E26: =VLOOKUP(C26,[1]在职人员信息表!$F:$G,2,FALSE) -> 人力行政中心 | F26: =VLOOKUP(C26,[1]在职人员信息表!$F:$H,3,FALSE) -> 司机 | G26: 44287 | H26: 司机限额200 | I26: 200 | M26: 司机无请示 | R26: =_xlfn.XLOOKUP(C26,'[4]20250916话费报销调整'!$B:$B,'[4]20250916话费报销调整'!$D:$D,0,0) -> 0
A27: 24 | C27: 乔宇飞 | D27: =VLOOKUP(C27,[2]在职人员信息表!$F:$U,16,FALSE) -> 15272319921015121x | E27: =VLOOKUP(C27,[1]在职人员信息表!$F:$G,2,FALSE) -> 人力行政中心 | F27: =VLOOKUP(C27,[1]在职人员信息表!$F:$H,3,FALSE) -> 司机 | G27: 44409 | H27: 司机限额200 | I27: 200 | M27: 司机无请示 | Q27: =_xlfn.XLOOKUP(C27,[3]调动人员明细表!$D:$D,[3]调动人员明细表!$F:$F,0,0) -> 44621 | R27: =_xlfn.XLOOKUP(C27,'[4]20250916话费报销调整'!$B:$B,'[4]20250916话费报销调整'!$D:$D,0,0) -> 0
A28: 25 | C28: 孙云慧 | D28: =VLOOKUP(C28,[2]在职人员信息表!$F:$U,16,FALSE) -> 152624198001010038 | E28: =VLOOKUP(C28,[1]在职人员信息表!$F:$G,2,FALSE) -> 人力行政中心 | F28: =VLOOKUP(C28,[1]在职人员信息表!$F:$H,3,FALSE) -> 司机 | G28: 45444 | H28: 司机限额200 | I28: 200 | M28: 司机无请示 | R28: =_xlfn.XLOOKUP(C28,'[4]20250916话费报销调整'!$B:$B,'[4]20250916话费报销调整'!$D:$D,0,0) -> 0
A29: 26 | C29: 董雪峰 | D29: =VLOOKUP(C29,[2]在职人员信息表!$F:$U,16,FALSE) -> 150221198911252033 | E29: =VLOOKUP(C29,[1]在职人员信息表!$F:$G,2,FALSE) -> 人力行政中心 | F29: =VLOOKUP(C29,[1]在职人员信息表!$F:$H,3,FALSE) -> 司机 | G29: 45627 | H29: 司机限额200 | I29: 200 | M29: 司机无请示 | P29: 2024年11月调动，调动后无审批 | Q29: =_xlfn.XLOOKUP(C29,[3]调动人员明细表!$D:$D,[3]调动人员明细表!$F:$F,0,0) -> 45603 | R29: =_xlfn.XLOOKUP(C29,'[4]20250916话费报销调整'!$B:$B,'[4]20250916话费报销调整'!$D:$D,0,0) -> 0
A30: 27 | C30: 刘彦飞 | D30: =VLOOKUP(C30,[2]在职人员信息表!$F:$U,16,FALSE) -> 152626198702282418 | E30: =VLOOKUP(C30,[1]在职人员信息表!$F:$G,2,FALSE) -> 人力行政中心 | F30: =VLOOKUP(C30,[1]在职人员信息表!$F:$H,3,FALSE) -> 司机 | G30: 45717 | H30: 司机限额200 | I30: 200 | M30: 司机无请示 | P30: 2025年2月调动，调动后无审批 | Q30: =_xlfn.XLOOKUP(C30,[3]调动人员明细表!$D:$D,[3]调动人员明细表!$F:$F,0,0) -> 45714 | R30: =_xlfn.XLOOKUP(C30,'[4]20250916话费报销调整'!$B:$B,'[4]20250916话费报销调整'!$D:$D,0,0) -> 0
A31: 28 | C31: 刘静平 | D31: =VLOOKUP(C31,[2]在职人员信息表!$F:$U,16,FALSE) -> 152723198301120916 | E31: =VLOOKUP(C31,[1]在职人员信息表!$F:$G,2,FALSE) -> 通风科 | F31: =VLOOKUP(C31,[1]在职人员信息表!$F:$H,3,FALSE) -> 瓦检班长 | G31: 45870 | H31: 2025年班组长评选结果公示 | I31: 200 | M31: 2025年优秀班组长 | N31: 有 | O31: 45874 | R31: =_xlfn.XLOOKUP(C31,'[4]20250916话费报销调整'!$B:$B,'[4]20250916话费报销调整'!$D:$D,0,0) -> 0 | S31: 39 | T31: 39.1 | U31: 39
A32: 29 | C32: 胡成义 | D32: =VLOOKUP(C32,[2]在职人员信息表!$F:$U,16,FALSE) -> 320322199007300832 | E32: =VLOOKUP(C32,[1]在职人员信息表!$F:$G,2,FALSE) -> 综采队 | F32: =VLOOKUP(C32,[1]在职人员信息表!$F:$H,3,FALSE) -> 班长 | G32: 45870 | I32: 200 | N32: 有 | O32: 45874 | Q32: =_xlfn.XLOOKUP(C32,[3]调动人员明细表!$D:$D,[3]调动人员明细表!$F:$F,0,0) -> 45400 | R32: =_xlfn.XLOOKUP(C32,'[4]20250916话费报销调整'!$B:$B,'[4]20250916话费报销调整'!$D:$D,0,0) -> 0 | AE32: =VLOOKUP(C32,[5]Sheet1!$C$1:$G$65536,5,FALSE) -> 江苏省沛县大屯镇丰乐村352号
A33: 30 | C33: 赵丙海 | D33: =VLOOKUP(C33,[2]在职人员信息表!$F:$U,16,FALSE) -> 210124197511263839 | E33: =VLOOKUP(C33,[1]在职人员信息表!$F:$G,2,FALSE) -> 安全监察科 | F33: =VLOOKUP(C33,[1]在职人员信息表!$F:$H,3,FALSE) -> 安检班长 | G33: 45870 | I33: 200 | N33: 有 | O33: 45874 | R33: =_xlfn.XLOOKUP(C33,'[4]20250916话费报销调整'!$B:$B,'[4]20250916话费报销调整'!$D:$D,0,0) -> 0 | S33: 108 | T33: 108 | U33: 108
A34: 31 | C34: 武军生 | D34: =VLOOKUP(C34,[2]在职人员信息表!$F:$U,16,FALSE) -> 640202198008240017 | E34: =VLOOKUP(C34,[1]在职人员信息表!$F:$G,2,FALSE) -> 机运队 | F34: =VLOOKUP(C34,[1]在职人员信息表!$F:$H,3,FALSE) -> 电工班副班长 | G34: 45870 | I34: 200 | N34: 有 | O34: 45874 | R34: =_xlfn.XLOOKUP(C34,'[4]20250916话费报销调整'!$B:$B,'[4]20250916话费报销调整'!$D:$D,0,0) -> 0 | S34: 129 | T34: 129 | U34: 129.1 | AE34: =VLOOKUP(C34,[5]Sheet1!$C$1:$G$65536,5,FALSE) -> 宁夏银川市
A35: 32 | C35: 贾海军 | D35: =VLOOKUP(C35,[2]在职人员信息表!$F:$U,16,FALSE) -> 14223419760416601X | E35: =VLOOKUP(C35,[1]在职人员信息表!$F:$G,2,FALSE) -> 复垦绿化队 | F35: =VLOOKUP(C35,[1]在职人员信息表!$F:$H,3,FALSE) -> 维修班长 | G35: 45870 | I35: 200 | N35: 有 | O35: 45874 | R35: =_xlfn.XLOOKUP(C35,'[4]20250916话费报销调整'!$B:$B,'[4]20250916话费报销调整'!$D:$D,0,0) -> 0 | S35: 109 | T35: 121.5 | U35: 109 | AE35: =VLOOKUP(C35,[5]Sheet1!$C$1:$G$65536,5,FALSE) -> 山西省偏关县
A36: 33 | C36: 高志军 | D36: =VLOOKUP(C36,[2]在职人员信息表!$F:$U,16,FALSE) -> 152801197406233311 | E36: =VLOOKUP(C36,[1]在职人员信息表!$F:$G,2,FALSE) -> 选煤厂 | F36: =VLOOKUP(C36,[1]在职人员信息表!$F:$H,3,FALSE) -> 电工班长 | G36: 45870 | I36: 200 | N36: 有 | O36: 45874 | R36: =_xlfn.XLOOKUP(C36,'[4]20250916话费报销调整'!$B:$B,'[4]20250916话费报销调整'!$D:$D,0,0) -> 0 | S36: 69 | T36: 69 | U36: 74.4 | AE36: =VLOOKUP(C36,[5]Sheet1!$C$1:$G$65536,5,FALSE) -> 内蒙古自治区巴彦淖尔市 临河区
A37: 34 | C37: 康保忠 | D37: =VLOOKUP(C37,[2]在职人员信息表!$F:$U,16,FALSE) -> 150102196809011555 | E37: =VLOOKUP(C37,[1]在职人员信息表!$F:$G,2,FALSE) -> 选煤厂 | F37: =VLOOKUP(C37,[1]在职人员信息表!$F:$H,3,FALSE) -> 快速装车班长 | G37: 45870 | I37: 200 | N37: 有 | O37: 45874 | R37: =_xlfn.XLOOKUP(C37,'[4]20250916话费报销调整'!$B:$B,'[4]20250916话费报销调整'!$D:$D,0,0) -> 0 | S37: 86.9 | T37: 86.9 | U37: 86.9 | AE37: =VLOOKUP(C37,[5]Sheet1!$C$1:$G$65536,5,FALSE) -> 内蒙古自治区呼和浩特市
A38: 35 | C38: 黄忠华 | D38: =VLOOKUP(C38,[2]在职人员信息表!$F:$U,16,FALSE) -> 150221199104104418 | E38: =VLOOKUP(C38,[1]在职人员信息表!$F:$G,2,FALSE) -> 生产机修科 | F38: =VLOOKUP(C38,[1]在职人员信息表!$F:$H,3,FALSE) -> 维修班长 | G38: 45870 | I38: 200 | N38: 有 | O38: 45874 | Q38: =_xlfn.XLOOKUP(C38,[3]调动人员明细表!$D:$D,[3]调动人员明细表!$F:$F,0,0) -> 45660 | R38: =_xlfn.XLOOKUP(C38,'[4]20250916话费报销调整'!$B:$B,'[4]20250916话费报销调整'!$D:$D,0,0) -> 0 | S38: 186.75 | T38: 147.6 | U38: 200
A39: 36 | C39: 李安喜 | E39: 机运队 | F39: =VLOOKUP(C39,[1]在职人员信息表!$F:$H,3,FALSE) -> 地面电工 | I39: 200
A40: 37 | C40: 杨纪仓 | E40: 综采队 | F40: =VLOOKUP(C40,[1]在职人员信息表!$F:$H,3,FALSE) -> 检修班班长 | I40: 200
A41: 38 | B41: 有任命人员 | C41: 李波 | D41: =VLOOKUP(C41,[2]在职人员信息表!$F:$U,16,FALSE) -> 130522198205272415 | E41: =VLOOKUP(C41,[2]在职人员信息表!$F:$G,2,FALSE) -> 公司领导 | F41: =VLOOKUP(C41,[2]在职人员信息表!$F:$H,3,FALSE) -> 董事长 | G41: 董事长 | H41: =VLOOKUP(C41,[2]任职汇总表!$D:$I,6,FALSE()) -> 45235 | I41: 800
A42: 39 | C42: 章杨 | D42: =VLOOKUP(C42,[2]在职人员信息表!$F:$U,16,FALSE) -> 42030019810508031X | E42: =VLOOKUP(C42,[2]在职人员信息表!$F:$G,2,FALSE) -> 公司领导 | F42: =VLOOKUP(C42,[2]在职人员信息表!$F:$H,3,FALSE) -> 总经理 | G42: 总经理级 | H42: =VLOOKUP(C42,[2]任职汇总表!$D:$I,6,FALSE()) -> 45486 | I42: 800 | S42: 552.6 | T42: 552.6 | U42: 552.8 | V42: 552.8 | W42: 552.6
A43: 40 | C43: 窦发权 | D43: =VLOOKUP(C43,[2]在职人员信息表!$F:$U,16,FALSE) -> 370902197109021292 | E43: =VLOOKUP(C43,[2]在职人员信息表!$F:$G,2,FALSE) -> 公司领导 | F43: =VLOOKUP(C43,[2]在职人员信息表!$F:$H,3,FALSE) -> 总工程师 | G43: 总经理级 | H43: =VLOOKUP(C43,[2]任职汇总表!$D:$I,6,FALSE()) -> 45181 | I43: 800 | S43: 225.3 | T43: 144 | U43: 141.84 | AE43: =VLOOKUP(C43,[5]Sheet1!$C$1:$G$65536,5,FALSE) -> 山东省泰安市高新区 | AF43: 46115 | AG43: 46119 | AH43: 537
A44: 41 | C44: 奚明 | D44: =VLOOKUP(C44,[2]在职人员信息表!$F:$U,16,FALSE) -> 21128219830626081X | E44: =VLOOKUP(C44,[2]在职人员信息表!$F:$G,2,FALSE) -> 公司领导 | F44: =VLOOKUP(C44,[2]在职人员信息表!$F:$H,3,FALSE) -> 常务副总经理 | G44: 副总级 | H44: =VLOOKUP(C44,[2]任职汇总表!$D:$I,6,FALSE()) -> 44880 | I44: 600 | AE44: =VLOOKUP(C44,[5]Sheet1!$C$1:$G$65536,5,FALSE) -> 北京市
A45: 42 | C45: 宋云飞 | D45: =VLOOKUP(C45,[2]在职人员信息表!$F:$U,16,FALSE) -> 230822198111094910 | E45: =VLOOKUP(C45,[2]在职人员信息表!$F:$G,2,FALSE) -> 公司领导 | F45: =VLOOKUP(C45,[2]在职人员信息表!$F:$H,3,FALSE) -> 副总经理 | G45: 副总级 | H45: =VLOOKUP(C45,[2]任职汇总表!$D:$I,6,FALSE()) -> 45555 | I45: 600 | AE45: =VLOOKUP(C45,[5]Sheet1!$C$1:$G$65536,5,FALSE) -> 北京
A46: 43 | C46: 周洪刚 | D46: =VLOOKUP(C46,[2]在职人员信息表!$F:$U,16,FALSE) -> 130403196411292114 | E46: =VLOOKUP(C46,[2]在职人员信息表!$F:$G,2,FALSE) -> 公司领导 | F46: =VLOOKUP(C46,[2]在职人员信息表!$F:$H,3,FALSE) -> 总经理助理兼多种经营部经理 | G46: 副总级 | H46: =VLOOKUP(C46,[2]任职汇总表!$D:$I,6,FALSE()) -> 43164 | I46: 600 | J46: 1000 | S46: 136.1 | T46: 136.1 | U46: 137.3 | AE46: =VLOOKUP(C46,[5]Sheet1!$C$1:$G$65536,5,FALSE) -> 河北省邯郸市 | AF46: 46065 | AG46: 46076 | AH46: 1157.4 | AI46: 46142 | AJ46: 46149 | AK46: 1032
A47: 44 | C47: 王震 | D47: =VLOOKUP(C47,[2]在职人员信息表!$F:$U,16,FALSE) -> 152723198509184812 | E47: =VLOOKUP(C47,[2]在职人员信息表!$F:$G,2,FALSE) -> 公司领导 | F47: =VLOOKUP(C47,[2]在职人员信息表!$F:$H,3,FALSE) -> 副总经理 | G47: 副总级 | H47: =VLOOKUP(C47,[2]任职汇总表!$D:$I,6,FALSE()) -> 44917 | I47: 600 | J47: 1000 | S47: 378.4 | T47: 376.6 | U47: 374
A48: 45 | C48: 李秦生 | D48: =VLOOKUP(C48,[2]在职人员信息表!$F:$U,16,FALSE) -> 362329198611264574 | E48: =VLOOKUP(C48,[2]在职人员信息表!$F:$G,2,FALSE) -> 公司领导 | F48: =VLOOKUP(C48,[2]在职人员信息表!$F:$H,3,FALSE) -> 副总经理兼矿长 | G48: 副总级 | H48: =VLOOKUP(C48,[2]任职汇总表!$D:$I,6,FALSE()) -> 45486 | I48: 600 | S48: 273.2 | T48: 273.9 | U48: 273.3 | AE48: =VLOOKUP(C48,[5]Sheet1!$C$1:$G$65536,5,FALSE) -> 江西上饶市余干县 | AF48: 46066 | AG48: 46075 | AH48: 2170 | AI48: 46060 | AJ48: 46079 | AK48: 3094 | AL48: 46060 | AM48: 46079 | AN48: 1657
A49: 46 | C49: 赵佳 | D49: =VLOOKUP(C49,[2]在职人员信息表!$F:$U,16,FALSE) -> 150122198401160527 | E49: =VLOOKUP(C49,[2]在职人员信息表!$F:$G,2,FALSE) -> 公司领导 | F49: =VLOOKUP(C49,[2]在职人员信息表!$F:$H,3,FALSE) -> 力量发展财务副总监兼力量煤业财务总监 | G49: 副总级 | H49: =VLOOKUP(C49,[2]任职汇总表!$D:$I,6,FALSE()) -> 45861 | I49: 600
A50: 47 | C50: 杨维海 | D50: =VLOOKUP(C50,[2]在职人员信息表!$F:$U,16,FALSE) -> 340403197510102439 | E50: =VLOOKUP(C50,[2]在职人员信息表!$F:$G,2,FALSE) -> 矿级领导 | F50: =VLOOKUP(C50,[2]在职人员信息表!$F:$H,3,FALSE) -> 副矿长 | G50: 高级经理级 | H50: =VLOOKUP(C50,[2]任职汇总表!$D:$I,6,FALSE()) -> 45642 | I50: 600 | S50: 247.9 | T50: 247.9 | U50: 247.8 | AE50: =VLOOKUP(C50,[5]Sheet1!$C$1:$G$65536,5,FALSE) -> 安徽省淮南市田家庵区 | AF50: 46064 | AG50: 46076 | AH50: 1656.55
A51: 48 | C51: 高翔 | D51: =VLOOKUP(C51,[2]在职人员信息表!$F:$U,16,FALSE) -> 14010219810504601X | E51: =VLOOKUP(C51,[2]在职人员信息表!$F:$G,2,FALSE) -> 矿级领导 | F51: =VLOOKUP(C51,[2]在职人员信息表!$F:$H,3,FALSE) -> 生产副矿长 | G51: 高级经理级 | H51: =VLOOKUP(C51,[2]任职汇总表!$D:$I,6,FALSE()) -> 45642 | I51: 600 | S51: 258.9 | T51: 258.9 | U51: 258.9 | AE51: =VLOOKUP(C51,[5]Sheet1!$C$1:$G$65536,5,FALSE) -> 山西省阳泉市立新区
A52: 49 | C52: 王荣 | D52: =VLOOKUP(C52,[2]在职人员信息表!$F:$U,16,FALSE) -> 140581198801043215 | E52: =VLOOKUP(C52,[2]在职人员信息表!$F:$G,2,FALSE) -> 矿级领导 | F52: =VLOOKUP(C52,[2]在职人员信息表!$F:$H,3,FALSE) -> 总工程师 | G52: 高级经理级 | H52: =VLOOKUP(C52,[2]任职汇总表!$D:$I,6,FALSE()) -> 45642 | I52: 600
A53: 50 | C53: 陈永清 | D53: =VLOOKUP(C53,[2]在职人员信息表!$F:$U,16,FALSE) -> 230321197809105011 | E53: =VLOOKUP(C53,[2]在职人员信息表!$F:$G,2,FALSE) -> 矿级领导 | F53: 机电科科长 | G53: 正经理级/副矿级 | H53: =VLOOKUP(C53,[2]任职汇总表!$D:$I,6,FALSE()) -> 45642 | I53: 400 | S53: 120.55 | T53: 100 | U53: 100 | AE53: =VLOOKUP(C53,[5]Sheet1!$C$1:$G$65536,5,FALSE) -> 山东威海 | AF53: 46066 | AG53: 46075 | AH53: 1306 | AI53: 46138 | AJ53: 46148 | AK53: 1555.5
A54: 51 | C54: 史红军 | D54: =VLOOKUP(C54,[2]在职人员信息表!$F:$U,16,FALSE) -> 412328197409081532 | E54: =VLOOKUP(C54,[2]在职人员信息表!$F:$G,2,FALSE) -> 选煤厂 | F54: =VLOOKUP(C54,[2]在职人员信息表!$F:$H,3,FALSE) -> 总经理助理兼选煤厂厂长 | G54: 高级经理级 | H54: =VLOOKUP(C54,[2]任职汇总表!$D:$I,6,FALSE()) -> 45286 | I54: 600 | S54: 170.9 | T54: 169.1 | U54: 169 | AE54: =VLOOKUP(C54,[5]Sheet1!$C$1:$G$65536,5,FALSE) -> 河南省永城市 | AF54: 46157 | AG54: 46167 | AH54: 3025.12
A55: 52 | C55: 谈安彬 | D55: =VLOOKUP(C55,[2]在职人员信息表!$F:$U,16,FALSE) -> 512323198105240334 | E55: =VLOOKUP(C55,[2]在职人员信息表!$F:$G,2,FALSE) -> 矿级领导 | F55: =VLOOKUP(C55,[2]在职人员信息表!$F:$H,3,FALSE) -> 地质防治水副总工程师 | G55: 正经理级/副矿级 | H55: =VLOOKUP(C55,[2]任职汇总表!$D:$I,6,FALSE()) -> 45460 | I55: 400 | S55: 199.4 | T55: 199.1 | U55: 199.9 | AE55: =VLOOKUP(C55,[5]Sheet1!$C$1:$G$65536,5,FALSE) -> 河南省登封市 | AF55: 46066 | AG55: 46075 | AH55: 1181.47
A56: 53 | C56: 李亚杰 | D56: =VLOOKUP(C56,[2]在职人员信息表!$F:$U,16,FALSE) -> 140428198808152812 | E56: =VLOOKUP(C56,[2]在职人员信息表!$F:$G,2,FALSE) -> 矿级领导 | F56: =VLOOKUP(C56,[2]在职人员信息表!$F:$H,3,FALSE) -> 安全副总工程师 | G56: 正经理级/副矿级 | H56: =VLOOKUP(C56,[2]任职汇总表!$D:$I,6,FALSE()) -> 45423 | I56: 400 | S56: 259.01 | T56: 259.01 | U56: 318.13 | AE56: =VLOOKUP(C56,[5]Sheet1!$C$1:$G$65536,5,FALSE) -> 山西省长治市长子县 | AF56: 46066 | AG56: 46075 | AH56: 1214.08
A57: 54 | C57: 付浩声 | D57: =VLOOKUP(C57,[2]在职人员信息表!$F:$U,16,FALSE) -> 370983198605021358 | E57: =VLOOKUP(C57,[2]在职人员信息表!$F:$G,2,FALSE) -> 矿级领导 | F57: =VLOOKUP(C57,[2]在职人员信息表!$F:$H,3,FALSE) -> 机电副总工程师 | G57: 正经理级/副矿级 | H57: =VLOOKUP(C57,[2]任职汇总表!$D:$I,6,FALSE()) -> 45423 | I57: 400 | S57: 315 | T57: 315 | U57: 315 | AE57: =VLOOKUP(C57,[5]Sheet1!$C$1:$G$65536,5,FALSE) -> 山东泰安肥城 | AH57: 1239.69 | AI57: 46127 | AJ57: 46138 | AK57: 1008.11
A58: 55 | C58: 张春宝 | D58: =VLOOKUP(C58,[2]在职人员信息表!$F:$U,16,FALSE) -> 152103198304015478 | E58: =VLOOKUP(C58,[2]在职人员信息表!$F:$G,2,FALSE) -> 通风科 | F58: =VLOOKUP(C58,[2]在职人员信息表!$F:$H,3,FALSE) -> 通风副总工程师 | G58: 正经理级/副矿级 | H58: =VLOOKUP(C58,[2]任职汇总表!$D:$I,6,FALSE()) -> 45597 | I58: 400 | S58: 292.05 | T58: 235.7 | U58: 262.33 | AE58: =VLOOKUP(C58,[5]Sheet1!$C$1:$G$65536,5,FALSE) -> 呼伦贝尔市扎兰屯市 | AF58: 46066 | AG58: 46075 | AH58: 2000
A59: 56 | C59: 孙启明 | D59: =VLOOKUP(C59,[2]在职人员信息表!$F:$U,16,FALSE) -> 150428198903200159 | E59: =VLOOKUP(C59,[2]在职人员信息表!$F:$G,2,FALSE) -> 综采队 | F59: =VLOOKUP(C59,[2]在职人员信息表!$F:$H,3,FALSE) -> 矿长助理兼综采队队长 | G59: 正经理级/副矿级 | H59: =VLOOKUP(C59,[2]任职汇总表!$D:$I,6,FALSE()) -> 45597 | I59: 400 | S59: 199.7 | T59: 199.98 | U59: 198 | AE59: =VLOOKUP(C59,[5]Sheet1!$C$1:$G$65536,5,FALSE) -> 鄂尔多斯市东胜区 | AF59: 46025 | AG59: 46026 | AH59: 236 | AI59: 46067 | AJ59: 46076 | AK59: 212 | AL59: 46082 | AM59: 46082 | AN59: 242 | AO59: 46102 | AP59: 46104 | AQ59: 260 | AR59: 46123 | AS59: 46125 | AT59: 293
A60: 57 | C60: 尹烈欢 | D60: =VLOOKUP(C60,[2]在职人员信息表!$F:$U,16,FALSE) -> 362321198502011059 | E60: =VLOOKUP(C60,[2]在职人员信息表!$F:$G,2,FALSE) -> 机运队 | F60: =VLOOKUP(C60,[2]在职人员信息表!$F:$H,3,FALSE) -> 矿长助理兼机运队队长 | G60: 正经理级/副矿级 | H60: =VLOOKUP(C60,[2]任职汇总表!$D:$I,6,FALSE()) -> 45698 | I60: 400 | S60: 321.1 | T60: 322.2 | U60: 322.4 | AE60: =VLOOKUP(C60,[5]Sheet1!$C$1:$G$65536,5,FALSE) -> 江西省上饶市广信区 信水滨城
A61: 58 | C61: 张磊 | D61: =VLOOKUP(C61,[2]在职人员信息表!$F:$U,16,FALSE) -> 140108198805043918 | E61: =VLOOKUP(C61,[2]在职人员信息表!$F:$G,2,FALSE) -> 选煤厂 | F61: =VLOOKUP(C61,[2]在职人员信息表!$F:$H,3,FALSE) -> 常务副厂长 | G61: 正经理级/副矿级 | H61: =VLOOKUP(C61,[2]任职汇总表!$D:$I,6,FALSE()) -> 45775 | I61: 400
A62: 59 | C62: 邬志雄 | D62: =VLOOKUP(C62,[2]在职人员信息表!$F:$U,16,FALSE) -> 152723198801254515 | E62: 矿级领导 | F62: 安全副矿长 | G62: 正经理级/副矿级 | H62: =VLOOKUP(C62,[2]任职汇总表!$D:$I,6,FALSE()) -> 45866 | I62: 400 | S62: 273 | T62: 265 | U62: 273.1
A63: 60 | C63: 赵喜龙 | D63: =VLOOKUP(C63,[2]在职人员信息表!$F:$U,16,FALSE) -> 152723198610124814 | E63: =VLOOKUP(C63,[2]在职人员信息表!$F:$G,2,FALSE) -> 通风科 | F63: =VLOOKUP(C63,[2]在职人员信息表!$F:$H,3,FALSE) -> 矿长助理 | G63: 正经理级/副矿级 | H63: =VLOOKUP(C63,[2]任职汇总表!$D:$I,6,FALSE()) -> 45866 | I63: 400
A64: 61 | C64: 周元甲 | D64: =VLOOKUP(C64,[2]在职人员信息表!$F:$U,16,FALSE) -> 152723198410215439 | E64: =VLOOKUP(C64,[2]在职人员信息表!$F:$G,2,FALSE) -> 开发部 | F64: =VLOOKUP(C64,[2]在职人员信息表!$F:$H,3,FALSE) -> 经理 | G64: 正经理级/副矿级 | H64: =VLOOKUP(C64,[2]任职汇总表!$D:$I,6,FALSE()) -> 45881 | I64: 400 | J64: 1000
A65: 62 | C65: 石岭 | D65: =VLOOKUP(C65,[2]在职人员信息表!$F:$U,16,FALSE) -> 142232198701063831 | E65: =VLOOKUP(C65,[2]在职人员信息表!$F:$G,2,FALSE) -> 采购部 | F65: =VLOOKUP(C65,[2]在职人员信息表!$F:$H,3,FALSE) -> 经理 | G65: 正经理级/副矿级 | H65: =VLOOKUP(C65,[2]任职汇总表!$D:$I,6,FALSE()) -> 45881 | I65: 400 | AE65: =VLOOKUP(C65,[5]Sheet1!$C$1:$G$65536,5,FALSE) -> 山西太原
A66: 63 | C66: 邓志伟 | D66: =VLOOKUP(C66,[2]在职人员信息表!$F:$U,16,FALSE) -> 152325198603106029 | E66: =VLOOKUP(C66,[2]在职人员信息表!$F:$G,2,FALSE) -> 人力行政中心 | F66: =VLOOKUP(C66,[2]在职人员信息表!$F:$H,3,FALSE) -> 高级主任人力资源管理师 | G66: 正经理级/副矿级 | H66: =VLOOKUP(C66,[2]任职汇总表!$D:$I,6,FALSE()) -> 45769 | I66: 400
A67: 64 | C67: 赵乐 | D67: =VLOOKUP(C67,[2]在职人员信息表!$F:$U,16,FALSE) -> 152723198802081222 | E67: =VLOOKUP(C67,[2]在职人员信息表!$F:$G,2,FALSE) -> 人力行政中心 | F67: =VLOOKUP(C67,[2]在职人员信息表!$F:$H,3,FALSE) -> 经理 | G67: 正经理级/副矿级 | H67: =VLOOKUP(C67,[2]任职汇总表!$D:$I,6,FALSE()) -> 45664 | I67: 400
A68: 65 | C68: 李金慧 | D68: =VLOOKUP(C68,[2]在职人员信息表!$F:$U,16,FALSE) -> 130828198708180269 | E68: =VLOOKUP(C68,[2]在职人员信息表!$F:$G,2,FALSE) -> 法务监察部 | F68: =VLOOKUP(C68,[2]在职人员信息表!$F:$H,3,FALSE) -> 经理 | G68: 正经理级/副矿级 | H68: =VLOOKUP(C68,[2]任职汇总表!$D:$I,6,FALSE()) -> 45145 | I68: 400 | J68: 600 | S68: 231.1 | T68: 230.7 | U68: 231.1
A69: 66 | C69: 郭贵清 | D69: =VLOOKUP(C69,[2]在职人员信息表!$F:$U,16,FALSE) -> 152102196412021212 | E69: =VLOOKUP(C69,[2]在职人员信息表!$F:$G,2,FALSE) -> 总工办 | F69: =VLOOKUP(C69,[2]在职人员信息表!$F:$H,3,FALSE) -> 总工办职员 | G69: 正经理级/副矿级 | H69: =VLOOKUP(C69,[2]任职汇总表!$D:$I,6,FALSE()) -> 44559 | I69: 400 | S69: 210.8 | T69: 211.1 | U69: 211 | AE69: =VLOOKUP(C69,[5]Sheet1!$C$1:$G$65536,5,FALSE) -> 浙江省嘉兴市 | AF69: 46066 | AG69: 46075 | AH69: 1837 | AI69: 46066 | AJ69: 46075 | AK69: 1837 | AL69: 46151 | AM69: 46161 | AN69: 1627
A70: 67 | C70: 赵衍国 | D70: =VLOOKUP(C70,[2]在职人员信息表!$F:$U,16,FALSE) -> 370922196708141318 | E70: =VLOOKUP(C70,[2]在职人员信息表!$F:$G,2,FALSE) -> 总工办 | F70: =VLOOKUP(C70,[2]在职人员信息表!$F:$H,3,FALSE) -> 总工办职员 | G70: 正经理级/副矿级 | H70: =VLOOKUP(C70,[2]任职汇总表!$D:$I,6,FALSE()) -> 43556 | I70: 400 | S70: 220.3 | T70: 224.2 | U70: 221.6 | AE70: =VLOOKUP(C70,[5]Sheet1!$C$1:$G$65536,5,FALSE) -> 山东省烟台市莱山区 | AF70: 46115 | AG70: 46121 | AH70: 1400 | AI70: 46143 | AJ70: 46147 | AK70: 1400
A71: 68 | C71: 吴运标 | D71: =VLOOKUP(C71,[2]在职人员信息表!$F:$U,16,FALSE) -> 340621197702275610 | E71: =VLOOKUP(C71,[2]在职人员信息表!$F:$G,2,FALSE) -> 总工办 | F71: =VLOOKUP(C71,[2]在职人员信息表!$F:$H,3,FALSE) -> 总工办职员 | G71: 正经理级/副矿级 | H71: =VLOOKUP(C71,[2]任职汇总表!$D:$I,6,FALSE()) -> 45289 | I71: 400 | S71: 206.28 | T71: 170.75 | U71: 159.54 | AE71: =VLOOKUP(C71,[5]Sheet1!$C$1:$G$65536,5,FALSE) -> 四川省达州市 | AF71: 46065 | AG71: 46076 | AH71: 1281.5 | AI71: 46139 | AJ71: 46150 | AK71: 1055
A72: 69 | C72: 白新江 | D72: =VLOOKUP(C72,[2]在职人员信息表!$F:$U,16,FALSE) -> 140224198001280630 | E72: =VLOOKUP(C72,[2]在职人员信息表!$F:$G,2,FALSE) -> 总工办 | F72: =VLOOKUP(C72,[2]在职人员信息表!$F:$H,3,FALSE) -> 总工办主任 | G72: 正经理级/副矿级 | H72: =VLOOKUP(C72,[2]任职汇总表!$D:$I,6,FALSE()) -> 45630 | I72: 400 | S72: 213 | T72: 213 | U72: 213.3
A73: 70 | C73: 刘栓柱 | D73: =VLOOKUP(C73,[2]在职人员信息表!$F:$U,16,FALSE) -> 130521197011257013 | E73: =VLOOKUP(C73,[2]在职人员信息表!$F:$G,2,FALSE) -> 总工办 | F73: =VLOOKUP(C73,[2]在职人员信息表!$F:$H,3,FALSE) -> 总工办职员 | G73: 正经理级/副矿级 | H73: =VLOOKUP(C73,[2]任职汇总表!$D:$I,6,FALSE()) -> 45630 | I73: 400 | S73: 183.1 | T73: 102.4 | U73: 117.1 | AE73: =VLOOKUP(C73,[5]Sheet1!$C$1:$G$65536,5,FALSE) -> 河北邢台市 | AF73: 46138 | AG73: 46137 | AH73: 780 | AI73: 46181 | AJ73: 46190 | AK73: 780
A74: 71 | C74: 郝春红 | D74: =VLOOKUP(C74,[2]在职人员信息表!$F:$U,16,FALSE) -> 231026198311142342 | E74: =VLOOKUP(C74,[2]在职人员信息表!$F:$G,2,FALSE) -> 经营管理部 | F74: =VLOOKUP(C74,[2]在职人员信息表!$F:$H,3,FALSE) -> 经理 | G74: 正经理级/副矿级 | H74: =VLOOKUP(C74,[2]任职汇总表!$D:$I,6,FALSE()) -> 45505 | I74: 400 | S74: 156.65 | T74: 144 | U74: 205.9 | AE74: =VLOOKUP(C74,[5]Sheet1!$C$1:$G$65536,5,FALSE) -> 黑龙江省鸡西市
A75: 72 | C75: 刘忠勋 | E75: 矿级领导 | F75: 副总工程师 | G75: 正经理级/副矿级 | I75: 400 | AE75: =VLOOKUP(C75,[5]Sheet1!$C$1:$G$65536,5,FALSE) -> 山东青岛
A76: 73 | C76: 张广振 | D76: =VLOOKUP(C76,[2]在职人员信息表!$F:$U,16,FALSE) -> 370881198111304835 | E76: =VLOOKUP(C76,[2]在职人员信息表!$F:$G,2,FALSE) -> 综采队 | F76: =VLOOKUP(C76,[2]在职人员信息表!$F:$H,3,FALSE) -> 常务副队长 | G76: 副经理级/正科级 | H76: =VLOOKUP(C76,[2]任职汇总表!$D:$I,6,FALSE()) -> 45090 | I76: 300 | S76: 131 | T76: 131.26 | U76: 131.1 | AE76: =VLOOKUP(C76,[5]Sheet1!$C$1:$G$65536,5,FALSE) -> 山东省济宁市兖州区 | AF76: 46106 | AG76: 46117 | AH76: 1288 | AI76: 46140 | AJ76: 46148 | AK76: 1088.5 | AL76: 46148 | AM76: 46154 | AN76: 2267.5 | AO76: 46181 | AP76: 46185 | AQ76: 1395
A77: 74 | C77: 荣启亭 | D77: =VLOOKUP(C77,[2]在职人员信息表!$F:$U,16,FALSE) -> 370983198101161832 | E77: =VLOOKUP(C77,[2]在职人员信息表!$F:$G,2,FALSE) -> 综掘队 | F77: =VLOOKUP(C77,[2]在职人员信息表!$F:$H,3,FALSE) -> 队长 | G77: 副经理级/正科级 | H77: =VLOOKUP(C77,[2]任职汇总表!$D:$I,6,FALSE()) -> 45866 | I77: 300 | S77: 295.45 | T77: 295.2 | U77: 300 | AE77: =VLOOKUP(C77,[5]Sheet1!$C$1:$G$65536,5,FALSE) -> 山东省肥城市湖屯镇小店村194号
A78: 75 | C78: 贺伟 | D78: =VLOOKUP(C78,[2]在职人员信息表!$F:$U,16,FALSE) -> 15272319861209601X | E78: =VLOOKUP(C78,[2]在职人员信息表!$F:$G,2,FALSE) -> 安全监察科 | F78: =VLOOKUP(C78,[2]在职人员信息表!$F:$H,3,FALSE) -> 科长 | G78: 副经理级/正科级 | H78: =VLOOKUP(C78,[2]任职汇总表!$D:$I,6,FALSE()) -> 45145 | I78: 300 | S78: 125.65 | T78: 300 | U78: 300
A79: 76 | C79: 王亮勋 | D79: =VLOOKUP(C79,[2]在职人员信息表!$F:$U,16,FALSE) -> 410622197402106035 | E79: =VLOOKUP(C79,[2]在职人员信息表!$F:$G,2,FALSE) -> 选煤厂 | F79: =VLOOKUP(C79,[2]在职人员信息表!$F:$H,3,FALSE) -> 安全副厂长 | G79: 副经理级/正科级 | H79: =VLOOKUP(C79,[2]任职汇总表!$D:$I,6,FALSE()) -> 44210 | I79: 300 | S79: 214.15 | T79: 199 | U79: 199.1
A80: 77 | C80: 任建龙 | D80: =VLOOKUP(C80,[2]在职人员信息表!$F:$U,16,FALSE) -> 152723198804241517 | E80: =VLOOKUP(C80,[2]在职人员信息表!$F:$G,2,FALSE) -> 总调度室 | F80: =VLOOKUP(C80,[2]在职人员信息表!$F:$H,3,FALSE) -> 主任 | G80: 副经理级/正科级 | H80: =VLOOKUP(C80,[2]任职汇总表!$D:$I,6,FALSE()) -> 45866 | I80: 300 | S80: 263.09 | T80: 144 | U80: 123.84
A81: 78 | C81: 陈建军 | D81: =VLOOKUP(C81,[2]在职人员信息表!$F:$U,16,FALSE) -> 410107196310270510 | E81: =VLOOKUP(C81,[2]在职人员信息表!$F:$G,2,FALSE) -> 机电科 | F81: =VLOOKUP(C81,[2]在职人员信息表!$F:$H,3,FALSE) -> 工程师 | G81: 副经理级/正科级 | H81: =VLOOKUP(C81,[2]任职汇总表!$D:$I,6,FALSE()) -> 44608 | I81: 300
A82: 79 | C82: 柴方柱 | D82: =VLOOKUP(C82,[2]在职人员信息表!$F:$U,16,FALSE) -> 220603197809090333 | E82: =VLOOKUP(C82,[2]在职人员信息表!$F:$G,2,FALSE) -> 机电科 | F82: =VLOOKUP(C82,[2]在职人员信息表!$F:$H,3,FALSE) -> 科长 | G82: 副经理级/正科级 | H82: =VLOOKUP(C82,[2]任职汇总表!$D:$I,6,FALSE()) -> 45229 | I82: 300
A83: 80 | C83: 徐振炎 | D83: =VLOOKUP(C83,[2]在职人员信息表!$F:$U,16,FALSE) -> 370826198807295151 | E83: =VLOOKUP(C83,[2]在职人员信息表!$F:$G,2,FALSE) -> 生产机修科 | F83: =VLOOKUP(C83,[2]在职人员信息表!$F:$H,3,FALSE) -> 科长 | G83: 副经理级/正科级 | H83: =VLOOKUP(C83,[2]任职汇总表!$D:$I,6,FALSE()) -> 45664 | I83: 300 | S83: 219 | T83: 219.7 | U83: 219.4 | AE83: =VLOOKUP(C83,[5]Sheet1!$C$1:$G$65536,5,FALSE) -> 山东省济宁市
A84: 81 | C84: 赵国锋 | D84: =VLOOKUP(C84,[2]在职人员信息表!$F:$U,16,FALSE) -> 370922196506096950 | E84: =VLOOKUP(C84,[2]在职人员信息表!$F:$G,2,FALSE) -> 生产机修科 | F84: =VLOOKUP(C84,[2]在职人员信息表!$F:$H,3,FALSE) -> 工程师 | G84: 副经理级/正科级 | H84: =VLOOKUP(C84,[2]任职汇总表!$D:$I,6,FALSE()) -> 44608 | I84: 300 | S84: 79.5 | T84: 80.9 | U84: 76.9 | AE84: =VLOOKUP(C84,[5]Sheet1!$C$1:$G$65536,5,FALSE) -> 山东省泰安市岱岳区 | AF84: 46116 | AG84: 46126 | AH84: 1126
A85: 82 | C85: 郝佳 | D85: =VLOOKUP(C85,[2]在职人员信息表!$F:$U,16,FALSE) -> 152723198207184526 | E85: =VLOOKUP(C85,[2]在职人员信息表!$F:$G,2,FALSE) -> 财务部 | F85: =VLOOKUP(C85,[2]在职人员信息表!$F:$H,3,FALSE) -> 财务副经理 | G85: 副经理级/正科级 | H85: =VLOOKUP(C85,[2]任职汇总表!$D:$I,6,FALSE()) -> 45052 | I85: 300
A86: 83 | C86: 李善君 | D86: =VLOOKUP(C86,[2]在职人员信息表!$F:$U,16,FALSE) -> 152127198212082121 | E86: =VLOOKUP(C86,[2]在职人员信息表!$F:$G,2,FALSE) -> 采购部 | F86: =VLOOKUP(C86,[2]在职人员信息表!$F:$H,3,FALSE) -> 副经理 | G86: 副经理级/正科级 | H86: =VLOOKUP(C86,[2]任职汇总表!$D:$I,6,FALSE()) -> 45532 | I86: 300 | AE86: =VLOOKUP(C86,[5]Sheet1!$C$1:$G$65536,5,FALSE) -> 呼和浩特
A87: 84 | C87: 杨皓鸣 | D87: =VLOOKUP(C87,[2]在职人员信息表!$F:$U,16,FALSE) -> 152723199206140331 | E87: =VLOOKUP(C87,[2]在职人员信息表!$F:$G,2,FALSE) -> 人力行政中心 | F87: =VLOOKUP(C87,[2]在职人员信息表!$F:$H,3,FALSE) -> 副经理 | G87: 副经理级/正科级 | H87: =VLOOKUP(C87,[2]任职汇总表!$D:$I,6,FALSE()) -> 45145 | I87: 300
A88: 85 | C88: 乔玮 | D88: =VLOOKUP(C88,[2]在职人员信息表!$F:$U,16,FALSE) -> 152723198409151829 | E88: =VLOOKUP(C88,[2]在职人员信息表!$F:$G,2,FALSE) -> 人力行政中心 | F88: =VLOOKUP(C88,[2]在职人员信息表!$F:$H,3,FALSE) -> 副经理 | G88: 副经理级/正科级 | H88: =VLOOKUP(C88,[2]任职汇总表!$D:$I,6,FALSE()) -> 45145 | I88: 300
A89: 86 | C89: 刘梦佳 | D89: =VLOOKUP(C89,[2]在职人员信息表!$F:$U,16,FALSE) -> 152723199109141826 | E89: =VLOOKUP(C89,[2]在职人员信息表!$F:$G,2,FALSE) -> 总工办 | F89: =VLOOKUP(C89,[2]在职人员信息表!$F:$H,3,FALSE) -> 副主任 | G89: 副经理级/正科级 | H89: =VLOOKUP(C89,[2]任职汇总表!$D:$I,6,FALSE()) -> 45145 | I89: 300 | S89: 127 | T89: 127 | U89: 166.8
A90: 87 | C90: 张启鹏 | D90: =VLOOKUP(C90,[2]在职人员信息表!$F:$U,16,FALSE) -> 152723198104171810 | E90: =VLOOKUP(C90,[2]在职人员信息表!$F:$G,2,FALSE) -> 多种经营部-多经 | F90: =VLOOKUP(C90,[2]在职人员信息表!$F:$H,3,FALSE) -> 副经理 | G90: 副经理级/正科级 | H90: =VLOOKUP(C90,[2]任职汇总表!$D:$I,6,FALSE()) -> 44202 | I90: 300 | S90: 300 | T90: 292 | U90: 300
A91: 88 | C91: 王海军 | D91: 152723198009280912 | E91: 复垦绿化队 | F91: 队长 | G91: 副经理级/正科级 | H91: =VLOOKUP(C91,[2]任职汇总表!$D:$I,6,FALSE()) -> 43164 | I91: 300 | S91: 300 | T91: 300 | U91: 300
A92: 89 | C92: 李徐强 | E92: 选煤厂 | F92: 副厂长 | G92: 副经理级/正科级 | I92: 300 | T92: 224 | U92: 224
A93: 90 | C93: 杨培 | D93: =VLOOKUP(C93,[2]在职人员信息表!$F:$U,16,FALSE) -> 152723198612071517 | E93: =VLOOKUP(C93,[2]在职人员信息表!$F:$G,2,FALSE) -> 综采队 | F93: =VLOOKUP(C93,[2]在职人员信息表!$F:$H,3,FALSE) -> 副队长 | G93: 副科级/经理助理/主管 | H93: =VLOOKUP(C93,[2]任职汇总表!$D:$I,6,FALSE()) -> 44958 | I93: 200 | S93: 132.4 | T93: 164.1 | U93: 131
A94: 91 | C94: 商好学 | D94: =VLOOKUP(C94,[2]在职人员信息表!$F:$U,16,FALSE) -> 370826197111153732 | E94: =VLOOKUP(C94,[2]在职人员信息表!$F:$G,2,FALSE) -> 综采队 | F94: =VLOOKUP(C94,[2]在职人员信息表!$F:$H,3,FALSE) -> 副队长 | G94: 副科级/经理助理/主管 | H94: =VLOOKUP(C94,[2]任职汇总表!$D:$I,6,FALSE()) -> 44958 | I94: 200 | S94: 149.2 | T94: 149 | U94: 149.1 | AE94: =VLOOKUP(C94,[5]Sheet1!$C$1:$G$65536,5,FALSE) -> 山东省济宁市微山县 | AF94: 46140 | AG94: 46148 | AH94: 1000
A95: 92 | C95: 杨肖 | D95: =VLOOKUP(C95,[2]在职人员信息表!$F:$U,16,FALSE) -> 320322198908010811 | E95: 财务部 | F95: 副经理 | G95: 副经理级/正科级 | I95: 200 | K95: 调动单 | AE95: =VLOOKUP(C95,[5]Sheet1!$C$1:$G$65536,5,FALSE) -> 江苏省徐州市沛县 | AF95: 46067 | AG95: 46075 | AH95: 1271 | AI95: 46143 | AJ95: 46150 | AK95: 1400
A96: 93 | C96: 尹树山 | D96: =VLOOKUP(C96,[2]在职人员信息表!$F:$U,16,FALSE) -> 130227197307093611 | E96: =VLOOKUP(C96,[2]在职人员信息表!$F:$G,2,FALSE) -> 综采队 | F96: =VLOOKUP(C96,[2]在职人员信息表!$F:$H,3,FALSE) -> 副队长 | G96: 副科级/经理助理/主管 | H96: =VLOOKUP(C96,[2]任职汇总表!$D:$I,6,FALSE()) -> 44958 | I96: 200 | S96: 199 | T96: 199 | U96: 199 | AE96: =VLOOKUP(C96,[5]Sheet1!$C$1:$G$65536,5,FALSE) -> 河北省唐山市迁西县罗屯镇长岭丰村
A97: 94 | C97: 张坤 | D97: =VLOOKUP(C97,[2]在职人员信息表!$F:$U,16,FALSE) -> 211404198108276230 | E97: =VLOOKUP(C97,[2]在职人员信息表!$F:$G,2,FALSE) -> 综采队 | F97: =VLOOKUP(C97,[2]在职人员信息表!$F:$H,3,FALSE) -> 副队长 | G97: 副科级/经理助理/主管 | H97: =VLOOKUP(C97,[2]任职汇总表!$D:$I,6,FALSE()) -> 44958 | I97: 200 | S97: 140.9 | T97: 140.9 | U97: 140.9 | AE97: =VLOOKUP(C97,[5]Sheet1!$C$1:$G$65536,5,FALSE) -> 辽宁省葫芦岛市
A98: 95 | C98: 索爱军 | D98: =VLOOKUP(C98,[2]在职人员信息表!$F:$U,16,FALSE) -> 130406198501023012 | E98: =VLOOKUP(C98,[2]在职人员信息表!$F:$G,2,FALSE) -> 综掘队 | F98: =VLOOKUP(C98,[2]在职人员信息表!$F:$H,3,FALSE) -> 副队长 | G98: 副科级/经理助理/主管 | H98: =VLOOKUP(C98,[2]任职汇总表!$D:$I,6,FALSE()) -> 44964 | I98: 200 | S98: 200 | T98: 15 | U98: 200 | AE98: =VLOOKUP(C98,[5]Sheet1!$C$1:$G$65536,5,FALSE) -> 河北省邯郸市峰峰矿区界城镇苏一村4队16号 | AF98: 46023 | AG98: 46031 | AH98: 1000 | AI98: 46066 | AJ98: 46076 | AK98: 838
A99: 96 | C99: 刘凤山 | D99: =VLOOKUP(C99,[2]在职人员信息表!$F:$U,16,FALSE) -> 150429197812103435 | E99: =VLOOKUP(C99,[2]在职人员信息表!$F:$G,2,FALSE) -> 综掘队 | F99: =VLOOKUP(C99,[2]在职人员信息表!$F:$H,3,FALSE) -> 副队长 | G99: 副科级/经理助理/主管 | H99: =VLOOKUP(C99,[2]任职汇总表!$D:$I,6,FALSE()) -> 44964 | I99: 200 | S99: 168 | T99: 168.4 | U99: 168 | AE99: =VLOOKUP(C99,[5]Sheet1!$C$1:$G$65536,5,FALSE) -> 内蒙古赤峰市宁城县三座店镇小塘土沟村7组 | AF99: 46079 | AG99: 46089 | AH99: 1000
A100: 97 | C100: 索爱国 | D100: =VLOOKUP(C100,[2]在职人员信息表!$F:$U,16,FALSE) -> 130406197709293017 | E100: =VLOOKUP(C100,[2]在职人员信息表!$F:$G,2,FALSE) -> 综掘队 | F100: =VLOOKUP(C100,[2]在职人员信息表!$F:$H,3,FALSE) -> 副队长 | G100: 副科级/经理助理/主管 | H100: =VLOOKUP(C100,[2]任职汇总表!$D:$I,6,FALSE()) -> 45881 | I100: 200 | AE100: =VLOOKUP(C100,[5]Sheet1!$C$1:$G$65536,5,FALSE) -> 河北省邯郸市峰峰矿区界城镇苏一村4队16号
...

Sheet Sheet1
A1: 内蒙古准格尔旗力量煤业有限公司人员2025年员工福利档案
A2: 序号 | B2: 姓名 | C2: 工作部门 | D2: 岗位 | E2: 级别 | F2: 任职日期 | G2: 话费报销标准 | H2: 燃油标准 | I2: 电话费 | W2: 探亲地 | X2: 第一次探亲 | AA2: 第二次探亲 | AD2: 第三次探亲 | AG2: 第四次探亲 | AJ2: 第五次探亲 | AM2: 第六次探亲 | AP2: 探亲费 总金额 | AQ2: 报销合计 金额 | AR2: 备案日期 | AS2: 经办人 | AT2: 备注
I3: 1月 | J3: 2月 | K3: 3月 | L3: 4月 | M3: 5月 | N3: 6月 | O3: 7月 | P3: 8月 | Q3: 9月 | R3: 10月 | S3: 11月 | T3: 12月 | U3: 13月 | V3: 14月 | X3: 开始时间 | Y3: 结束时间 | Z3: 金额 | AA3: 开始时间 | AB3: 结束时间 | AC3: 金额 | AD3: 开始时间 | AE3: 结束时间 | AF3: 金额 | AG3: 开始时间 | AH3: 结束时间 | AI3: 金额 | AJ3: 开始时间 | AK3: 结束时间 | AL3: 金额 | AM3: 开始时间 | AN3: 结束时间 | AO3: 金额
A4: 1 | B4: 李波 | C4: =VLOOKUP(B4,[2]在职人员信息表!$F:$G,2,FALSE) -> 公司领导 | D4: =VLOOKUP(B4,[2]在职人员信息表!$F:$H,3,FALSE) -> 董事长 | E4: 董事长 | F4: =VLOOKUP(B4,[2]任职汇总表!$D:$I,6,FALSE()) -> 45235
A5: 2 | B5: 章杨 | C5: =VLOOKUP(B5,[2]在职人员信息表!$F:$G,2,FALSE) -> 公司领导 | D5: =VLOOKUP(B5,[2]在职人员信息表!$F:$H,3,FALSE) -> 总经理 | E5: 总经理级 | F5: =VLOOKUP(B5,[2]任职汇总表!$D:$I,6,FALSE()) -> 45486 | I5: 792.12 | J5: 800 | K5: 542.2 | L5: 542.4 | M5: 543.1 | N5: 555.4 | O5: 560.5 | X5: 45703 | Y5: 45705 | Z5: 485 | AA5: 45727 | AB5: 45730 | AC5: 406 | AD5: 45750 | AE5: 45753 | AF5: 430 | AG5: 45777 | AH5: 45785 | AI5: 533
A6: 3 | B6: 奚明 | C6: =VLOOKUP(B6,[2]在职人员信息表!$F:$G,2,FALSE) -> 公司领导 | D6: =VLOOKUP(B6,[2]在职人员信息表!$F:$H,3,FALSE) -> 常务副总经理 | E6: 副总级 | F6: =VLOOKUP(B6,[2]任职汇总表!$D:$I,6,FALSE()) -> 44880 | I6: 248 | J6: 248.1 | K6: 248.1 | L6: 248 | M6: 248 | N6: 248
A7: 4 | B7: 窦发权 | C7: =VLOOKUP(B7,[2]在职人员信息表!$F:$G,2,FALSE) -> 公司领导 | D7: =VLOOKUP(B7,[2]在职人员信息表!$F:$H,3,FALSE) -> 总工程师 | E7: 总经理级 | F7: =VLOOKUP(B7,[2]任职汇总表!$D:$I,6,FALSE()) -> 45181 | I7: 131.78 | J7: 139.5 | K7: 144.5 | L7: 244.2 | M7: 454 | N7: 144.2 | W7: 山东泰安 | X7: 45805 | Y7: 45813 | Z7: 1246.47
A8: 5 | B8: 宋云飞 | C8: =VLOOKUP(B8,[2]在职人员信息表!$F:$G,2,FALSE) -> 公司领导 | D8: =VLOOKUP(B8,[2]在职人员信息表!$F:$H,3,FALSE) -> 副总经理 | E8: 副总级 | F8: =VLOOKUP(B8,[2]任职汇总表!$D:$I,6,FALSE()) -> 45555 | I8: 289.9 | J8: 310.9 | K8: 281 | W8: =VLOOKUP(B8,Sheet1!$B$4:$B$95,5,FALSE) -> #REF!
A9: 6 | B9: 周洪刚 | C9: =VLOOKUP(B9,[2]在职人员信息表!$F:$G,2,FALSE) -> 公司领导 | D9: =VLOOKUP(B9,[2]在职人员信息表!$F:$H,3,FALSE) -> 总经理助理兼多种经营部经理 | E9: 副总级 | F9: =VLOOKUP(B9,[2]任职汇总表!$D:$I,6,FALSE()) -> 43164 | H9: 1000 | I9: 138.7 | J9: 138.7 | K9: 138 | W9: =VLOOKUP(B9,Sheet1!$B$4:$B$95,5,FALSE) -> #REF! | X9: 45682 | Y9: 45692 | Z9: 1226.89 | AA9: 45743 | AB9: 45753 | AC9: 1146.81 | AD9: 45773 | AE9: 45799 | AF9: 677
A10: 7 | B10: 王震 | C10: =VLOOKUP(B10,[2]在职人员信息表!$F:$G,2,FALSE) -> 公司领导 | D10: =VLOOKUP(B10,[2]在职人员信息表!$F:$H,3,FALSE) -> 副总经理 | E10: 副总级 | F10: =VLOOKUP(B10,[2]任职汇总表!$D:$I,6,FALSE()) -> 44917 | H10: 1000 | I10: 306.7 | J10: 306.51 | K10: 309.2 | L10: 297.2 | M10: 305.8 | N10: 295.9
A11: 8 | B11: 李秦生 | C11: =VLOOKUP(B11,[2]在职人员信息表!$F:$G,2,FALSE) -> 公司领导 | D11: =VLOOKUP(B11,[2]在职人员信息表!$F:$H,3,FALSE) -> 副总经理兼矿长 | E11: 副总级 | F11: =VLOOKUP(B11,[2]任职汇总表!$D:$I,6,FALSE()) -> 45486 | I11: 386.3 | J11: 386.2 | K11: 387.2 | L11: 386.8 | M11: 386.2 | N11: 386.7 | W11: =VLOOKUP(B11,Sheet1!$B$4:$B$95,5,FALSE) -> #REF! | X11: 45684 | Y11: 45692 | Z11: 2599 | AA11: 45680 | AB11: 45702 | AC11: 2967.33 | AD11: 45680 | AE11: 45702 | AF11: 1656.67
A12: 9 | B12: 赵佳 | C12: =VLOOKUP(B12,[2]在职人员信息表!$F:$G,2,FALSE) -> 公司领导 | D12: =VLOOKUP(B12,[2]在职人员信息表!$F:$H,3,FALSE) -> 力量发展财务副总监兼力量煤业财务总监 | E12: 副总级 | F12: =VLOOKUP(B12,[2]任职汇总表!$D:$I,6,FALSE()) -> 45861
A13: 10 | B13: 杨维海 | C13: =VLOOKUP(B13,[2]在职人员信息表!$F:$G,2,FALSE) -> 矿级领导 | D13: =VLOOKUP(B13,[2]在职人员信息表!$F:$H,3,FALSE) -> 副矿长 | E13: 高级经理级 | F13: =VLOOKUP(B13,[2]任职汇总表!$D:$I,6,FALSE()) -> 45642 | I13: 178.4 | J13: 178.5 | K13: 218.4 | L13: 188.4 | M13: 148.8 | N13: 148.4 | W13: =VLOOKUP(B13,Sheet1!$B$4:$B$95,5,FALSE) -> #REF! | X13: 45787 | Y13: 45797 | Z13: 2246.56
A14: 11 | B14: 高翔 | C14: =VLOOKUP(B14,[2]在职人员信息表!$F:$G,2,FALSE) -> 矿级领导 | D14: =VLOOKUP(B14,[2]在职人员信息表!$F:$H,3,FALSE) -> 生产副矿长 | E14: 高级经理级 | F14: =VLOOKUP(B14,[2]任职汇总表!$D:$I,6,FALSE()) -> 45642 | I14: 280 | J14: 280 | K14: 270 | W14: =VLOOKUP(B14,Sheet1!$B$4:$B$95,5,FALSE) -> #REF! | X14: 45658 | Y14: 45668 | Z14: 1024.99 | AA14: 45699 | AB14: 45708 | AC14: 1052.52 | AD14: 45814 | AE14: 45825 | AF14: 549.35
A15: 12 | B15: 王荣 | C15: =VLOOKUP(B15,[2]在职人员信息表!$F:$G,2,FALSE) -> 矿级领导 | D15: =VLOOKUP(B15,[2]在职人员信息表!$F:$H,3,FALSE) -> 总工程师 | E15: 高级经理级 | F15: =VLOOKUP(B15,[2]任职汇总表!$D:$I,6,FALSE()) -> 45642 | I15: 450.1 | J15: 480.3 | K15: 600 | L15: 485 | M15: 600 | N15: 582.24 | W15: =VLOOKUP(B15,Sheet1!$B$4:$B$95,5,FALSE) -> #REF! | X15: 45684 | Y15: 45692 | Z15: 1516.83 | AA15: 45801 | AB15: 45811 | AC15: 1346.66
A16: 13 | B16: 陈永清 | C16: =VLOOKUP(B16,[2]在职人员信息表!$F:$G,2,FALSE) -> 矿级领导 | D16: =VLOOKUP(B16,[2]在职人员信息表!$F:$H,3,FALSE) -> 机电副矿长 | E16: 高级经理级 | F16: =VLOOKUP(B16,[2]任职汇总表!$D:$I,6,FALSE()) -> 45642 | I16: 100 | J16: 100 | K16: 100 | W16: =VLOOKUP(B16,Sheet1!$B$4:$B$95,5,FALSE) -> #REF! | X16: 45658 | Y16: 45668 | Z16: 1296 | AA16: 45697 | AB16: 45707 | AC16: 1270 | AD16: 45794 | AE16: 45804 | AF16: 1403.5
A17: 14 | B17: 谈安彬 | C17: =VLOOKUP(B17,[2]在职人员信息表!$F:$G,2,FALSE) -> 矿级领导 | D17: =VLOOKUP(B17,[2]在职人员信息表!$F:$H,3,FALSE) -> 地质防治水副总工程师 | E17: 正经理级/副矿级 | F17: =VLOOKUP(B17,[2]任职汇总表!$D:$I,6,FALSE()) -> 45460 | I17: 169.6 | J17: 169.9 | K17: 169.2 | L17: 169.4 | M17: 169.2 | N17: 169.1 | W17: =VLOOKUP(B17,Sheet1!$B$4:$B$95,5,FALSE) -> #REF! | X17: 45684 | Y17: 45692 | Z17: 1356.05 | AA17: 45815 | AB17: 45825 | AC17: 1374.05
A18: 15 | B18: 李亚杰 | C18: =VLOOKUP(B18,[2]在职人员信息表!$F:$G,2,FALSE) -> 矿级领导 | D18: =VLOOKUP(B18,[2]在职人员信息表!$F:$H,3,FALSE) -> 安全副总工程师 | E18: 正经理级/副矿级 | F18: =VLOOKUP(B18,[2]任职汇总表!$D:$I,6,FALSE()) -> 45423 | I18: 234.51 | J18: 234.71 | K18: 234.61 | L18: 259.01 | M18: 347.11 | N18: 259.11 | W18: =VLOOKUP(B18,Sheet1!$B$4:$B$95,5,FALSE) -> #REF! | X18: 45766 | Y18: 45776 | Z18: 1383.16
A19: 16 | B19: 付浩声 | C19: =VLOOKUP(B19,[2]在职人员信息表!$F:$G,2,FALSE) -> 矿级领导 | D19: =VLOOKUP(B19,[2]在职人员信息表!$F:$H,3,FALSE) -> 机电副总工程师 | E19: 正经理级/副矿级 | F19: =VLOOKUP(B19,[2]任职汇总表!$D:$I,6,FALSE()) -> 45423 | I19: 180.2 | J19: 180 | K19: 180.2 | W19: =VLOOKUP(B19,Sheet1!$B$4:$B$95,5,FALSE) -> #REF! | X19: 45682 | Y19: 45690 | Z19: 1239 | AA19: 45837 | AB19: 45847 | AC19: 1328.88
A20: 17 | B20: 张春宝 | C20: =VLOOKUP(B20,[2]在职人员信息表!$F:$G,2,FALSE) -> 通风科 | D20: =VLOOKUP(B20,[2]在职人员信息表!$F:$H,3,FALSE) -> 通风副总工程师 | E20: 正经理级/副矿级 | F20: =VLOOKUP(B20,[2]任职汇总表!$D:$I,6,FALSE()) -> 45597 | I20: 381.6 | J20: 374.08 | K20: 347.75 | L20: 307.9 | M20: 306.28 | N20: 295.61 | W20: =VLOOKUP(B20,Sheet1!$B$4:$B$95,5,FALSE) -> #REF! | X20: 45807 | Y20: 45817 | Z20: 1730
A21: 18 | B21: 孙启明 | C21: =VLOOKUP(B21,[2]在职人员信息表!$F:$G,2,FALSE) -> 综采队 | D21: =VLOOKUP(B21,[2]在职人员信息表!$F:$H,3,FALSE) -> 矿长助理兼综采队队长 | E21: 正经理级/副矿级 | F21: =VLOOKUP(B21,[2]任职汇总表!$D:$I,6,FALSE()) -> 45597 | I21: 180.5 | J21: 282.65 | K21: 307.8 | W21: =VLOOKUP(B21,Sheet1!$B$4:$B$95,5,FALSE) -> #REF! | X21: 45668 | Y21: 45669 | Z21: 274.5 | AA21: 45739 | AB21: 45739 | AC21: 280
A22: 19 | B22: 张广振 | C22: =VLOOKUP(B22,[2]在职人员信息表!$F:$G,2,FALSE) -> 综采队 | D22: =VLOOKUP(B22,[2]在职人员信息表!$F:$H,3,FALSE) -> 常务副队长 | E22: 副经理级/正科级 | F22: =VLOOKUP(B22,[2]任职汇总表!$D:$I,6,FALSE()) -> 45090 | I22: 131 | J22: 131.4 | K22: 131.4 | W22: =VLOOKUP(B22,Sheet1!$B$4:$B$95,5,FALSE) -> #REF! | X22: 45722 | Y22: 45727 | Z22: 1124 | AA22: 45755 | AB22: 45760 | AC22: 1093
A23: 20 | B23: 杨培 | C23: =VLOOKUP(B23,[2]在职人员信息表!$F:$G,2,FALSE) -> 综采队 | D23: =VLOOKUP(B23,[2]在职人员信息表!$F:$H,3,FALSE) -> 副队长 | E23: 副科级/经理助理/主管 | F23: =VLOOKUP(B23,[2]任职汇总表!$D:$I,6,FALSE()) -> 44958 | I23: 182.4 | J23: 182.1 | K23: 182
A24: 21 | B24: 商好学 | C24: =VLOOKUP(B24,[2]在职人员信息表!$F:$G,2,FALSE) -> 综采队 | D24: =VLOOKUP(B24,[2]在职人员信息表!$F:$H,3,FALSE) -> 副队长 | E24: 副科级/经理助理/主管 | F24: =VLOOKUP(B24,[2]任职汇总表!$D:$I,6,FALSE()) -> 44958 | I24: 145 | J24: 149 | K24: 149.2 | W24: =VLOOKUP(B24,Sheet1!$B$4:$B$95,5,FALSE) -> #REF! | X24: 45742 | Y24: 45751 | Z24: 500
A25: 22 | B25: 杨肖 | C25: =VLOOKUP(B25,[2]在职人员信息表!$F:$G,2,FALSE) -> 综采队 | D25: =VLOOKUP(B25,[2]在职人员信息表!$F:$H,3,FALSE) -> 综采安装材料主管 | E25: 副科级/经理助理/主管 | F25: =VLOOKUP(B25,[2]任职汇总表!$D:$I,6,FALSE()) -> #N/A | I25: 161.8 | J25: 170 | K25: 145.05 | W25: =VLOOKUP(B25,Sheet1!$B$4:$B$95,5,FALSE) -> #REF! | X25: 2025-3.26 | Y25: 45752 | Z25: 1000
A26: 23 | B26: 尹树山 | C26: =VLOOKUP(B26,[2]在职人员信息表!$F:$G,2,FALSE) -> 综采队 | D26: =VLOOKUP(B26,[2]在职人员信息表!$F:$H,3,FALSE) -> 副队长 | E26: 副科级/经理助理/主管 | F26: =VLOOKUP(B26,[2]任职汇总表!$D:$I,6,FALSE()) -> 44958 | I26: 169 | J26: 169 | K26: 169 | W26: =VLOOKUP(B26,Sheet1!$B$4:$B$95,5,FALSE) -> #REF! | X26: 45714 | Y26: 45722 | Z26: 474.5 | AA26: 45773 | AB26: 45777 | AC26: 521.5
A27: 24 | B27: 张坤 | C27: =VLOOKUP(B27,[2]在职人员信息表!$F:$G,2,FALSE) -> 综采队 | D27: =VLOOKUP(B27,[2]在职人员信息表!$F:$H,3,FALSE) -> 副队长 | E27: 副科级/经理助理/主管 | F27: =VLOOKUP(B27,[2]任职汇总表!$D:$I,6,FALSE()) -> 44958 | I27: 130.9 | J27: 130.9 | K27: 130.9 | W27: =VLOOKUP(B27,Sheet1!$B$4:$B$95,5,FALSE) -> #REF!
A28: 25 | B28: 索爱军 | C28: =VLOOKUP(B28,[2]在职人员信息表!$F:$G,2,FALSE) -> 综掘队 | D28: =VLOOKUP(B28,[2]在职人员信息表!$F:$H,3,FALSE) -> 副队长 | E28: 副科级/经理助理/主管 | F28: =VLOOKUP(B28,[2]任职汇总表!$D:$I,6,FALSE()) -> 44964 | I28: 200 | J28: 200 | K28: 200 | L28: 200 | M28: 200 | N28: 200 | W28: =VLOOKUP(B28,Sheet1!$B$4:$B$95,5,FALSE) -> #REF! | X28: 45684 | Y28: 45692 | Z28: 1000 | AA28: 45764 | AB28: 45774 | AC28: 1000
A29: 26 | B29: 荣启亭 | C29: =VLOOKUP(B29,[2]在职人员信息表!$F:$G,2,FALSE) -> 综掘队 | D29: =VLOOKUP(B29,[2]在职人员信息表!$F:$H,3,FALSE) -> 队长 | E29: 副经理级/ 正科级 | F29: =VLOOKUP(B29,[2]任职汇总表!$D:$I,6,FALSE()) -> 45866 | I29: 114.25 | J29: 136.3 | K29: 158.35 | L29: 132.55 | M29: 125.05 | N29: 174.85 | W29: =VLOOKUP(B29,Sheet1!$B$4:$B$95,5,FALSE) -> #REF!
A30: 27 | B30: 刘凤山 | C30: =VLOOKUP(B30,[2]在职人员信息表!$F:$G,2,FALSE) -> 综掘队 | D30: =VLOOKUP(B30,[2]在职人员信息表!$F:$H,3,FALSE) -> 副队长 | E30: 副科级/经理助理/主管 | F30: =VLOOKUP(B30,[2]任职汇总表!$D:$I,6,FALSE()) -> 44964 | I30: 169.4 | J30: 168.7 | K30: 168 | L30: 168.7 | M30: 168.2 | N30: 168 | W30: =VLOOKUP(B30,Sheet1!$B$4:$B$95,5,FALSE) -> #REF! | X30: 45770 | Y30: 45780 | Z30: 1000
A31: 28 | B31: 索爱国 | C31: =VLOOKUP(B31,[2]在职人员信息表!$F:$G,2,FALSE) -> 综掘队 | D31: =VLOOKUP(B31,[2]在职人员信息表!$F:$H,3,FALSE) -> 副队长 | E31: 副科级/经理助理/主管 | F31: =VLOOKUP(B31,[2]任职汇总表!$D:$I,6,FALSE()) -> 45881
A32: 29 | B32: 贺伟 | C32: =VLOOKUP(B32,[2]在职人员信息表!$F:$G,2,FALSE) -> 安全监察科 | D32: =VLOOKUP(B32,[2]在职人员信息表!$F:$H,3,FALSE) -> 科长 | E32: 副经理级/正科级 | F32: =VLOOKUP(B32,[2]任职汇总表!$D:$I,6,FALSE()) -> 45145 | I32: 151 | J32: 131.9 | K32: 132.2 | L32: 131.3 | M32: 131.5 | N32: 141.2
A33: 30 | B33: 郭小强 | C33: =VLOOKUP(B33,[2]在职人员信息表!$F:$G,2,FALSE) -> 安全监察科 | D33: =VLOOKUP(B33,[2]在职人员信息表!$F:$H,3,FALSE) -> 副科长 | E33: 副科级/经理助理/主管 | F33: =VLOOKUP(B33,[2]任职汇总表!$D:$I,6,FALSE()) -> 44607 | I33: 179 | J33: 179.9 | K33: 179.3 | L33: 179 | M33: 179.1 | N33: 177.76 | W33: =VLOOKUP(B33,Sheet1!$B$4:$B$95,5,FALSE) -> #REF! | X33: 45708 | Y33: 45711 | Z33: 717.39 | AA33: 45792 | AB33: 45795 | AC33: 732.74 | AD33: 2025.6.27 | AE33: 45838 | AF33: 733.91
A34: 31 | B34: 尹烈欢 | C34: =VLOOKUP(B34,[2]在职人员信息表!$F:$G,2,FALSE) -> 机运队 | D34: =VLOOKUP(B34,[2]在职人员信息表!$F:$H,3,FALSE) -> 矿长助理兼机运队队长 | E34: 正经理级/副矿级 | F34: =VLOOKUP(B34,[2]任职汇总表!$D:$I,6,FALSE()) -> 45698 | I34: 322.7 | J34: 322.8 | K34: 322.5 | L34: 322.4 | M34: 322.7 | N34: 322.4 | W34: =VLOOKUP(B34,Sheet1!$B$4:$B$95,5,FALSE) -> #REF! | X34: 45684 | Y34: 45692 | Z34: 2000
A35: 32 | B35: 程学军 | C35: =VLOOKUP(B35,[2]在职人员信息表!$F:$G,2,FALSE) -> 机运队 | D35: =VLOOKUP(B35,[2]在职人员信息表!$F:$H,3,FALSE) -> 副队长 | E35: 副科级/经理助理/主管 | F35: =VLOOKUP(B35,[2]任职汇总表!$D:$I,6,FALSE()) -> 41432 | I35: 186.1 | J35: 196.52 | K35: 185.9 | L35: 200 | M35: 200 | N35: 200 | W35: =VLOOKUP(B35,Sheet1!$B$4:$B$95,5,FALSE) -> #REF! | X35: 45763 | Y35: 45773 | Z35: 560
A36: 33 | B36: 李龙博 | C36: =VLOOKUP(B36,[2]在职人员信息表!$F:$G,2,FALSE) -> 机运队 | D36: =VLOOKUP(B36,[2]在职人员信息表!$F:$H,3,FALSE) -> 副队长 | E36: 副科级/经理助理/主管 | F36: =VLOOKUP(B36,[2]任职汇总表!$D:$I,6,FALSE()) -> 44653 | I36: 68 | J36: 68 | K36: 68 | L36: 68 | M36: 68 | N36: 68 | W36: =VLOOKUP(B36,Sheet1!$B$4:$B$95,5,FALSE) -> #REF! | X36: 45710 | Y36: 45716 | Z36: 1000
A37: 34 | B37: 孙珠红 | C37: =VLOOKUP(B37,[2]在职人员信息表!$F:$G,2,FALSE) -> 机运队 | D37: =VLOOKUP(B37,[2]在职人员信息表!$F:$H,3,FALSE) -> 检修班班长 | E37: 副科级/经理助理/主管 | F37: =VLOOKUP(B37,[2]任职汇总表!$D:$I,6,FALSE()) -> 45012 | I37: 114.87 | J37: 146 | K37: 146 | L37: 146 | M37: 200 | N37: 59.5 | W37: =VLOOKUP(B37,Sheet1!$B$4:$B$95,5,FALSE) -> #REF!
A38: 35 | B38: 史红军 | C38: =VLOOKUP(B38,[2]在职人员信息表!$F:$G,2,FALSE) -> 选煤厂 | D38: =VLOOKUP(B38,[2]在职人员信息表!$F:$H,3,FALSE) -> 总经理助理兼选煤厂厂长 | E38: 高级经理级 | F38: =VLOOKUP(B38,[2]任职汇总表!$D:$I,6,FALSE()) -> 45286 | I38: 219 | J38: 162.1 | K38: 162.6 | L38: 162.1 | M38: 162.1 | N38: 162.1 | W38: =VLOOKUP(B38,Sheet1!$B$4:$B$95,5,FALSE) -> #REF! | X38: 45694 | Y38: 45698 | Z38: 2540.37 | AA38: 45759 | AB38: 45767 | AC38: 2533.07 | AD38: 45872 | AE38: 45882 | AF38: 2639.42
A39: 36 | B39: 王亮勋 | C39: =VLOOKUP(B39,[2]在职人员信息表!$F:$G,2,FALSE) -> 选煤厂 | D39: =VLOOKUP(B39,[2]在职人员信息表!$F:$H,3,FALSE) -> 安全副厂长 | E39: 副经理级/正科级 | F39: =VLOOKUP(B39,[2]任职汇总表!$D:$I,6,FALSE()) -> 44210 | I39: 199.5 | J39: 199 | K39: 199 | L39: 199 | M39: 210.25 | N39: 219
A40: 37 | B40: 张磊 | C40: =VLOOKUP(B40,[2]在职人员信息表!$F:$G,2,FALSE) -> 选煤厂 | D40: =VLOOKUP(B40,[2]在职人员信息表!$F:$H,3,FALSE) -> 常务副厂长 | E40: 正经理级/副矿级 | F40: =VLOOKUP(B40,[2]任职汇总表!$D:$I,6,FALSE()) -> 45775 | I40: 180.1 | J40: 180.1 | K40: 180.1 | L40: 180.3 | M40: 180.6 | N40: 180
A41: 38 | B41: 贾喜钢 | C41: =VLOOKUP(B41,[2]在职人员信息表!$F:$G,2,FALSE) -> 选煤厂 | D41: =VLOOKUP(B41,[2]在职人员信息表!$F:$H,3,FALSE) -> 主洗主管 | E41: 副科级/经理助理/主管 | F41: =VLOOKUP(B41,[2]任职汇总表!$D:$I,6,FALSE()) -> 43164 | I41: 138 | J41: 137.9 | K41: 152.9 | L41: 152.9 | M41: 152.9 | N41: 153.1
A42: 39 | B42: 艾祖国 | C42: =VLOOKUP(B42,[2]在职人员信息表!$F:$G,2,FALSE) -> 选煤厂 | D42: =VLOOKUP(B42,[2]在职人员信息表!$F:$H,3,FALSE) -> 机修副班长 | E42: 副科级/经理助理/主管 | F42: =VLOOKUP(B42,[2]任职汇总表!$D:$I,6,FALSE()) -> 45012 | I42: 200 | J42: 200 | K42: 200 | L42: 159 | M42: 159 | N42: 174.4 | W42: =VLOOKUP(B42,Sheet1!$B$4:$B$95,5,FALSE) -> #REF!
A43: 40 | B43: 邬志雄 | C43: =VLOOKUP(B43,[2]在职人员信息表!$F:$G,2,FALSE) -> 总调度室 | D43: =VLOOKUP(B43,[2]在职人员信息表!$F:$H,3,FALSE) -> 安全副厂长 | E43: 正经理级/副矿级 | F43: =VLOOKUP(B43,[2]任职汇总表!$D:$I,6,FALSE()) -> 45866 | I43: 273 | J43: 273.1 | K43: 273 | L43: 273.1 | M43: 273.1 | N43: 273
A44: 41 | B44: 任建龙 | C44: =VLOOKUP(B44,[2]在职人员信息表!$F:$G,2,FALSE) -> 总调度室 | D44: =VLOOKUP(B44,[2]在职人员信息表!$F:$H,3,FALSE) -> 主任 | E44: 副经理级/ 正科级 | F44: =VLOOKUP(B44,[2]任职汇总表!$D:$I,6,FALSE()) -> 45866 | I44: 173.11 | J44: 153.88 | K44: 149.41 | L44: 148.09 | M44: 152.17 | N44: 165.21
A45: 42 | B45: 王恒 | C45: =VLOOKUP(B45,[2]在职人员信息表!$F:$G,2,FALSE) -> 总调度室 | D45: =VLOOKUP(B45,[2]在职人员信息表!$F:$H,3,FALSE) -> 副主任 | E45: 副科级/经理助理/主管 | F45: =VLOOKUP(B45,[2]任职汇总表!$D:$I,6,FALSE()) -> 45012 | I45: 180 | J45: 180.3 | K45: 180.7 | L45: 180 | M45: 193.4 | N45: 180
A46: 43 | B46: 孙太洋 | C46: =VLOOKUP(B46,[2]在职人员信息表!$F:$G,2,FALSE) -> 总调度室 | D46: =VLOOKUP(B46,[2]在职人员信息表!$F:$H,3,FALSE) -> 副主任工程师 | E46: 副科级/经理助理/主管 | F46: =VLOOKUP(B46,[2]任职汇总表!$D:$I,6,FALSE()) -> 45400 | I46: 112 | J46: 30.72 | K46: 93.48 | L46: 112 | M46: 112.1 | N46: 112 | W46: =VLOOKUP(B46,Sheet1!$B$4:$B$95,5,FALSE) -> #REF!
A47: 44 | B47: 李龙 | C47: =VLOOKUP(B47,[2]在职人员信息表!$F:$G,2,FALSE) -> 总调度室 | D47: =VLOOKUP(B47,[2]在职人员信息表!$F:$H,3,FALSE) -> 副主任工程师 | E47: 副科级/经理助理/主管 | F47: =VLOOKUP(B47,[2]任职汇总表!$D:$I,6,FALSE()) -> 45769 | I47: 160.85 | J47: 139.8 | K47: 140.1 | L47: 139.3 | M47: 200 | N47: 140.3
A48: 45 | B48: 陈建军 | C48: =VLOOKUP(B48,[2]在职人员信息表!$F:$G,2,FALSE) -> 机电科 | D48: =VLOOKUP(B48,[2]在职人员信息表!$F:$H,3,FALSE) -> 工程师 | E48: 副经理级/正科级 | F48: =VLOOKUP(B48,[2]任职汇总表!$D:$I,6,FALSE()) -> 44608 | I48: 80.3 | J48: 78 | K48: 78 | W48: =VLOOKUP(B48,Sheet1!$B$4:$B$95,5,FALSE) -> #REF! | X48: 45741 | Y48: 45751 | Z48: 641.5 | AA48: 45801 | AB48: 45811 | AC48: 869.5
A49: 46 | B49: 柴方柱 | C49: =VLOOKUP(B49,[2]在职人员信息表!$F:$G,2,FALSE) -> 机电科 | D49: =VLOOKUP(B49,[2]在职人员信息表!$F:$H,3,FALSE) -> 科长 | E49: 副经理级/正科级 | F49: =VLOOKUP(B49,[2]任职汇总表!$D:$I,6,FALSE()) -> 45229 | I49: 250.15 | J49: 221.66 | K49: 232.1 | W49: =VLOOKUP(B49,Sheet1!$B$4:$B$95,5,FALSE) -> #REF!
A50: 47 | B50: 马志峰 | C50: =VLOOKUP(B50,[2]在职人员信息表!$F:$G,2,FALSE) -> 机电科 | D50: =VLOOKUP(B50,[2]在职人员信息表!$F:$H,3,FALSE) -> 副科长 | E50: 副科级/经理助理/主管 | F50: =VLOOKUP(B50,[2]任职汇总表!$D:$I,6,FALSE()) -> 45400 | I50: 200 | J50: 200 | K50: 200
A51: 48 | B51: 赵忠良 | C51: =VLOOKUP(B51,[2]在职人员信息表!$F:$G,2,FALSE) -> 机电科 | D51: =VLOOKUP(B51,[2]在职人员信息表!$F:$H,3,FALSE) -> 副主任工程师 | E51: 副科级/经理助理/主管 | F51: =VLOOKUP(B51,[2]任职汇总表!$D:$I,6,FALSE()) -> 45028 | I51: 70 | J51: 82 | K51: 70 | W51: =VLOOKUP(B51,Sheet1!$B$4:$B$95,5,FALSE) -> #REF! | X51: 45684 | Y51: 45692 | Z51: 1000 | AA51: 45760 | AB51: 45770 | AC51: 1000 | AD51: 45821 | AE51: 45830 | AF51: 1000
A52: 49 | B52: 李斯海 | C52: =VLOOKUP(B52,[2]在职人员信息表!$F:$G,2,FALSE) -> 机电科 | D52: =VLOOKUP(B52,[2]在职人员信息表!$F:$H,3,FALSE) -> 副主任工程师 | E52: 副科级/经理助理/主管 | F52: =VLOOKUP(B52,[2]任职汇总表!$D:$I,6,FALSE()) -> 45400 | I52: 181.2 | J52: 181 | K52: 181.4 | W52: =VLOOKUP(B52,Sheet1!$B$4:$B$95,5,FALSE) -> #REF!
A53: 50 | B53: 郭连敏 | C53: =VLOOKUP(B53,[2]在职人员信息表!$F:$G,2,FALSE) -> 机电科 | D53: =VLOOKUP(B53,[2]在职人员信息表!$F:$H,3,FALSE) -> 副科长 | E53: 副科级/经理助理/主管 | F53: =VLOOKUP(B53,[2]任职汇总表!$D:$I,6,FALSE()) -> 45803
A54: 51 | B54: 张小星 | C54: =VLOOKUP(B54,[2]在职人员信息表!$F:$G,2,FALSE) -> 机电科 | D54: =VLOOKUP(B54,[2]在职人员信息表!$F:$H,3,FALSE) -> 副主任工程师 | E54: 副科级/经理助理/主管 | F54: =VLOOKUP(B54,[2]任职汇总表!$D:$I,6,FALSE()) -> 45769
A55: 52 | B55: 赵喜龙 | C55: =VLOOKUP(B55,[2]在职人员信息表!$F:$G,2,FALSE) -> 通风科 | D55: =VLOOKUP(B55,[2]在职人员信息表!$F:$H,3,FALSE) -> 矿长助理 | E55: 正经理级/副矿级 | F55: =VLOOKUP(B55,[2]任职汇总表!$D:$I,6,FALSE()) -> 45866 | I55: 300 | J55: 300 | K55: 300 | L55: 300 | M55: 300 | N55: 300
A56: 53 | B56: 赵彦锋 | C56: =VLOOKUP(B56,[2]在职人员信息表!$F:$G,2,FALSE) -> 通风科 | D56: =VLOOKUP(B56,[2]在职人员信息表!$F:$H,3,FALSE) -> 副科长 | E56: 副科级/经理助理/主管 | F56: =VLOOKUP(B56,[2]任职汇总表!$D:$I,6,FALSE()) -> 44292 | I56: 165.2 | J56: 162.88 | K56: 160.34 | L56: 157.64 | M56: 161.52 | N56: 161.36
A57: 54 | B57: 徐振炎 | C57: =VLOOKUP(B57,[2]在职人员信息表!$F:$G,2,FALSE) -> 生产机修科 | D57: =VLOOKUP(B57,[2]在职人员信息表!$F:$H,3,FALSE) -> 科长 | E57: 副经理级/正科级 | F57: =VLOOKUP(B57,[2]任职汇总表!$D:$I,6,FALSE()) -> 45664 | I57: 200 | J57: 209.7 | K57: 300 | L57: 210.2 | M57: 210.2 | N57: 209.6 | W57: =VLOOKUP(B57,Sheet1!$B$4:$B$95,5,FALSE) -> #REF!
A58: 55 | B58: 赵国锋 | C58: =VLOOKUP(B58,[2]在职人员信息表!$F:$G,2,FALSE) -> 生产机修科 | D58: =VLOOKUP(B58,[2]在职人员信息表!$F:$H,3,FALSE) -> 工程师 | E58: 副经理级/正科级 | F58: =VLOOKUP(B58,[2]任职汇总表!$D:$I,6,FALSE()) -> 44608 | I58: 80.5 | J58: 105.45 | K58: 106.45 | L58: 82.65 | M58: 80.9 | N58: 92.9 | W58: =VLOOKUP(B58,Sheet1!$B$4:$B$95,5,FALSE) -> #REF! | X58: 45751 | Y58: 45761 | Z58: 897.5 | AA58: 45828 | AB58: 45838 | AC58: 1143
A59: 56 | B59: 冀贵龙 | C59: =VLOOKUP(B59,[2]在职人员信息表!$F:$G,2,FALSE) -> 生产机修科 | D59: =VLOOKUP(B59,[2]在职人员信息表!$F:$H,3,FALSE) -> 电工高级技师 | E59: 副科级/经理助理/主管 | F59: =VLOOKUP(B59,[2]任职汇总表!$D:$I,6,FALSE()) -> 43916 | I59: 200 | J59: 200 | K59: 200 | L59: 200 | M59: 200 | N59: 200 | W59: =VLOOKUP(B59,Sheet1!$B$4:$B$95,5,FALSE) -> #REF! | X59: 45748 | Y59: 45758 | Z59: 400 | AA59: 45814 | AB59: 45824 | AC59: 400
A60: 57 | B60: 董武 | C60: =VLOOKUP(B60,[2]在职人员信息表!$F:$G,2,FALSE) -> 生产机修科 | D60: =VLOOKUP(B60,[2]在职人员信息表!$F:$H,3,FALSE) -> 副主任工程师 | E60: 副科级/经理助理/主管 | F60: =VLOOKUP(B60,[2]任职汇总表!$D:$I,6,FALSE()) -> 45012 | W60: 江西省南昌市 | X60: 45764 | Y60: 45773 | Z60: 978 | AA60: 45806 | AB60: 45816 | AC60: 906
A61: 58 | B61: 刘智强 | C61: =VLOOKUP(B61,[2]在职人员信息表!$F:$G,2,FALSE) -> 生产机修科 | D61: =VLOOKUP(B61,[2]在职人员信息表!$F:$H,3,FALSE) -> 主管 | E61: 副科级/经理助理/主管 | F61: =VLOOKUP(B61,[2]任职汇总表!$D:$I,6,FALSE()) -> #N/A | I61: 200 | J61: 200 | K61: 200
A62: 59 | B62: 周元甲 | C62: =VLOOKUP(B62,[2]在职人员信息表!$F:$G,2,FALSE) -> 开发部 | D62: =VLOOKUP(B62,[2]在职人员信息表!$F:$H,3,FALSE) -> 经理 | E62: 正经理级/副矿级 | F62: =VLOOKUP(B62,[2]任职汇总表!$D:$I,6,FALSE()) -> 45881 | H62: 1000 | I62: 240.45 | J62: 300 | K62: 233.1 | L62: 100.4 | M62: 98.3 | N62: 98.1
A63: 60 | B63: 高文豹 | C63: =VLOOKUP(B63,[2]在职人员信息表!$F:$G,2,FALSE) -> 开发部 | D63: =VLOOKUP(B63,[2]在职人员信息表!$F:$H,3,FALSE) -> 专员 | E63: 副科级/经理助理/主管 | F63: =VLOOKUP(B63,[2]任职汇总表!$D:$I,6,FALSE()) -> #N/A | H63: 1000 | I63: 109.1 | J63: 109.6 | K63: 119.2 | L63: 150 | M63: 150 | N63: 150
A64: 61 | B64: 李纪宏 | C64: =VLOOKUP(B64,[2]在职人员信息表!$F:$G,2,FALSE) -> 开发部 | D64: =VLOOKUP(B64,[2]在职人员信息表!$F:$H,3,FALSE) -> 主管 | E64: 副科级/经理助理/主管 | F64: =VLOOKUP(B64,[2]任职汇总表!$D:$I,6,FALSE()) -> 45881 | H64: 1000 | I64: 200 | J64: 200 | K64: 200 | L64: 200 | M64: 200 | N64: 197.3
A65: 62 | B65: 刘彦彤 | C65: =VLOOKUP(B65,[2]在职人员信息表!$F:$G,2,FALSE) -> 开发部 | D65: =VLOOKUP(B65,[2]在职人员信息表!$F:$H,3,FALSE) -> 主管 | E65: 副科级/经理助理/主管 | F65: =VLOOKUP(B65,[2]任职汇总表!$D:$I,6,FALSE()) -> 45881 | H65: 1000 | I65: 200 | J65: 200 | K65: 200 | L65: 200 | M65: 200 | N65: 200
A66: 63 | B66: 郝佳 | C66: =VLOOKUP(B66,[2]在职人员信息表!$F:$G,2,FALSE) -> 财务部 | D66: =VLOOKUP(B66,[2]在职人员信息表!$F:$H,3,FALSE) -> 财务副经理 | E66: 副经理级/正科级 | F66: =VLOOKUP(B66,[2]任职汇总表!$D:$I,6,FALSE()) -> 45052
A67: 64 | B67: 王琴 | C67: =VLOOKUP(B67,[2]在职人员信息表!$F:$G,2,FALSE) -> 财务部 | D67: =VLOOKUP(B67,[2]在职人员信息表!$F:$H,3,FALSE) -> 融资主管 | E67: 副科级/经理助理/主管 | F67: =VLOOKUP(B67,[2]任职汇总表!$D:$I,6,FALSE()) -> 44721
A68: 65 | B68: 周婷 | C68: =VLOOKUP(B68,[2]在职人员信息表!$F:$G,2,FALSE) -> 财务部 | D68: =VLOOKUP(B68,[2]在职人员信息表!$F:$H,3,FALSE) -> 会计主管 | E68: 副科级/经理助理/主管 | F68: =VLOOKUP(B68,[2]任职汇总表!$D:$I,6,FALSE()) -> 44721
A69: 66 | B69: 石岭 | C69: =VLOOKUP(B69,[2]在职人员信息表!$F:$G,2,FALSE) -> 采购部 | D69: =VLOOKUP(B69,[2]在职人员信息表!$F:$H,3,FALSE) -> 经理 | E69: 正经理级/副矿级 | F69: =VLOOKUP(B69,[2]任职汇总表!$D:$I,6,FALSE()) -> 45881 | I69: 129.6 | J69: 129.6 | K69: 138.1 | W69: =VLOOKUP(B69,Sheet1!$B$4:$B$95,5,FALSE) -> #REF!
A70: 67 | B70: 李善君 | C70: =VLOOKUP(B70,[2]在职人员信息表!$F:$G,2,FALSE) -> 采购部 | D70: =VLOOKUP(B70,[2]在职人员信息表!$F:$H,3,FALSE) -> 副经理 | E70: 副经理级/正科级 | F70: =VLOOKUP(B70,[2]任职汇总表!$D:$I,6,FALSE()) -> 45532 | I70: 110.2 | J70: 110.1 | K70: 110.1 | W70: =VLOOKUP(B70,Sheet1!$B$4:$B$95,5,FALSE) -> #REF!
A71: 68 | B71: 訾园 | C71: =VLOOKUP(B71,[2]在职人员信息表!$F:$G,2,FALSE) -> 人力行政中心 | D71: =VLOOKUP(B71,[2]在职人员信息表!$F:$H,3,FALSE) -> 主管 | E71: 副科级/经理助理/主管 | F71: =VLOOKUP(B71,[2]任职汇总表!$D:$I,6,FALSE()) -> 45145 | I71: 144 | J71: 144 | K71: 144 | L71: 144 | M71: 144 | N71: 171
A72: 69 | B72: 邓志伟 | C72: =VLOOKUP(B72,[2]在职人员信息表!$F:$G,2,FALSE) -> 人力行政中心 | D72: =VLOOKUP(B72,[2]在职人员信息表!$F:$H,3,FALSE) -> 高级主任人力资源管理师 | E72: 正经理级/副矿级 | F72: =VLOOKUP(B72,[2]任职汇总表!$D:$I,6,FALSE()) -> 45769 | I72: 255.4 | J72: 273.48 | K72: 273.1 | L72: 261 | M72: 270.9 | N72: 270.4
A73: 70 | B73: 张永春 | C73: =VLOOKUP(B73,[2]在职人员信息表!$F:$G,2,FALSE) -> 人力行政中心 | D73: =VLOOKUP(B73,[2]在职人员信息表!$F:$H,3,FALSE) -> 人力行政中心主管 | E73: 副科级/经理助理/主管 | F73: =VLOOKUP(B73,[2]任职汇总表!$D:$I,6,FALSE()) -> 44607 | I73: 181.55 | J73: 200 | K73: 200 | L73: 177.5 | M73: 191 | N73: 170.99
A74: 71 | B74: 赵乐 | C74: =VLOOKUP(B74,[2]在职人员信息表!$F:$G,2,FALSE) -> 人力行政中心 | D74: =VLOOKUP(B74,[2]在职人员信息表!$F:$H,3,FALSE) -> 经理 | E74: 正经理级/副矿级 | F74: =VLOOKUP(B74,[2]任职汇总表!$D:$I,6,FALSE()) -> 45664 | I74: 300 | J74: 341.7 | K74: 340.8 | L74: 341.2 | M74: 350.3 | N74: 350.9
A75: 72 | B75: 杨皓鸣 | C75: =VLOOKUP(B75,[2]在职人员信息表!$F:$G,2,FALSE) -> 人力行政中心 | D75: =VLOOKUP(B75,[2]在职人员信息表!$F:$H,3,FALSE) -> 副经理 | E75: 副经理级/正科级 | F75: =VLOOKUP(B75,[2]任职汇总表!$D:$I,6,FALSE()) -> 45145 | I75: 189.99 | J75: 201.99 | K75: 201 | L75: 201.4 | M75: 201.2 | N75: 201.1
A76: 73 | B76: 乔玮 | C76: =VLOOKUP(B76,[2]在职人员信息表!$F:$G,2,FALSE) -> 人力行政中心 | D76: =VLOOKUP(B76,[2]在职人员信息表!$F:$H,3,FALSE) -> 副经理 | E76: 副经理级/正科级 | F76: =VLOOKUP(B76,[2]任职汇总表!$D:$I,6,FALSE()) -> 45145 | I76: 114.9 | J76: 114.6 | K76: 114.6 | L76: 114.6 | M76: 114.6 | N76: 114.6
A77: 74 | B77: 杨学塨 | C77: =VLOOKUP(B77,[2]在职人员信息表!$F:$G,2,FALSE) -> 人力行政中心 | D77: =VLOOKUP(B77,[2]在职人员信息表!$F:$H,3,FALSE) -> 车辆主管 | E77: 副科级/经理助理/主管 | F77: =VLOOKUP(B77,[2]任职汇总表!$D:$I,6,FALSE()) -> 44324 | I77: 199.1 | J77: 200 | K77: 199.2 | L77: 199 | M77: 199 | N77: 199.6 | W77: =VLOOKUP(B77,Sheet1!$B$4:$B$95,5,FALSE) -> #REF! | X77: 45775 | Y77: 45782 | Z77: 1000 | AA77: 45871 | AB77: 45879 | AC77: 1000
A78: 75 | B78: 马二苗 | C78: =VLOOKUP(B78,[2]在职人员信息表!$F:$G,2,FALSE) -> 人力行政中心-安保 | D78: =VLOOKUP(B78,[2]在职人员信息表!$F:$H,3,FALSE) -> 副科长 | E78: 副科级/经理助理/主管 | F78: =VLOOKUP(B78,[2]任职汇总表!$D:$I,6,FALSE()) -> 44636 | I78: 200 | J78: 200 | K78: 200 | L78: 198.4 | M78: 200 | N78: 200
A79: 76 | B79: 李金慧 | C79: =VLOOKUP(B79,[2]在职人员信息表!$F:$G,2,FALSE) -> 法务监察部 | D79: =VLOOKUP(B79,[2]在职人员信息表!$F:$H,3,FALSE) -> 经理 | E79: 正经理级/副矿级 | F79: =VLOOKUP(B79,[2]任职汇总表!$D:$I,6,FALSE()) -> 45145 | H79: 600 | I79: 210 | J79: 210.6 | K79: 210 | L79: 210.3 | M79: 210.1 | N79: 210
A80: 77 | B80: 刘伟 | C80: =VLOOKUP(B80,[2]在职人员信息表!$F:$G,2,FALSE) -> 法务监察部 | D80: =VLOOKUP(B80,[2]在职人员信息表!$F:$H,3,FALSE) -> 副主任法务监察员 | E80: 副科级/经理助理/主管 | F80: =VLOOKUP(B80,[2]任职汇总表!$D:$I,6,FALSE()) -> 45028 | I80: 92.9 | J80: 88.2 | K80: 95.9 | L80: 93.4 | M80: 99.45 | N80: 95.6
A81: 78 | B81: 郭贵清 | C81: =VLOOKUP(B81,[2]在职人员信息表!$F:$G,2,FALSE) -> 总工办 | D81: =VLOOKUP(B81,[2]在职人员信息表!$F:$H,3,FALSE) -> 总工办职员 | E81: 正经理级/副矿级 | F81: =VLOOKUP(B81,[2]任职汇总表!$D:$I,6,FALSE()) -> 44559 | I81: 221.2 | J81: 217 | K81: 217 | L81: 217 | M81: 217.1 | N81: 217.2 | W81: =VLOOKUP(B81,Sheet1!$B$4:$B$95,5,FALSE) -> #REF! | X81: 45682 | Y81: 45692 | Z81: 1784 | AA81: 45682 | AB81: 45692 | AC81: 1784 | AD81: 45799 | AE81: 45810 | AF81: 1780
A82: 79 | B82: 赵衍国 | C82: =VLOOKUP(B82,[2]在职人员信息表!$F:$G,2,FALSE) -> 总工办 | D82: =VLOOKUP(B82,[2]在职人员信息表!$F:$H,3,FALSE) -> 总工办职员 | E82: 正经理级/副矿级 | F82: =VLOOKUP(B82,[2]任职汇总表!$D:$I,6,FALSE()) -> 43556 | I82: 220.5 | J82: 221 | K82: 221.5 | L82: 221.7 | M82: 222.7 | N82: 232.3 | W82: =VLOOKUP(B82,Sheet1!$B$4:$B$95,5,FALSE) -> #REF! | X82: 45745 | Y82: 45753 | Z82: 1400 | AA82: 45778 | AB82: 45785 | AC82: 1400 | AD82: 45872 | AE82: 45879 | AF82: 1400
A83: 80 | B83: 吴运标 | C83: =VLOOKUP(B83,[2]在职人员信息表!$F:$G,2,FALSE) -> 总工办 | D83: =VLOOKUP(B83,[2]在职人员信息表!$F:$H,3,FALSE) -> 总工办职员 | E83: 正经理级/副矿级 | F83: =VLOOKUP(B83,[2]任职汇总表!$D:$I,6,FALSE()) -> 45289 | I83: 152.05 | J83: 174.08 | K83: 188.72 | L83: 149.69 | M83: 134.97 | N83: 131.71 | W83: =VLOOKUP(B83,Sheet1!$B$4:$B$95,5,FALSE) -> #REF! | X83: 45682 | Y83: 45692 | Z83: 1382.5 | AA83: 45723 | AB83: 45729 | AC83: 898 | AD83: 45774 | AE83: 45785 | AF83: 911 | AG83: 45848 | AH83: 45859 | AI83: 1155.5
A84: 81 | B84: 白新江 | C84: =VLOOKUP(B84,[2]在职人员信息表!$F:$G,2,FALSE) -> 总工办 | D84: =VLOOKUP(B84,[2]在职人员信息表!$F:$H,3,FALSE) -> 总工办主任 | E84: 正经理级/副矿级 | F84: =VLOOKUP(B84,[2]任职汇总表!$D:$I,6,FALSE()) -> 45630 | I84: 400 | J84: 400 | K84: 400 | L84: 400 | M84: 400 | N84: 400
A85: 82 | B85: 刘梦佳 | C85: =VLOOKUP(B85,[2]在职人员信息表!$F:$G,2,FALSE) -> 总工办 | D85: =VLOOKUP(B85,[2]在职人员信息表!$F:$H,3,FALSE) -> 副主任 | E85: 副经理级/正科级 | F85: =VLOOKUP(B85,[2]任职汇总表!$D:$I,6,FALSE()) -> 45145 | I85: 162 | J85: 162 | K85: 192.1 | L85: 102.1 | M85: 102.2 | N85: 102.6
A86: 83 | B86: 刘栓柱 | C86: =VLOOKUP(B86,[2]在职人员信息表!$F:$G,2,FALSE) -> 总工办 | D86: =VLOOKUP(B86,[2]在职人员信息表!$F:$H,3,FALSE) -> 总工办职员 | E86: 正经理级/副矿级 | F86: =VLOOKUP(B86,[2]任职汇总表!$D:$I,6,FALSE()) -> 45630 | I86: 102.5 | J86: 102.2 | K86: 102.1 | L86: 102.1 | M86: 102.2 | N86: 102.6 | W86: =VLOOKUP(B86,Sheet1!$B$4:$B$95,5,FALSE) -> #REF! | X86: 45778 | Y86: 45788 | Z86: 780 | AA86: 45849 | AB86: 45859 | AC86: 780
A87: 84 | B87: 顾群亮 | C87: =VLOOKUP(B87,[2]在职人员信息表!$F:$G,2,FALSE) -> 总工办 | D87: =VLOOKUP(B87,[2]在职人员信息表!$F:$H,3,FALSE) -> 总工办职员 | E87: 副科级/经理助理/主管 | F87: =VLOOKUP(B87,[2]任职汇总表!$D:$I,6,FALSE()) -> 45630 | I87: 139.4 | J87: 159 | K87: 200 | L87: 149 | M87: 149 | N87: 139.1 | W87: =VLOOKUP(B87,Sheet1!$B$4:$B$95,5,FALSE) -> #REF! | X87: 45772 | Y87: 45782 | Z87: 790 | AA87: 45830 | AB87: 45840 | AC87: 790
A88: 85 | B88: 高西海 | C88: =VLOOKUP(B88,[2]在职人员信息表!$F:$G,2,FALSE) -> 总工办 | D88: =VLOOKUP(B88,[2]在职人员信息表!$F:$H,3,FALSE) -> 总工办职员 | E88: 副科级/经理助理/主管 | F88: =VLOOKUP(B88,[2]任职汇总表!$D:$I,6,FALSE()) -> 45423 | I88: 124.9 | J88: 124.9 | K88: 125 | L88: 124.9 | M88: 124.9 | N88: 124.9 | W88: =VLOOKUP(B88,Sheet1!$B$4:$B$95,5,FALSE) -> #REF! | X88: 45681 | Y88: 45691 | Z88: 790 | AA88: 45761 | AB88: 45766 | AC88: 895
A89: 86 | B89: 张启鹏 | C89: =VLOOKUP(B89,[2]在职人员信息表!$F:$G,2,FALSE) -> 多种经营部-多经 | D89: =VLOOKUP(B89,[2]在职人员信息表!$F:$H,3,FALSE) -> 副经理 | E89: 副经理级/正科级 | F89: =VLOOKUP(B89,[2]任职汇总表!$D:$I,6,FALSE()) -> 44202 | I89: 300 | J89: 293 | K89: 300
A90: 87 | B90: 郝春红 | C90: =VLOOKUP(B90,[2]在职人员信息表!$F:$G,2,FALSE) -> 经营管理部 | D90: =VLOOKUP(B90,[2]在职人员信息表!$F:$H,3,FALSE) -> 经理 | E90: 正经理级/副矿级 | F90: =VLOOKUP(B90,[2]任职汇总表!$D:$I,6,FALSE()) -> 45505 | I90: 144.2 | J90: 144.4 | K90: 144.5 | L90: 144.1 | M90: 144 | N90: 144.2 | W90: =VLOOKUP(B90,Sheet1!$B$4:$B$95,5,FALSE) -> #REF! | X90: 45776 | Y90: 45786 | Z90: 1902 | AA90: 45882 | AB90: 45893 | AC90: 2000
A91: 88 | B91: 郭永旭 | C91: =VLOOKUP(B91,[2]在职人员信息表!$F:$G,2,FALSE) -> 经营管理部 | D91: =VLOOKUP(B91,[2]在职人员信息表!$F:$H,3,FALSE) -> 主管 | E91: 副科级/经理助理/主管 | F91: =VLOOKUP(B91,[2]任职汇总表!$D:$I,6,FALSE()) -> 45532 | I91: 200 | J91: 198.2 | K91: 198.6 | L91: 200 | M91: 198 | N91: 198
A92: 89 | B92: 车立鹏 | C92: =VLOOKUP(B92,[2]在职人员信息表!$F:$G,2,FALSE) -> 经营管理部 | D92: =VLOOKUP(B92,[2]在职人员信息表!$F:$H,3,FALSE) -> 副主任工程师 | E92: 副科级/经理助理/主管 | F92: =VLOOKUP(B92,[2]任职汇总表!$D:$I,6,FALSE()) -> 44610 | I92: 187.9 | J92: 187.9 | K92: 187.9 | L92: 187.9 | M92: 187.9 | N92: 187.9
A93: 90 | B93: 赵智巍 | C93: =VLOOKUP(B93,[2]在职人员信息表!$F:$G,2,FALSE) -> 经营管理部 | D93: =VLOOKUP(B93,[2]在职人员信息表!$F:$H,3,FALSE) -> 造价工程师 | E93: 副科级/经理助理/主管 | F93: =VLOOKUP(B93,[2]任职汇总表!$D:$I,6,FALSE()) -> 44609 | I93: 144.4 | J93: 144.1 | K93: 144 | L93: 144 | M93: 144.2 | N93: 144.1 | W93: =VLOOKUP(B93,Sheet1!$B$4:$B$95,5,FALSE) -> #REF!
A94: 91 | B94: 王海军 | C94: =VLOOKUP(B94,[2]在职人员信息表!$F:$G,2,FALSE) -> 选煤厂 | D94: 队长 | E94: 副经理级/正科级 | F94: =VLOOKUP(B94,[2]任职汇总表!$D:$I,6,FALSE()) -> 43164 | I94: 300 | J94: 300 | K94: 300 | L94: 300 | M94: 300 | N94: 300
A95: 92 | B95: 鲁当军 | C95: =VLOOKUP(B95,[2]在职人员信息表!$F:$G,2,FALSE) -> 复垦绿化队 | D95: =VLOOKUP(B95,[2]在职人员信息表!$F:$H,3,FALSE) -> 副队长 | E95: 副科级/经理助理/主管 | F95: =VLOOKUP(B95,[2]任职汇总表!$D:$I,6,FALSE()) -> 44653 | I95: 156.8 | J95: 136.9 | K95: 136.9 | L95: 136.9 | M95: 137 | N95: 136.9

Sheet 任命人员话费福利
A1: 2025年内蒙古准格尔旗力量煤业有限公司主管（含）以上人员 话费及燃油费报销台账
A2: 序号 | C2: 姓名 | D2: 身份证号 | E2: 工作部门 | F2: 岗位 | G2: 话费报销情况 | J2: 燃油报销情况 （元/月） | K2: 备注
C3: 姓名 | D3: 身份证号 | E3: 工作部门 | F3: 岗位 | G3: 级别 | H3: 话费开始报销月份 | I3: 话费报销标准（元/月）
A4: 1 | C4: 李波 | D4: =VLOOKUP(C4,[2]在职人员信息表!$F:$U,16,FALSE) -> 130522198205272415 | E4: =VLOOKUP(C4,[2]在职人员信息表!$F:$G,2,FALSE) -> 公司领导 | F4: =VLOOKUP(C4,[2]在职人员信息表!$F:$H,3,FALSE) -> 董事长 | G4: 董事长 | H4: =VLOOKUP(C4,[2]任职汇总表!$D:$I,6,FALSE()) -> 45235 | I4: 800
A5: 2 | C5: 章杨 | D5: =VLOOKUP(C5,[2]在职人员信息表!$F:$U,16,FALSE) -> 42030019810508031X | E5: =VLOOKUP(C5,[2]在职人员信息表!$F:$G,2,FALSE) -> 公司领导 | F5: =VLOOKUP(C5,[2]在职人员信息表!$F:$H,3,FALSE) -> 总经理 | G5: 总经理级 | H5: =VLOOKUP(C5,[2]任职汇总表!$D:$I,6,FALSE()) -> 45486 | I5: 800
A6: 3 | C6: 窦发权 | D6: =VLOOKUP(C6,[2]在职人员信息表!$F:$U,16,FALSE) -> 370902197109021292 | E6: =VLOOKUP(C6,[2]在职人员信息表!$F:$G,2,FALSE) -> 公司领导 | F6: =VLOOKUP(C6,[2]在职人员信息表!$F:$H,3,FALSE) -> 总工程师 | G6: 总经理级 | H6: =VLOOKUP(C6,[2]任职汇总表!$D:$I,6,FALSE()) -> 45181 | I6: 800
A7: 4 | C7: 奚明 | D7: =VLOOKUP(C7,[2]在职人员信息表!$F:$U,16,FALSE) -> 21128219830626081X | E7: =VLOOKUP(C7,[2]在职人员信息表!$F:$G,2,FALSE) -> 公司领导 | F7: =VLOOKUP(C7,[2]在职人员信息表!$F:$H,3,FALSE) -> 常务副总经理 | G7: 副总级 | H7: =VLOOKUP(C7,[2]任职汇总表!$D:$I,6,FALSE()) -> 44880 | I7: 600
A8: 5 | C8: 宋云飞 | D8: =VLOOKUP(C8,[2]在职人员信息表!$F:$U,16,FALSE) -> 230822198111094910 | E8: =VLOOKUP(C8,[2]在职人员信息表!$F:$G,2,FALSE) -> 公司领导 | F8: =VLOOKUP(C8,[2]在职人员信息表!$F:$H,3,FALSE) -> 副总经理 | G8: 副总级 | H8: =VLOOKUP(C8,[2]任职汇总表!$D:$I,6,FALSE()) -> 45555 | I8: 600
A9: 6 | C9: 周洪刚 | D9: =VLOOKUP(C9,[2]在职人员信息表!$F:$U,16,FALSE) -> 130403196411292114 | E9: =VLOOKUP(C9,[2]在职人员信息表!$F:$G,2,FALSE) -> 公司领导 | F9: =VLOOKUP(C9,[2]在职人员信息表!$F:$H,3,FALSE) -> 总经理助理兼多种经营部经理 | G9: 副总级 | H9: =VLOOKUP(C9,[2]任职汇总表!$D:$I,6,FALSE()) -> 43164 | I9: 600 | J9: 1000
A10: 7 | C10: 王震 | D10: =VLOOKUP(C10,[2]在职人员信息表!$F:$U,16,FALSE) -> 152723198509184812 | E10: =VLOOKUP(C10,[2]在职人员信息表!$F:$G,2,FALSE) -> 公司领导 | F10: =VLOOKUP(C10,[2]在职人员信息表!$F:$H,3,FALSE) -> 副总经理 | G10: 副总级 | H10: =VLOOKUP(C10,[2]任职汇总表!$D:$I,6,FALSE()) -> 44917 | I10: 600 | J10: 1000
A11: 8 | C11: 李秦生 | D11: =VLOOKUP(C11,[2]在职人员信息表!$F:$U,16,FALSE) -> 362329198611264574 | E11: =VLOOKUP(C11,[2]在职人员信息表!$F:$G,2,FALSE) -> 公司领导 | F11: =VLOOKUP(C11,[2]在职人员信息表!$F:$H,3,FALSE) -> 副总经理兼矿长 | G11: 副总级 | H11: =VLOOKUP(C11,[2]任职汇总表!$D:$I,6,FALSE()) -> 45486 | I11: 600
A12: 9 | C12: 赵佳 | D12: =VLOOKUP(C12,[2]在职人员信息表!$F:$U,16,FALSE) -> 150122198401160527 | E12: =VLOOKUP(C12,[2]在职人员信息表!$F:$G,2,FALSE) -> 公司领导 | F12: =VLOOKUP(C12,[2]在职人员信息表!$F:$H,3,FALSE) -> 力量发展财务副总监兼力量煤业财务总监 | G12: 副总级 | H12: =VLOOKUP(C12,[2]任职汇总表!$D:$I,6,FALSE()) -> 45861 | I12: 600
A13: 10 | C13: 杨维海 | D13: =VLOOKUP(C13,[2]在职人员信息表!$F:$U,16,FALSE) -> 340403197510102439 | E13: =VLOOKUP(C13,[2]在职人员信息表!$F:$G,2,FALSE) -> 矿级领导 | F13: =VLOOKUP(C13,[2]在职人员信息表!$F:$H,3,FALSE) -> 副矿长 | G13: 高级经理级 | H13: =VLOOKUP(C13,[2]任职汇总表!$D:$I,6,FALSE()) -> 45642 | I13: 600
A14: 11 | C14: 高翔 | D14: =VLOOKUP(C14,[2]在职人员信息表!$F:$U,16,FALSE) -> 14010219810504601X | E14: =VLOOKUP(C14,[2]在职人员信息表!$F:$G,2,FALSE) -> 矿级领导 | F14: =VLOOKUP(C14,[2]在职人员信息表!$F:$H,3,FALSE) -> 生产副矿长 | G14: 高级经理级 | H14: =VLOOKUP(C14,[2]任职汇总表!$D:$I,6,FALSE()) -> 45642 | I14: 600
A15: 12 | C15: 王荣 | D15: =VLOOKUP(C15,[2]在职人员信息表!$F:$U,16,FALSE) -> 140581198801043215 | E15: =VLOOKUP(C15,[2]在职人员信息表!$F:$G,2,FALSE) -> 矿级领导 | F15: =VLOOKUP(C15,[2]在职人员信息表!$F:$H,3,FALSE) -> 总工程师 | G15: 高级经理级 | H15: =VLOOKUP(C15,[2]任职汇总表!$D:$I,6,FALSE()) -> 45642 | I15: 600
A16: 13 | C16: 陈永清 | D16: =VLOOKUP(C16,[2]在职人员信息表!$F:$U,16,FALSE) -> 230321197809105011 | E16: =VLOOKUP(C16,[2]在职人员信息表!$F:$G,2,FALSE) -> 矿级领导 | F16: =VLOOKUP(C16,[2]在职人员信息表!$F:$H,3,FALSE) -> 机电副矿长 | G16: 高级经理级 | H16: =VLOOKUP(C16,[2]任职汇总表!$D:$I,6,FALSE()) -> 45642 | I16: 600
A17: 14 | C17: 史红军 | D17: =VLOOKUP(C17,[2]在职人员信息表!$F:$U,16,FALSE) -> 412328197409081532 | E17: =VLOOKUP(C17,[2]在职人员信息表!$F:$G,2,FALSE) -> 选煤厂 | F17: =VLOOKUP(C17,[2]在职人员信息表!$F:$H,3,FALSE) -> 总经理助理兼选煤厂厂长 | G17: 高级经理级 | H17: =VLOOKUP(C17,[2]任职汇总表!$D:$I,6,FALSE()) -> 45286 | I17: 600
A18: 15 | C18: 谈安彬 | D18: =VLOOKUP(C18,[2]在职人员信息表!$F:$U,16,FALSE) -> 512323198105240334 | E18: =VLOOKUP(C18,[2]在职人员信息表!$F:$G,2,FALSE) -> 矿级领导 | F18: =VLOOKUP(C18,[2]在职人员信息表!$F:$H,3,FALSE) -> 地质防治水副总工程师 | G18: 正经理级/副矿级 | H18: =VLOOKUP(C18,[2]任职汇总表!$D:$I,6,FALSE()) -> 45460 | I18: 400
A19: 16 | C19: 李亚杰 | D19: =VLOOKUP(C19,[2]在职人员信息表!$F:$U,16,FALSE) -> 140428198808152812 | E19: =VLOOKUP(C19,[2]在职人员信息表!$F:$G,2,FALSE) -> 矿级领导 | F19: =VLOOKUP(C19,[2]在职人员信息表!$F:$H,3,FALSE) -> 安全副总工程师 | G19: 正经理级/副矿级 | H19: =VLOOKUP(C19,[2]任职汇总表!$D:$I,6,FALSE()) -> 45423 | I19: 400
A20: 17 | C20: 付浩声 | D20: =VLOOKUP(C20,[2]在职人员信息表!$F:$U,16,FALSE) -> 370983198605021358 | E20: =VLOOKUP(C20,[2]在职人员信息表!$F:$G,2,FALSE) -> 矿级领导 | F20: =VLOOKUP(C20,[2]在职人员信息表!$F:$H,3,FALSE) -> 机电副总工程师 | G20: 正经理级/副矿级 | H20: =VLOOKUP(C20,[2]任职汇总表!$D:$I,6,FALSE()) -> 45423 | I20: 400
A21: 18 | C21: 张春宝 | D21: =VLOOKUP(C21,[2]在职人员信息表!$F:$U,16,FALSE) -> 152103198304015478 | E21: =VLOOKUP(C21,[2]在职人员信息表!$F:$G,2,FALSE) -> 通风科 | F21: =VLOOKUP(C21,[2]在职人员信息表!$F:$H,3,FALSE) -> 通风副总工程师 | G21: 正经理级/副矿级 | H21: =VLOOKUP(C21,[2]任职汇总表!$D:$I,6,FALSE()) -> 45597 | I21: 400
A22: 19 | C22: 孙启明 | D22: =VLOOKUP(C22,[2]在职人员信息表!$F:$U,16,FALSE) -> 150428198903200159 | E22: =VLOOKUP(C22,[2]在职人员信息表!$F:$G,2,FALSE) -> 综采队 | F22: =VLOOKUP(C22,[2]在职人员信息表!$F:$H,3,FALSE) -> 矿长助理兼综采队队长 | G22: 正经理级/副矿级 | H22: =VLOOKUP(C22,[2]任职汇总表!$D:$I,6,FALSE()) -> 45597 | I22: 400
... A24: 21 | C24: 张磊 | D24: =VLOOKUP(C24,[2]在职人员信息表!$F:$U,16,FALSE) -> 140108198805043918 | E24: =VLOOKUP(C24,[2]在职人员信息表!$F:$G,2,FALSE) -> 选煤厂 | F24: =VLOOKUP(C24,[2]在职人员信息表!$F:$H,3,FALSE) -> 常务副厂长 | G24: 正经理级/副矿级 | H24: =VLOOKUP(C24,[2]任职汇总表!$D:$I,6,FALSE()) -> 45775 | I24: 400
A25: 22 | C25: 邬志雄 | D25: =VLOOKUP(C25,[2]在职人员信息表!$F:$U,16,FALSE) -> 152723198801254515 | E25: 矿级领导 | F25: 安全副矿长 | G25: 正经理级/副矿级 | H25: =VLOOKUP(C25,[2]任职汇总表!$D:$I,6,FALSE()) -> 45866 | I25: 400
A26: 23 | C26: 赵喜龙 | D26: =VLOOKUP(C26,[2]在职人员信息表!$F:$U,16,FALSE) -> 152723198610124814 | E26: =VLOOKUP(C26,[2]在职人员信息表!$F:$G,2,FALSE) -> 通风科 | F26: =VLOOKUP(C26,[2]在职人员信息表!$F:$H,3,FALSE) -> 矿长助理 | G26: 正经理级/副矿级 | H26: =VLOOKUP(C26,[2]任职汇总表!$D:$I,6,FALSE()) -> 45866 | I26: 400
A27: 24 | C27: 周元甲 | D27: =VLOOKUP(C27,[2]在职人员信息表!$F:$U,16,FALSE) -> 152723198410215439 | E27: =VLOOKUP(C27,[2]在职人员信息表!$F:$G,2,FALSE) -> 开发部 | F27: =VLOOKUP(C27,[2]在职人员信息表!$F:$H,3,FALSE) -> 经理 | G27: 正经理级/副矿级 | H27: =VLOOKUP(C27,[2]任职汇总表!$D:$I,6,FALSE()) -> 45881 | I27: 400 | J27: 1000
A28: 25 | C28: 石岭 | D28: =VLOOKUP(C28,[2]在职人员信息表!$F:$U,16,FALSE) -> 142232198701063831 | E28: =VLOOKUP(C28,[2]在职人员信息表!$F:$G,2,FALSE) -> 采购部 | F28: =VLOOKUP(C28,[2]在职人员信息表!$F:$H,3,FALSE) -> 经理 | G28: 正经理级/副矿级 | H28: =VLOOKUP(C28,[2]任职汇总表!$D:$I,6,FALSE()) -> 45881 | I28: 400
A29: 26 | C29: 邓志伟 | D29: =VLOOKUP(C29,[2]在职人员信息表!$F:$U,16,FALSE) -> 152325198603106029 | E29: =VLOOKUP(C29,[2]在职人员信息表!$F:$G,2,FALSE) -> 人力行政中心 | F29: =VLOOKUP(C29,[2]在职人员信息表!$F:$H,3,FALSE) -> 高级主任人力资源管理师 | G29: 正经理级/副矿级 | H29: =VLOOKUP(C29,[2]任职汇总表!$D:$I,6,FALSE()) -> 45769 | I29: 400
A30: 27 | C30: 赵乐 | D30: =VLOOKUP(C30,[2]在职人员信息表!$F:$U,16,FALSE) -> 152723198802081222 | E30: =VLOOKUP(C30,[2]在职人员信息表!$F:$G,2,FALSE) -> 人力行政中心 | F30: =VLOOKUP(C30,[2]在职人员信息表!$F:$H,3,FALSE) -> 经理 | G30: 正经理级/副矿级 | H30: =VLOOKUP(C30,[2]任职汇总表!$D:$I,6,FALSE()) -> 45664 | I30: 400
A31: 28 | C31: 李金慧 | D31: =VLOOKUP(C31,[2]在职人员信息表!$F:$U,16,FALSE) -> 130828198708180269 | E31: =VLOOKUP(C31,[2]在职人员信息表!$F:$G,2,FALSE) -> 法务监察部 | F31: =VLOOKUP(C31,[2]在职人员信息表!$F:$H,3,FALSE) -> 经理 | G31: 正经理级/副矿级 | H31: =VLOOKUP(C31,[2]任职汇总表!$D:$I,6,FALSE()) -> 45145 | I31: 400 | J31: 600
A32: 29 | C32: 郭贵清 | D32: =VLOOKUP(C32,[2]在职人员信息表!$F:$U,16,FALSE) -> 152102196412021212 | E32: =VLOOKUP(C32,[2]在职人员信息表!$F:$G,2,FALSE) -> 总工办 | F32: =VLOOKUP(C32,[2]在职人员信息表!$F:$H,3,FALSE) -> 总工办职员 | G32: 正经理级/副矿级 | H32: =VLOOKUP(C32,[2]任职汇总表!$D:$I,6,FALSE()) -> 44559 | I32: 400
A33: 30 | C33: 赵衍国 | D33: =VLOOKUP(C33,[2]在职人员信息表!$F:$U,16,FALSE) -> 370922196708141318 | E33: =VLOOKUP(C33,[2]在职人员信息表!$F:$G,2,FALSE) -> 总工办 | F33: =VLOOKUP(C33,[2]在职人员信息表!$F:$H,3,FALSE) -> 总工办职员 | G33: 正经理级/副矿级 | H33: =VLOOKUP(C33,[2]任职汇总表!$D:$I,6,FALSE()) -> 43556 | I33: 400
A34: 31 | C34: 吴运标 | D34: =VLOOKUP(C34,[2]在职人员信息表!$F:$U,16,FALSE) -> 340621197702275610 | E34: =VLOOKUP(C34,[2]在职人员信息表!$F:$G,2,FALSE) -> 总工办 | F34: =VLOOKUP(C34,[2]在职人员信息表!$F:$H,3,FALSE) -> 总工办职员 | G34: 正经理级/副矿级 | H34: =VLOOKUP(C34,[2]任职汇总表!$D:$I,6,FALSE()) -> 45289 | I34: 400
A35: 32 | C35: 白新江 | D35: =VLOOKUP(C35,[2]在职人员信息表!$F:$U,16,FALSE) -> 140224198001280630 | E35: =VLOOKUP(C35,[2]在职人员信息表!$F:$G,2,FALSE) -> 总工办 | F35: =VLOOKUP(C35,[2]在职人员信息表!$F:$H,3,FALSE) -> 总工办主任 | G35: 正经理级/副矿级 | H35: =VLOOKUP(C35,[2]任职汇总表!$D:$I,6,FALSE()) -> 45630 | I35: 400
A36: 33 | C36: 刘栓柱 | D36: =VLOOKUP(C36,[2]在职人员信息表!$F:$U,16,FALSE) -> 130521197011257013 | E36: =VLOOKUP(C36,[2]在职人员信息表!$F:$G,2,FALSE) -> 总工办 | F36: =VLOOKUP(C36,[2]在职人员信息表!$F:$H,3,FALSE) -> 总工办职员 | G36: 正经理级/副矿级 | H36: =VLOOKUP(C36,[2]任职汇总表!$D:$I,6,FALSE()) -> 45630 | I36: 400
A37: 34 | C37: 郝春红 | D37: =VLOOKUP(C37,[2]在职人员信息表!$F:$U,16,FALSE) -> 231026198311142342 | E37: =VLOOKUP(C37,[2]在职人员信息表!$F:$G,2,FALSE) -> 经营管理部 | F37: =VLOOKUP(C37,[2]在职人员信息表!$F:$H,3,FALSE) -> 经理 | G37: 正经理级/副矿级 | H37: =VLOOKUP(C37,[2]任职汇总表!$D:$I,6,FALSE()) -> 45505 | I37: 400
A38: 35 | C38: 张广振 | D38: =VLOOKUP(C38,[2]在职人员信息表!$F:$U,16,FALSE) -> 370881198111304835 | E38: =VLOOKUP(C38,[2]在职人员信息表!$F:$G,2,FALSE) -> 综采队 | F38: =VLOOKUP(C38,[2]在职人员信息表!$F:$H,3,FALSE) -> 常务副队长 | G38: 副经理级/正科级 | H38: =VLOOKUP(C38,[2]任职汇总表!$D:$I,6,FALSE()) -> 45090 | I38: 300
A39: 36 | C39: 荣启亭 | D39: =VLOOKUP(C39,[2]在职人员信息表!$F:$U,16,FALSE) -> 370983198101161832 | E39: =VLOOKUP(C39,[2]在职人员信息表!$F:$G,2,FALSE) -> 综掘队 | F39: =VLOOKUP(C39,[2]在职人员信息表!$F:$H,3,FALSE) -> 队长 | G39: 副经理级/正科级 | H39: =VLOOKUP(C39,[2]任职汇总表!$D:$I,6,FALSE()) -> 45866 | I39: 300
A40: 37 | C40: 贺伟 | D40: =VLOOKUP(C40,[2]在职人员信息表!$F:$U,16,FALSE) -> 15272319861209601X | E40: =VLOOKUP(C40,[2]在职人员信息表!$F:$G,2,FALSE) -> 安全监察科 | F40: =VLOOKUP(C40,[2]在职人员信息表!$F:$H,3,FALSE) -> 科长 | G40: 副经理级/正科级 | H40: =VLOOKUP(C40,[2]任职汇总表!$D:$I,6,FALSE()) -> 45145 | I40: 300
A41: 38 | C41: 王亮勋 | D41: =VLOOKUP(C41,[2]在职人员信息表!$F:$U,16,FALSE) -> 410622197402106035 | E41: =VLOOKUP(C41,[2]在职人员信息表!$F:$G,2,FALSE) -> 选煤厂 | F41: =VLOOKUP(C41,[2]在职人员信息表!$F:$H,3,FALSE) -> 安全副厂长 | G41: 副经理级/正科级 | H41: =VLOOKUP(C41,[2]任职汇总表!$D:$I,6,FALSE()) -> 44210 | I41: 300
A42: 39 | C42: 任建龙 | D42: =VLOOKUP(C42,[2]在职人员信息表!$F:$U,16,FALSE) -> 152723198804241517 | E42: =VLOOKUP(C42,[2]在职人员信息表!$F:$G,2,FALSE) -> 总调度室 | F42: =VLOOKUP(C42,[2]在职人员信息表!$F:$H,3,FALSE) -> 主任 | G42: 副经理级/正科级 | H42: =VLOOKUP(C42,[2]任职汇总表!$D:$I,6,FALSE()) -> 45866 | I42: 300
A43: 40 | C43: 陈建军 | D43: =VLOOKUP(C43,[2]在职人员信息表!$F:$U,16,FALSE) -> 410107196310270510 | E43: =VLOOKUP(C43,[2]在职人员信息表!$F:$G,2,FALSE) -> 机电科 | F43: =VLOOKUP(C43,[2]在职人员信息表!$F:$H,3,FALSE) -> 工程师 | G43: 副经理级/正科级 | H43: =VLOOKUP(C43,[2]任职汇总表!$D:$I,6,FALSE()) -> 44608 | I43: 300
... A52: 49 | C52: 张启鹏 | D52: =VLOOKUP(C52,[2]在职人员信息表!$F:$U,16,FALSE) -> 152723198104171810 | E52: =VLOOKUP(C52,[2]在职人员信息表!$F:$G,2,FALSE) -> 多种经营部-多经 | F52: =VLOOKUP(C52,[2]在职人员信息表!$F:$H,3,FALSE) -> 副经理 | G52: 副经理级/正科级 | H52: =VLOOKUP(C52,[2]任职汇总表!$D:$I,6,FALSE()) -> 44202 | I52: 300
A53: 50 | C53: 王海军 | D53: 152723198009280912 | E53: 复垦绿化队 | F53: 队长 | G53: 副经理级/正科级 | H53: =VLOOKUP(C53,[2]任职汇总表!$D:$I,6,FALSE()) -> 43164 | I53: 300
A54: 51 | C54: 杨培 | D54: =VLOOKUP(C54,[2]在职人员信息表!$F:$U,16,FALSE) -> 152723198612071517 | E54: =VLOOKUP(C54,[2]在职人员信息表!$F:$G,2,FALSE) -> 综采队 | F54: =VLOOKUP(C54,[2]在职人员信息表!$F:$H,3,FALSE) -> 副队长 | G54: 副科级/经理助理/主管 | H54: =VLOOKUP(C54,[2]任职汇总表!$D:$I,6,FALSE()) -> 44958 | I54: 200
A55: 52 | C55: 商好学 | D55: =VLOOKUP(C55,[2]在职人员信息表!$F:$U,16,FALSE) -> 370826197111153732 | E55: =VLOOKUP(C55,[2]在职人员信息表!$F:$G,2,FALSE) -> 综采队 | F55: =VLOOKUP(C55,[2]在职人员信息表!$F:$H,3,FALSE) -> 副队长 | G55: 副科级/经理助理/主管 | H55: =VLOOKUP(C55,[2]任职汇总表!$D:$I,6,FALSE()) -> 44958 | I55: 200
A56: 53 | C56: 杨肖 | D56: =VLOOKUP(C56,[2]在职人员信息表!$F:$U,16,FALSE) -> 320322198908010811 | E56: =VLOOKUP(C56,[2]在职人员信息表!$F:$G,2,FALSE) -> 综采队 | F56: =VLOOKUP(C56,[2]在职人员信息表!$F:$H,3,FALSE) -> 综采安装材料主管 | G56: 副科级/经理助理/主管 | I56: 200 | K56: 调动单
A57: 54 | C57: 尹树山 | D57: =VLOOKUP(C57,[2]在职人员信息表!$F:$U,16,FALSE) -> 130227197307093611 | E57: =VLOOKUP(C57,[2]在职人员信息表!$F:$G,2,FALSE) -> 综采队 | F57: =VLOOKUP(C57,[2]在职人员信息表!$F:$H,3,FALSE) -> 副队长 | G57: 副科级/经理助理/主管 | H57: =VLOOKUP(C57,[2]任职汇总表!$D:$I,6,FALSE()) -> 44958 | I57: 200
A58: 55 | C58: 张坤 | D58: =VLOOKUP(C58,[2]在职人员信息表!$F:$U,16,FALSE) -> 211404198108276230 | E58: =VLOOKUP(C58,[2]在职人员信息表!$F:$G,2,FALSE) -> 综采队 | F58: =VLOOKUP(C58,[2]在职人员信息表!$F:$H,3,FALSE) -> 副队长 | G58: 副科级/经理助理/主管 | H58: =VLOOKUP(C58,[2]任职汇总表!$D:$I,6,FALSE()) -> 44958 | I58: 200
A59: 56 | C59: 索爱军 | D59: =VLOOKUP(C59,[2]在职人员信息表!$F:$U,16,FALSE) -> 130406198501023012 | E59: =VLOOKUP(C59,[2]在职人员信息表!$F:$G,2,FALSE) -> 综掘队 | F59: =VLOOKUP(C59,[2]在职人员信息表!$F:$H,3,FALSE) -> 副队长 | G59: 副科级/经理助理/主管 | H59: =VLOOKUP(C59,[2]任职汇总表!$D:$I,6,FALSE()) -> 44964 | I59: 200
A60: 57 | C60: 刘凤山 | D60: =VLOOKUP(C60,[2]在职人员信息表!$F:$U,16,FALSE) -> 150429197812103435 | E60: =VLOOKUP(C60,[2]在职人员信息表!$F:$G,2,FALSE) -> 综掘队 | F60: =VLOOKUP(C60,[2]在职人员信息表!$F:$H,3,FALSE) -> 副队长 | G60: 副科级/经理助理/主管 | H60: =VLOOKUP(C60,[2]任职汇总表!$D:$I,6,FALSE()) -> 44964 | I60: 200
A61: 58 | C61: 索爱国 | D61: =VLOOKUP(C61,[2]在职人员信息表!$F:$U,16,FALSE) -> 130406197709293017 | E61: =VLOOKUP(C61,[2]在职人员信息表!$F:$G,2,FALSE) -> 综掘队 | F61: =VLOOKUP(C61,[2]在职人员信息表!$F:$H,3,FALSE) -> 副队长 | G61: 副科级/经理助理/主管 | H61: =VLOOKUP(C61,[2]任职汇总表!$D:$I,6,FALSE()) -> 45881 | I61: 200
A62: 59 | C62: 郭小强 | D62: =VLOOKUP(C62,[2]在职人员信息表!$F:$U,16,FALSE) -> 612729199008286611 | E62: =VLOOKUP(C62,[2]在职人员信息表!$F:$G,2,FALSE) -> 安全监察科 | F62: =VLOOKUP(C62,[2]在职人员信息表!$F:$H,3,FALSE) -> 副科长 | G62: 副科级/经理助理/主管 | H62: =VLOOKUP(C62,[2]任职汇总表!$D:$I,6,FALSE()) -> 44607 | I62: 200
A63: 60 | C63: 程学军 | D63: =VLOOKUP(C63,[2]在职人员信息表!$F:$U,16,FALSE) -> 130406196609090912 | E63: =VLOOKUP(C63,[2]在职人员信息表!$F:$G,2,FALSE) -> 机运队 | F63: =VLOOKUP(C63,[2]在职人员信息表!$F:$H,3,FALSE) -> 副队长 | G63: 副科级/经理助理/主管 | H63: =VLOOKUP(C63,[2]任职汇总表!$D:$I,6,FALSE()) -> 41432 | I63: 200
A64: 61 | C64: 李龙博 | D64: =VLOOKUP(C64,[2]在职人员信息表!$F:$U,16,FALSE) -> 130522199008162414 | E64: =VLOOKUP(C64,[2]在职人员信息表!$F:$G,2,FALSE) -> 机运队 | F64: =VLOOKUP(C64,[2]在职人员信息表!$F:$H,3,FALSE) -> 副队长 | G64: 副科级/经理助理/主管 | H64: =VLOOKUP(C64,[2]任职汇总表!$D:$I,6,FALSE()) -> 44653 | I64: 200
A65: 62 | C65: 孙珠红 | D65: =VLOOKUP(C65,[2]在职人员信息表!$F:$U,16,FALSE) -> 140524197512100517 | E65: =VLOOKUP(C65,[2]在职人员信息表!$F:$G,2,FALSE) -> 机运队 | F65: =VLOOKUP(C65,[2]在职人员信息表!$F:$H,3,FALSE) -> 检修班班长 | G65: 副科级/经理助理/主管 | H65: =VLOOKUP(C65,[2]任职汇总表!$D:$I,6,FALSE()) -> 45012 | I65: 200
A66: 63 | C66: 贾喜钢 | D66: =VLOOKUP(C66,[2]在职人员信息表!$F:$U,16,FALSE) -> 150304197409132014 | E66: =VLOOKUP(C66,[2]在职人员信息表!$F:$G,2,FALSE) -> 选煤厂 | F66: =VLOOKUP(C66,[2]在职人员信息表!$F:$H,3,FALSE) -> 主洗主管 | G66: 副科级/经理助理/主管 | H66: =VLOOKUP(C66,[2]任职汇总表!$D:$I,6,FALSE()) -> 43164 | I66: 200
A67: 64 | C67: 艾祖国 | D67: =VLOOKUP(C67,[2]在职人员信息表!$F:$U,16,FALSE) -> 510224197408103737 | E67: =VLOOKUP(C67,[2]在职人员信息表!$F:$G,2,FALSE) -> 选煤厂 | F67: =VLOOKUP(C67,[2]在职人员信息表!$F:$H,3,FALSE) -> 机修副班长 | G67: 副科级/经理助理/主管 | H67: =VLOOKUP(C67,[2]任职汇总表!$D:$I,6,FALSE()) -> 45012 | I67: 200
A68: 65 | C68: 王恒 | D68: =VLOOKUP(C68,[2]在职人员信息表!$F:$U,16,FALSE) -> 152824199002213334 | E68: =VLOOKUP(C68,[2]在职人员信息表!$F:$G,2,FALSE) -> 总调度室 | F68: =VLOOKUP(C68,[2]在职人员信息表!$F:$H,3,FALSE) -> 副主任 | G68: 副科级/经理助理/主管 | H68: =VLOOKUP(C68,[2]任职汇总表!$D:$I,6,FALSE()) -> 45012 | I68: 200
... A78: 75 | C78: 董武 | D78: =VLOOKUP(C78,[2]在职人员信息表!$F:$U,16,FALSE) -> 362202196604181557 | E78: =VLOOKUP(C78,[2]在职人员信息表!$F:$G,2,FALSE) -> 生产机修科 | F78: =VLOOKUP(C78,[2]在职人员信息表!$F:$H,3,FALSE) -> 副主任工程师 | G78: 副科级/经理助理/主管 | H78: =VLOOKUP(C78,[2]任职汇总表!$D:$I,6,FALSE()) -> 45012 | I78: 200
A79: 76 | C79: 刘智强 | D79: =VLOOKUP(C79,[2]在职人员信息表!$F:$U,16,FALSE) -> 152723198901015714 | E79: =VLOOKUP(C79,[2]在职人员信息表!$F:$G,2,FALSE) -> 生产机修科 | F79: =VLOOKUP(C79,[2]在职人员信息表!$F:$H,3,FALSE) -> 主管 | G79: 副科级/经理助理/主管 | I79: 200 | K79: 调动单
A80: 77 | C80: 李纪宏 | D80: =VLOOKUP(C80,[2]在职人员信息表!$F:$U,16,FALSE) -> 152723199507254519 | E80: =VLOOKUP(C80,[2]在职人员信息表!$F:$G,2,FALSE) -> 开发部 | F80: =VLOOKUP(C80,[2]在职人员信息表!$F:$H,3,FALSE) -> 主管 | G80: 副科级/经理助理/主管 | H80: =VLOOKUP(C80,[2]任职汇总表!$D:$I,6,FALSE()) -> 45881 | I80: 200 | J80: 1000
A81: 78 | C81: 刘彦彤 | D81: =VLOOKUP(C81,[2]在职人员信息表!$F:$U,16,FALSE) -> 152722199101102121 | E81: =VLOOKUP(C81,[2]在职人员信息表!$F:$G,2,FALSE) -> 开发部 | F81: =VLOOKUP(C81,[2]在职人员信息表!$F:$H,3,FALSE) -> 主管 | G81: 副科级/经理助理/主管 | H81: =VLOOKUP(C81,[2]任职汇总表!$D:$I,6,FALSE()) -> 45881 | I81: 200 | J81: 1000
A82: 79 | C82: 王琴 | D82: =VLOOKUP(C82,[2]在职人员信息表!$F:$U,16,FALSE) -> 150122198802032649 | E82: =VLOOKUP(C82,[2]在职人员信息表!$F:$G,2,FALSE) -> 财务部 | F82: =VLOOKUP(C82,[2]在职人员信息表!$F:$H,3,FALSE) -> 融资主管 | G82: 副科级/经理助理/主管 | H82: =VLOOKUP(C82,[2]任职汇总表!$D:$I,6,FALSE()) -> 44721 | I82: 200
A83: 80 | C83: 周婷 | D83: =VLOOKUP(C83,[2]在职人员信息表!$F:$U,16,FALSE) -> 152723199107040925 | E83: =VLOOKUP(C83,[2]在职人员信息表!$F:$G,2,FALSE) -> 财务部 | F83: =VLOOKUP(C83,[2]在职人员信息表!$F:$H,3,FALSE) -> 会计主管 | G83: 副科级/经理助理/主管 | H83: =VLOOKUP(C83,[2]任职汇总表!$D:$I,6,FALSE()) -> 44721 | I83: 200
A84: 81 | C84: 訾园 | D84: =VLOOKUP(C84,[2]在职人员信息表!$F:$U,16,FALSE) -> 152722199302010020 | E84: =VLOOKUP(C84,[2]在职人员信息表!$F:$G,2,FALSE) -> 人力行政中心 | F84: =VLOOKUP(C84,[2]在职人员信息表!$F:$H,3,FALSE) -> 主管 | G84: 副科级/经理助理/主管 | H84: =VLOOKUP(C84,[2]任职汇总表!$D:$I,6,FALSE()) -> 45145 | I84: 200
A85: 82 | C85: 张永春 | D85: =VLOOKUP(C85,[2]在职人员信息表!$F:$U,16,FALSE) -> 15272319900608091X | E85: =VLOOKUP(C85,[2]在职人员信息表!$F:$G,2,FALSE) -> 人力行政中心 | F85: =VLOOKUP(C85,[2]在职人员信息表!$F:$H,3,FALSE) -> 人力行政中心主管 | G85: 副科级/经理助理/主管 | H85: =VLOOKUP(C85,[2]任职汇总表!$D:$I,6,FALSE()) -> 44607 | I85: 200
A86: 83 | C86: 杨学塨 | D86: =VLOOKUP(C86,[2]在职人员信息表!$F:$U,16,FALSE) -> 132124198001280192 | E86: =VLOOKUP(C86,[2]在职人员信息表!$F:$G,2,FALSE) -> 人力行政中心 | F86: =VLOOKUP(C86,[2]在职人员信息表!$F:$H,3,FALSE) -> 车辆主管 | G86: 副科级/经理助理/主管 | H86: =VLOOKUP(C86,[2]任职汇总表!$D:$I,6,FALSE()) -> 44324 | I86: 200
A87: 84 | C87: 马二苗 | D87: =VLOOKUP(C87,[2]在职人员信息表!$F:$U,16,FALSE) -> 150221198707204413 | E87: =VLOOKUP(C87,[2]在职人员信息表!$F:$G,2,FALSE) -> 人力行政中心-安保 | F87: =VLOOKUP(C87,[2]在职人员信息表!$F:$H,3,FALSE) -> 副科长 | G87: 副科级/经理助理/主管 | H87: =VLOOKUP(C87,[2]任职汇总表!$D:$I,6,FALSE()) -> 44636 | I87: 200
A88: 85 | C88: 刘伟 | D88: =VLOOKUP(C88,[2]在职人员信息表!$F:$U,16,FALSE) -> 152723199209070930 | E88: =VLOOKUP(C88,[2]在职人员信息表!$F:$G,2,FALSE) -> 法务监察部 | F88: =VLOOKUP(C88,[2]在职人员信息表!$F:$H,3,FALSE) -> 副主任法务监察员 | G88: 副科级/经理助理/主管 | H88: =VLOOKUP(C88,[2]任职汇总表!$D:$I,6,FALSE()) -> 45028 | I88: 200
A89: 86 | C89: 顾群亮 | D89: =VLOOKUP(C89,[2]在职人员信息表!$F:$U,16,FALSE) -> 411081197104216859 | E89: =VLOOKUP(C89,[2]在职人员信息表!$F:$G,2,FALSE) -> 总工办 | F89: =VLOOKUP(C89,[2]在职人员信息表!$F:$H,3,FALSE) -> 总工办职员 | G89: 副科级/经理助理/主管 | H89: =VLOOKUP(C89,[2]任职汇总表!$D:$I,6,FALSE()) -> 45630 | I89: 200
A90: 87 | C90: 高西海 | D90: =VLOOKUP(C90,[2]在职人员信息表!$F:$U,16,FALSE) -> 150304196611143011 | E90: =VLOOKUP(C90,[2]在职人员信息表!$F:$G,2,FALSE) -> 总工办 | F90: =VLOOKUP(C90,[2]在职人员信息表!$F:$H,3,FALSE) -> 总工办职员 | G90: 副科级/经理助理/主管 | H90: =VLOOKUP(C90,[2]任职汇总表!$D:$I,6,FALSE()) -> 45423 | I90: 200
A91: 88 | C91: 郭永旭 | D91: =VLOOKUP(C91,[2]在职人员信息表!$F:$U,16,FALSE) -> 152723198911097215 | E91: =VLOOKUP(C91,[2]在职人员信息表!$F:$G,2,FALSE) -> 经营管理部 | F91: =VLOOKUP(C91,[2]在职人员信息表!$F:$H,3,FALSE) -> 主管 | G91: 副科级/经理助理/主管 | H91: =VLOOKUP(C91,[2]任职汇总表!$D:$I,6,FALSE()) -> 45532 | I91: 200
A92: 89 | C92: 车立鹏 | D92: =VLOOKUP(C92,[2]在职人员信息表!$F:$U,16,FALSE) -> 150403199207084518 | E92: =VLOOKUP(C92,[2]在职人员信息表!$F:$G,2,FALSE) -> 经营管理部 | F92: =VLOOKUP(C92,[2]在职人员信息表!$F:$H,3,FALSE) -> 副主任工程师 | G92: 副科级/经理助理/主管 | H92: =VLOOKUP(C92,[2]任职汇总表!$D:$I,6,FALSE()) -> 44610 | I92: 200
A93: 90 | C93: 赵智巍 | D93: =VLOOKUP(C93,[2]在职人员信息表!$F:$U,16,FALSE) -> 152629198305242593 | E93: =VLOOKUP(C93,[2]在职人员信息表!$F:$G,2,FALSE) -> 经营管理部 | F93: =VLOOKUP(C93,[2]在职人员信息表!$F:$H,3,FALSE) -> 造价工程师 | G93: 副科级/经理助理/主管 | H93: =VLOOKUP(C93,[2]任职汇总表!$D:$I,6,FALSE()) -> 44609 | I93: 200
A94: 91 | C94: 鲁当军 | D94: =VLOOKUP(C94,[2]在职人员信息表!$F:$U,16,FALSE) -> 152723197407195719 | E94: =VLOOKUP(C94,[2]在职人员信息表!$F:$G,2,FALSE) -> 复垦绿化队 | F94: =VLOOKUP(C94,[2]在职人员信息表!$F:$H,3,FALSE) -> 副队长 | G94: 副科级/经理助理/主管 | H94: =VLOOKUP(C94,[2]任职汇总表!$D:$I,6,FALSE()) -> 44653 | I94: 200
A95: 合计 | I95: =SUM(I4:I94) -> 30000 | J95: =SUM(J4:J94) -> 5600

Sheet Sheet2

Sheet 2025培训费
A1: 内蒙古准格尔旗力量煤业有限公司人员2024年员工福利档案
A2: 截至2021年XX月XX日在职员工共计XXX人（本月新入职XX人，离职XX人，XX人内部调动，XX人外部调动）。
A3: 序号 | B3: 部门 | C3: 姓名 | D3: 职务 | E3: 身份证号 | F3: 联系电话
G4: 培训服务期 | J4: 培训服务期 | M4: 培训服务期 | P4: 培训服务期 | S4: 培训服务期 | V4: 备注
G5: 开始时间 | H5: 结束时间 | I5: 金额 | J5: 开始时间 | K5: 结束时间 | L5: 金额 | M5: 开始时间 | N5: 结束时间 | O5: 金额 | P5: 开始时间 | Q5: 结束时间 | R5: 金额 | S5: 开始时间 | T5: 结束时间 | U5: 金额
A6: M10000 | B6: 李波 | C6: 公司领导 | D6: 管理岗 | E6: 130522198205272415 | F6: -
B7: 章杨
A8: M10001 | B8: 刘冠杰 | C8: 公司领导 | D8: 管理岗 | E8: 152723196312021818 | F8: -
A9: M10002 | B9: 李运成 | C9: 公司领导 | D9: 管理岗 | E9: 130503196610061234 | F9: -
A10: M10003 | B10: 奚明 | C10: 公司领导 | D10: 管理岗 | E10: 21128219830626081X | F10: -
A11: M10004 | B11: 窦发权 | C11: 公司领导 | D11: 管理岗 | E11: 370902197109021292 | F11: -
A12: M10005 | B12: 马天峰 | C12: 公司领导 | D12: 管理岗 | E12: 640204196305152033 | F12: -
A13: M10006 | B13: 李印楼 | C13: 公司领导 | D13: 管理岗 | E13: 320322197003037337 | F13: -
A14: M10007 | B14: 宋云飞 | C14: 公司领导 | D14: 管理岗 | E14: 230822198111094910 | F14: -
A15: M10008 | B15: 周洪刚 | C15: 公司领导 | D15: 管理岗 | E15: 130403196411292114 | F15: -
A16: M10011 | B16: 王震 | C16: 公司领导 | D16: 管理岗 | E16: 152723198509184812 | F16: -
A17: M10172 | B17: 李秦生 | C17: 矿级领导 | D17: 管理岗 | E17: 362329198611264574 | F17: 15847702155
A18: M10412 | B18: 杨维海 | C18: 矿级领导 | D18: 管理岗 | E18: 340403197510102439 | F18: 15847076472
A19: M10283 | B19: 郭洪亮 | C19: 矿级领导 | D19: 管理岗 | E19: 230303198407064239 | F19: 18646751172 | G19: 45826 | H19: 45828 | I19: 400 | J19: 45839 | K19: 45844 | L19: 3400
A20: M10696 | B20: 刘栓柱 | C20: 矿级领导 | D20: 管理岗 | E20: 130521197011257013 | F20: 18647722268
A21: P10726 | B21: 高翔 | C21: 矿级领导 | D21: 管理岗 | E21: 14010219810504601X | F21: 13834280786 | G21: 45755 | H21: 45761 | I21: 4695 | J21: 45830 | K21: 45835 | L21: 3452.67
A22: P10866 | B22: 王荣 | C22: 矿级领导 | D22: 管理岗 | E22: 140581198801043215 | F22: 13834939720
A23: P10572 | B23: 陈永清 | C23: 矿级领导 | D23: 管理岗 | E23: 230321197809105011 | F23: 13834494335 | G23: 45818 | H23: 45823 | I23: 3400
A24: F10133 | B24: 管云丰 | C24: 矿级领导 | D24: 管理岗 | E24: 13262419740427753X | F24: 15149539452
B25: 谈安彬 | G25: 45696 | H25: 45703 | I25: 4153.86 | J25: 45791 | K25: 45799 | L25: 4619.97
A26: F10879 | B26: 孙启明 | C26: 综采队 | D26: 管理岗 | E26: 150428198903200159 | F26: 15149739502
A27: F10789 | B27: 张广振 | C27: 综采队 | D27: 管理岗 | E27: 370881198111304835 | F27: 18754751818
A28: F10868 | B28: 杨培 | C28: 综采队 | D28: 专业技术岗 | E28: 152723198612071517 | F28: 15947364973
A29: F10571 | B29: 商好学 | C29: 综采队 | D29: 专业技术岗 | E29: 370826197111153732 | F29: 15054887907
A30: F10658 | B30: 杨肖 | C30: 综采队 | D30: 专业技术岗 | E30: 320322198908010811 | F30: 13734830459
A31: S10926 | B31: 蔡庆鑫 | C31: 综采队 | D31: 专业技术岗 | E31: 152128199611050910 | F31: 15848627873
A32: M10818 | B32: 贾云云 | C32: 综采队 | D32: 专业技术岗 | E32: 140428199405043261 | F32: 15698615326
A33: M10115 | B33: 张向辉 | C33: 综采队 | D33: 工人岗 | E33: 220881197811216011 | F33: 15947177929
A34: M10519 | B34: 薛宪伟 | C34: 综采队 | D34: 工人岗 | E34: 320322198604162517 | F34: 18247708003
A35: P10685 | B35: 张延朝 | C35: 综采队 | D35: 工人岗 | E35: 132202198001264632 | F35: 15028919688
A36: P10797 | B36: 韩志发 | C36: 综采队 | D36: 工人岗 | E36: 132224197605111657 | F36: 15289211913
A37: P10746 | B37: 雷铁柱 | C37: 综采队 | D37: 工人岗 | E37: 130822197805036231 | F37: 15233372187
... A51: P10832 | B51: 刘新 | C51: 综采队 | D51: 工人岗 | E51: 210124197404192617 | F51: 17097446118
A52: P10525 | B52: 杨纪仓 | C52: 综采队 | D52: 工人岗 | E52: 370826198403242838 | F52: 15149436941 | G52: 45663 | H52: 45667 | I52: 900
A53: P10195 | B53: 马小平 | C53: 综采队 | D53: 工人岗 | E53: 152722197911043910 | F53: 15049436437
A54: P10488 | B54: 从晓岭 | C54: 综采队 | D54: 工人岗 | E54: 150426197806080397 | F54: 18748018119
A55: P10623 | B55: 宋云河 | C55: 综采队 | D55: 工人岗 | E55: 230221197506184212 | F55: 18947574241
A56: S10823 | B56: 郝云石 | C56: 综采队 | D56: 工人岗 | E56: 130523198310251698 | F56: 13111206735
A57: F10921 | B57: 付相红 | C57: 综采队 | D57: 工人岗 | E57: 370829199012251730 | F57: 17560748497 | G57: 45819 | H57: 45834 | I57: 5600
A58: F10410 | B58: 葛兵祥 | C58: 综采队 | D58: 工人岗 | E58: 320322197303160812 | F58: 15149676232
A59: F10897 | B59: 卢志远 | C59: 综采队 | D59: 工人岗 | E59: 411081197212076857 | F59: 18204773370
A60: F10124 | B60: 殷俊红 | C60: 综采队 | D60: 工人岗 | E60: 411081197207251278 | F60: 15147737964
A61: F10471 | B61: 陈春余 | C61: 综采队 | D61: 工人岗 | E61: 130226197212015251 | F61: 15147790535
A62: F10419 | B62: 李艳奎 | C62: 综采队 | D62: 工人岗 | E62: 130227197205263616 | F62: 15147521056
A63: M10010 | B63: 徐建岗 | C63: 综采队 | D63: 工人岗 | E63: 32032219760714087X | F63: 18648373361
A64: M10141 | B64: 王得祥 | C64: 安装队 | D64: 工人岗 | E64: 150429197608174834 | F64: 13624870469
A65: M10911 | B65: 董少尉 | C65: 综采队 | D65: 工人岗 | E65: 13052119770220157X | F65: 15049897592
A66: M10872 | B66: 王杰 | C66: 综采队 | D66: 工人岗 | E66: 150428198604030110 | F66: 13191375855
A67: P10768 | B67: 陈肖铮 | C67: 综采队 | D67: 工人岗 | E67: 130521198510127015 | F67: 18931935281
A68: P10380 | B68: 赵新春 | C68: 综采队 | D68: 工人岗 | E68: 511304198312232011 | F68: 18875760907
A69: P10916 | B69: 程永平 | C69: 综采队 | D69: 工人岗 | E69: 610523198301139076 | F69: 13379448163
... A93: T10742 | B93: 乔田靖 | C93: 综采队 | D93: 工人岗 | E93: 130521198210097010 | F93: 15194937837
A94: T10776 | B94: 翟晓东 | C94: 综采队 | D94: 工人岗 | E94: 150428198501210135 | F94: 15849674883
A95: T10772 | B95: 赵鹏飞 | C95: 综采队 | D95: 工人岗 | E95: 150428198012182313 | F95: 15947165203
A96: M10113 | B96: 马小东 | C96: 综采队 | D96: 工人岗 | E96: 130521198210167015 | F96: 15134905646
A97: P10376 | B97: 齐学军 | C97: 综采队 | D97: 工人岗 | E97: 150428197305172077 | F97: 18248332383
A98: P10109 | B98: 于国富 | C98: 综采队 | D98: 工人岗 | E98: 150428198109260111 | F98: 18204776286
A99: M10313 | B99: 张洪亮 | C99: 综采队 | D99: 工人岗 | E99: 370404196911066237 | F99: 13336371106
A100: P10660 | B100: 纪文德 | C100: 综采队 | D100: 工人岗 | E100: 231026197510163117 | F100: 15047727189
A101: P10674 | B101: 孙磊 | C101: 综采队 | D101: 工人岗 | E101: 320305198203071511 | F101: 14752261170
A102: M10192 | B102: 杨生龙 | C102: 综采队 | D102: 工人岗 | E102: 130426198806072339 | F102: 15081073235
A103: M10293 | B103: 张灿伟 | C103: 综采队 | D103: 工人岗 | E103: 370982198510166515 | F103: 13562834110
A104: M10111 | B104: 张大锋 | C104: 综采队 | D104: 工人岗 | E104: 372525198007101637 | F104: 13181092991
A105: M10294 | B105: 周红东 | C105: 综采队 | D105: 工人岗 | E105: 610623197501181018 | F105: 18992151048
A106: M10104 | B106: 张超 | C106: 综采队 | D106: 工人岗 | E106: 150426197912153799 | F106: 15149909936 | G106: 45659 | H106: 45670 | I106: 2100
A107: M10277 | B107: 赵云峰 | C107: 综采队 | D107: 工人岗 | E107: 15042819790611231x | F107: 15149181848
A108: M10324 | B108: 孙福海 | C108: 综采队 | D108: 工人岗 | E108: 230183197510203010 | F108: 18246713938
A109: M10292 | B109: 李帅 | C109: 综采队 | D109: 工人岗 | E109: 411325199008012359 | F109: 18819806653
A110: P10507 | B110: 黄运峰 | C110: 综采队 | D110: 工人岗 | E110: 230183198605104837 | F110: 13134855177 | G110: 45663 | H110: 45667 | I110: 630
A111: P10332 | B111: 马立军 | C111: 综采队 | D111: 工人岗 | E111: 130521198212097276 | F111: 17745700976
A112: P10537 | B112: 李勇 | C112: 综采队 | D112: 工人岗 | E112: 130521198505067054 | F112: 13730138396
A113: P10837 | B113: 王明富 | C113: 综采队 | D113: 工人岗 | E113: 130521198605067019 | F113: 18331918073
A114: P10827 | B114: 张志军 | C114: 综采队 | D114: 工人岗 | E114: 140427197906012011 | F114: 17636353991
A115: P10521 | B115: 李芳波 | C115: 综采队 | D115: 工人岗 | E115: 362321197911161010 | F115: 15180336296
A116: P10686 | B116: 王京敏 | C116: 综采队 | D116: 工人岗 | E116: 130521198206167012 | F116: 18714256218 | G116: 45722 | H116: 45732 | I116: 1600
A117: P10476 | B117: 李鹏飞 | C117: 综采队 | D117: 工人岗 | E117: 142228199006178514 | F117: 13754884545
B118: 杨宏磊
B119: 刘俊杰
A120: S10859 | B120: 骞庆宾 | C120: 综采队 | D120: 工人岗 | E120: 130521198311093510 | F120: 18617629976
A121: S10924 | B121: 乔瑾 | C121: 综采队 | D121: 工人岗 | E121: 150124198707112758 | F121: 14747343285
A122: S10815 | B122: 高二军 | C122: 综采队 | D122: 工人岗 | E122: 320322197902151619 | F122: 15190650361
A123: F10433 | B123: 师志峰 | C123: 综采队 | D123: 工人岗 | E123: 132132197904051513 | F123: 15130002166
A124: F10411 | B124: 李航 | C124: 综采队 | D124: 工人岗 | E124: 130123199203023916 | F124: 17736948866
A125: F10738 | B125: 高义辉 | C125: 综采队 | D125: 工人岗 | E125: 23213119900718251X | F125: 15047313770
A126: F10347 | B126: 刘振伟 | C126: 综采队 | D126: 工人岗 | E126: 142232198109278438 | F126: 15935009850 | G126: 45819 | H126: 45834 | I126: 5600
A127: F10351 | B127: 王文广 | C127: 综采队 | D127: 工人岗 | E127: 130521198801217037 | F127: 15030902052
A128: F10560 | B128: 侯现勇 | C128: 综采队 | D128: 工人岗 | E128: 370883198101151639 | F128: 15849909747
A129: F10874 | B129: 徐志明 | C129: 综采队 | D129: 工人岗 | E129: 370882198010084219 | F129: 15154762232
A130: F10640 | B130: 兰豪 | C130: 综采队 | D130: 工人岗 | E130: 41048219780809501X | F130: 18211985987
A131: F10715 | B131: 李振中 | C131: 综采队 | D131: 工人岗 | E131: 150428198005232319 | F131: 18347634928
A132: F10710 | B132: 刘文 | C132: 综采队 | D132: 工人岗 | E132: 150429197702023418 | F132: 15949435930
B133: 田中凯 | G133: 45714 | H133: 45723 | I133: 1600
B134: 江洪涛 | G134: 45714 | H134: 45723 | I134: 1600
B135: 杨亮 | G135: 45714 | H135: 45723 | I135: 1600
B136: 熊永举 | G136: 45714 | H136: 45723 | I136: 1600
...

Sheet 在职人员信息表（2023年电话费全部人员情况）
A1: 序号 | B1: 身份证号码 | C1: 工作单位 | D1: 人员构成 | E1: 工号 | F1: 姓名 | G1: 2022年报销 | H1: 2023年报销 | I1: 2022-2023报销合计 | J1: 工作部门 | K1: 岗位 | L1: 话费开始报销月份 | M1: 报销依据 | N1: 报销标准 | O1: 最终审批人 | P1: 是否有扫描件 | Q1: 兼职岗位/轮岗部门 | R1: 岗位类别 | S1: 级别 | T1: 人员 类别 | U1: 入职时间 | V1: 司龄 | W1: 合同类型 | X1: 性别 | Y1: 民族 | Z1: 出生日期 | AA1: 身份证地址 | AB1: 身份证号码 | AC1: 签发机关 | AD1: 身份证到期日期 | AE1: 年龄 | AF1: 政治 面貌 | AG1: 婚姻状况 | AH1: 身高（CM） | AI1: 驾驶 证 | AJ1: 血型 | AK1: 联系电话 | AL1: 紧急联系人 电话 | AM1: 最高 学历 | AN1: 毕业日期 | AO1: 毕业院校 | AP1: 专业 | AQ1: 专业技术职务名称 | AR1: 职业资格证书 | AS1: 优才类别 | AT1: 技能等级 | AU1: 劳动合同管理 | AV1: 劳动合同 开始日期 | AW1: 试用期 截止日期 | AX1: 最新 合同类型 | AY1: 最新 合同甲方 | AZ1: 最新合同 开始时间 | BA1: 最新合同 截止时间 | BB1: 最新合同 份数 | BC1: 最新合同 公章 | BD1: 最新合同 法人章 | BE1: 最新合同 签字 | BF1: 最新合同 指纹 | BG1: 其他合同 种类 | BH1: 其他合同 种类 | BI1: 备注 | BJ1: 电子 资料 | BK1: 身份证扫描件 | BL1: 职称证书扫描件 | BM1: 职业资格证扫描件 | BN1: 毕业证/学位证扫描件 | BO1: 退伍军人证扫描件 | BP1: 残疾人证扫描件 | BQ1: 档案室资料 | BR1: 档案柜 | BS1: 面试考评表 | BT1: 新员工入职单 | BU1: 个人简历 | BV1: 廉洁自律承诺书 | BW1: 入职承诺书 | BX1: 职业危害告知书 | BY1: 保密协议 | BZ1: 解除劳动合同证明 | CA1: 调动单 | CB1: 试用期考评表/转正审批表 | CC1: 职位申请表 | CD1: 人事考评审批表 | CE1: 培训协议 | CF1: 体检报告 | CG1: 其他文件 | CH1: 离职资料 | CI1: 离职申请表 | CJ1: 离职交接单 | CK1: 解除劳动合同证明 | CL1: 离职体检告知书 | CM1: 离职体检报告
A2: =IF(B2="","",ROW()-1) -> 1 | B2: =IF(AB2="","",AB2) -> 130522198205272415 | C2: 力量煤业 | D2: 公司人员 | E2: M10000 | F2: 李波 | G2: 0 | H2: 0 | I2: =G2+H2 -> 0 | J2: 公司领导 | K2: 董事长 | Q2: 2021-4-20兼任内蒙古量殖农牧业发展集团董事长； 2022-5-30任力量发展有限公司执行董事兼行政总裁； 2022-6-4兼管力量发展集团人事、行政工作； | R2: 管理岗 | S2: 董事长 | T2: 正式工 | U2: 38075 | V2: =IF(U2="","",ROUND(YEARFRAC(U2,TODAY(),1),1)) -> 22.3 | W2: 无固定期限 | X2: =IF(MOD(RIGHT(LEFT(AB2,17)),2),"男","女") -> 男 | Y2: 汉 | Z2: =MID(AB2,7,4)&"-"&MID(AB2,11,2)&"-"&MID(AB2,13,2) -> 1982-05-27 | AA2: 北京市东城区和平里中街甲7号 | AB2: 130522198205272415 | AC2: - | AD2: - | AE2: =YEAR(TODAY())-MID(AB2,7,4) -> 44 | AH2: - | AI2: - | AJ2: - | AK2: - | AL2: - | AM2: 本科 | AN2: 38169 | AO2: 北京科技大学 | AP2: 行政管理学 | AQ2: 高级经济师(人力资源管理/副高级)；中级经济师（人力资源管理/中级）；注册安全工程师（煤矿/中级） | AR2: 人力资源管理师（一级） | AV2: 39080 | AW2: 无 | AX2: 劳动合同 | AY2: 力量煤业 | AZ2: 41361 | BA2: 无固定期限 | BB2: 1 | BC2: √ | BD2: × | BE2: √ | BF2: × | BG2: 5 | BH2: 5 | BM2: √ | BN2: √ | BR2: LM-01-01 | BU2: √
A3: =IF(B3="","",ROW()-1) -> 2 | B3: =IF(AB3="","",AB3) -> 152723196312021818 | C3: 力量煤业 | D3: 公司人员 | E3: M10002 | F3: 刘冠杰 | G3: 0 | H3: 0 | I3: =G3+H3 -> 0 | J3: 公司领导 | K3: 财务总监 | Q3: 2021-9-5兼任内蒙古量蕴农牧业公司财务总监； 2021-09-08兼任集团财务常务副总监 | R3: 管理岗 | S3: 总经理级 | T3: 正式工 | U3: 43094 | V3: =IF(U3="","",ROUND(YEARFRAC(U3,TODAY(),1),1)) -> 8.5 | W3: 无劳动合同 | X3: =IF(MOD(RIGHT(LEFT(AB3,17)),2),"男","女") -> 男 | Y3: 汉 | Z3: =MID(AB3,7,4)&"-"&MID(AB3,11,2)&"-"&MID(AB3,13,2) -> 1963-12-02 | AA3: 内蒙古鄂尔多斯市准格尔旗薛家湾镇 | AB3: 152723196312021818 | AC3: - | AD3: - | AE3: =YEAR(TODAY())-MID(AB3,7,4) -> 63 | AH3: - | AI3: - | AJ3: - | AK3: - | AL3: - | AM3: 本科 | AN3: / | AO3: - | AP3: - | AV3: 43094 | AW3: 已转正 | AX3: 无 | AY3: 无 | AZ3: 无 | BA3: 无劳动合同 | BG3: 0 | BH3: 0 | BR3: LM-01-01
A4: =IF(B4="","",ROW()-1) -> 3 | B4: =IF(AB4="","",AB4) -> 130503196610061234 | C4: 力量煤业 | D4: 公司人员 | E4: M10001 | F4: 李运成 | G4: 2401.85 | H4: 0 | I4: =G4+H4 -> 2401.85 | J4: 公司领导 | K4: 总经理 | M4: 任命文件报销 | R4: 管理岗 | S4: 总经理级 | T4: 正式工 | U4: 41365 | V4: =IF(U4="","",ROUND(YEARFRAC(U4,TODAY(),1),1)) -> 13.3 | W4: 固定期限劳动合同 | X4: =IF(MOD(RIGHT(LEFT(AB4,17)),2),"男","女") -> 男 | Y4: 汉 | Z4: =MID(AB4,7,4)&"-"&MID(AB4,11,2)&"-"&MID(AB4,13,2) -> 1966-10-06 | AA4: 河北省邢台市桥西区显德汪煤矿住宅区31楼2单元12号 | AB4: 130503196610061234 | AC4: 邢台市公安局桥西分局 | AD4: 46846 | AE4: =YEAR(TODAY())-MID(AB4,7,4) -> 60 | AH4: - | AI4: - | AJ4: - | AK4: - | AL4: - | AM4: 本科 | AN4: 32509 | AO4: 山西矿业学院（现太原理工大学） | AP4: 矿井建设 | AQ4: 工程师（中级） | AV4: 41365 | AW4: 41426 | AX4: 劳动合同 | AY4: 力量煤业 | AZ4: 45017 | BA4: 46112 | BB4: 2 | BC4: √ | BD4: × | BE4: √ | BF4: × | BG4: 1 | BH4: 2 | BN4: √ | BR4: LM-01-01 | BS4: √ | BT4: √ | CC4: √ | CF4: 2018年
A5: =IF(B5="","",ROW()-1) -> 4 | B5: =IF(AB5="","",AB5) -> 21128219830626081X | C5: 力量煤业 | D5: 公司人员 | E5: M10003 | F5: 奚明 | G5: 1365.05 | H5: 0 | I5: =G5+H5 -> 1365.05 | J5: 公司领导 | K5: 常务副总经理 | M5: 任命文件报销 | R5: 管理岗 | S5: 副总级 | T5: 正式工 | U5: 43222 | V5: =IF(U5="","",ROUND(YEARFRAC(U5,TODAY(),1),1)) -> 8.2 | W5: 固定期限劳动合同 | X5: =IF(MOD(RIGHT(LEFT(AB5,17)),2),"男","女") -> 男 | Y5: 汉 | Z5: =MID(AB5,7,4)&"-"&MID(AB5,11,2)&"-"&MID(AB5,13,2) -> 1983-06-26 | AA5: 北京市朝阳区金蝉南里4号楼3单元402号 | AB5: 21128219830626081X | AC5: - | AD5: - | AE5: =YEAR(TODAY())-MID(AB5,7,4) -> 43 | AH5: - | AI5: - | AJ5: - | AK5: - | AL5: - | AM5: 研究生 | AN5: 43983 | AO5: 北京交通大学 | AP5: 工商管理 | AQ5: 高级经济师；注册造价工程师 | AR5: 皇家工料测量师RICS；项目管理师PMP | AV5: 43222 | AW5: 43282 | AX5: 劳动合同 | AY5: 力量煤业 | AZ5: 44348 | BA5: 45473 | BB5: 2 | BC5: √ | BD5: √ | BE5: √ | BF5: √ | BG5: 1 | BH5: 1 | BN5: √ | BR5: LM-01-01 | BT5: √ | BU5: √ | BY5: √ | BZ5: √ | CA5: √ | CB5: √ | CC5: √ | CF5: 2018年
A6: =IF(B6="","",ROW()-1) -> 5 | B6: =IF(AB6="","",AB6) -> 370902197109021292 | C6: 力量煤业 | D6: 公司人员 | E6: M10004 | F6: 窦发权 | G6: 3706.6 | H6: 0 | I6: =G6+H6 -> 3706.6 | J6: 公司领导 | K6: 副总经理 | M6: 任命文件报销 | Q6: 2022-4-13兼任力量发展集团有限公司集团副总工程师 | R6: 管理岗 | S6: 副总级 | T6: 正式工 | U6: 41671 | V6: =IF(U6="","",ROUND(YEARFRAC(U6,TODAY(),1),1)) -> 12.4 | W6: 固定期限劳动合同 | X6: =IF(MOD(RIGHT(LEFT(AB6,17)),2),"男","女") -> 男 | Y6: 汉 | Z6: =MID(AB6,7,4)&"-"&MID(AB6,11,2)&"-"&MID(AB6,13,2) -> 1971-09-02 | AA6: 山东省泰安市岱岳区龙潭路375号3号楼1单元501室 | AB6: 370902197109021292 | AC6: 泰安市公安局岱岳分局 | AD6: 长期 | AE6: =YEAR(TODAY())-MID(AB6,7,4) -> 55 | AH6: - | AI6: - | AJ6: - | AK6: - | AL6: - | AM6: 本科 | AN6: 34881 | AO6: 山东矿业学院 | AP6: 采矿工程 | AQ6: 工程师（采矿/高级）；注册安全工程师（煤矿/中级） | AV6: 41671 | AW6: 41730 | AX6: 劳动合同 | AY6: 力量煤业 | AZ6: 44287 | BA6: 45382 | BB6: 2 | BC6: √ | BD6: × | BE6: √ | BF6: √ | BG6: 2 | BH6: 4 | BR6: LM-01-01 | BU6: √ | CA6: √
A7: =IF(B7="","",ROW()-1) -> 6 | B7: =IF(AB7="","",AB7) -> 640204196305152033 | C7: 力量煤业 | D7: 公司人员 | E7: M10005 | F7: 马天峰 | G7: 2502.5 | H7: 0 | I7: =G7+H7 -> 2502.5 | J7: 公司领导 | K7: 副总经理 | M7: 任命文件报销 | R7: 管理岗 | S7: 副总级 | T7: 正式工 | U7: 40465 | V7: =IF(U7="","",ROUND(YEARFRAC(U7,TODAY(),1),1)) -> 15.7 | W7: 无固定期限 | X7: =IF(MOD(RIGHT(LEFT(AB7,17)),2),"男","女") -> 男 | Y7: 回 | Z7: =MID(AB7,7,4)&"-"&MID(AB7,11,2)&"-"&MID(AB7,13,2) -> 1963-05-15 | AA7: 宁夏石嘴山市惠农区矿安路北3-4-6 | AB7: 640204196305152033 | AC7: 石嘴山市公安局惠农区分局 | AD7: 长期 | AE7: =YEAR(TODAY())-MID(AB7,7,4) -> 63 | AH7: - | AI7: - | AJ7: - | AK7: - | AL7: - | AM7: 本科 | AN7: 31291 | AO7: 西安矿业学院 | AP7: 煤矿机械化 | AQ7: 工程师（机电/高级） | AV7: 40465 | AW7: 40525 | AX7: 劳动合同 | AY7: 力量煤业 | AZ7: 41196 | BA7: 无固定期限 | BB7: 2 | BC7: √ | BD7: √ | BE7: × | BF7: × | BG7: 1 | BH7: 1 | BL7: √ | BN7: √ | BR7: LM-01-01 | BS7: √ | BU7: √ | CC7: √ | CG7: 放弃缴纳公积金、社保说明
A8: =IF(B8="","",ROW()-1) -> 7 | B8: =IF(AB8="","",AB8) -> 320322197003037337 | C8: 力量煤业 | D8: 公司人员 | E8: M10006 | F8: 李印楼 | G8: 3470.55 | H8: 0 | I8: =G8+H8 -> 3470.55 | J8: 公司领导 | K8: 副总经理兼矿长 | M8: 任命文件报销 | R8: 管理岗 | S8: 副总级 | T8: 正式工 | U8: 41306 | V8: =IF(U8="","",ROUND(YEARFRAC(U8,TODAY(),1),1)) -> 13.4 | W8: 固定期限劳动合同 | X8: =IF(MOD(RIGHT(LEFT(AB8,17)),2),"男","女") -> 男 | Y8: 汉 | Z8: =MID(AB8,7,4)&"-"&MID(AB8,11,2)&"-"&MID(AB8,13,2) -> 1970-03-03 | AA8: 江苏省沛县大屯煤电徐庄风井小区433号 | AB8: 320322197003037337 | AC8: 沛县公安局 | AD8: 长期 | AE8: =YEAR(TODAY())-MID(AB8,7,4) -> 56 | AH8: - | AI8: - | AJ8: - | AK8: - | AL8: - | AM8: 大专 | AN8: 34881 | AO8: 中国矿业大学 | AP8: 机电一体化 | AQ8: 工程师（机电一体化/高级） | AV8: 41306 | AW8: 41365 | AX8: 劳动合同 | AY8: 力量煤业 | AZ8: 43922 | BA8: 46112 | BB8: 2 | BC8: √ | BD8: × | BE8: √ | BF8: √ | BG8: 2 | BH8: 3 | BL8: √ | BN8: √ | BR8: LM-01-01 | BS8: √ | BT8: √ | BU8: √ | BZ8: √ | CB8: √ | CC8: √ | CF8: 2018年 | CG8: 荣誉证书*5/工伤认定证/谈话记录
A9: =IF(B9="","",ROW()-1) -> 8 | B9: =IF(AB9="","",AB9) -> 230822198111094910 | C9: 力量煤业 | D9: 公司人员 | E9: M10007 | F9: 宋云飞 | G9: 0 | H9: 0 | I9: =G9+H9 -> 0 | J9: 公司领导 | K9: 副总经理 | Q9: 2022-11-15兼任内蒙古量蕴农业发展有限公司总经理 | R9: 管理岗 | S9: 副总级 | T9: 正式工 | U9: 41061 | V9: =IF(U9="","",ROUND(YEARFRAC(U9,TODAY(),1),1)) -> 14.1 | W9: 固定期限劳动合同 | X9: =IF(MOD(RIGHT(LEFT(AB9,17)),2),"男","女") -> 男 | Y9: 汉 | Z9: =MID(AB9,7,4)&"-"&MID(AB9,11,2)&"-"&MID(AB9,13,2) -> 1981-11-09 | AA9: 北京市朝阳区惠忠庵一号对外经济贸易大学（04研） | AB9: 230822198111094910 | AC9: - | AD9: - | AE9: =YEAR(TODAY())-MID(AB9,7,4) -> 45 | AH9: - | AI9: - | AJ9: - | AK9: - | AL9: - | AM9: 研究生 | AN9: 38899 | AO9: 对外经济贸易大学 | AP9: 技术经济及管理 | AV9: 42482 | AW9: 42542 | AX9: 劳动合同 | AY9: 力量煤业 | AZ9: 44306 | BA9: 45473 | BB9: 2 | BC9: √ | BD9: √ | BE9: √ | BF9: √ | BG9: 1 | BH9: 2 | BN9: √ | BR9: LM-01-01 | BT9: √ | BV9: √ | BW9: √ | BY9: √
A10: =IF(B10="","",ROW()-1) -> 9 | B10: =IF(AB10="","",AB10) -> 130403196411292114 | C10: 力量煤业 | D10: 公司人员 | E10: M10008 | F10: 周洪刚 | G10: 1889.2 | H10: 0 | I10: =G10+H10 -> 1889.2 | J10: 公司领导 | K10: 总经理助理兼多种经营部经理 | M10: 任命文件报销 | Q10: 2021-10-27兼任量蕴牧业发展有限公司常务副总经理 | R10: 管理岗 | S10: 副总级 | T10: 正式工 | U10: 40313 | V10: =IF(U10="","",ROUND(YEARFRAC(U10,TODAY(),1),1)) -> 16.1 | W10: 无固定期限 | X10: =IF(MOD(RIGHT(LEFT(AB10,17)),2),"男","女") -> 男 | Y10: 汉 | Z10: =MID(AB10,7,4)&"-"&MID(AB10,11,2)&"-"&MID(AB10,13,2) -> 1964-11-29 | AA10: 河北省邯郸市邯山区和平路373号9栋2单元7号 | AB10: 130403196411292114 | AC10: - | AD10: - | AE10: =YEAR(TODAY())-MID(AB10,7,4) -> 62 | AF10: 中共党员 | AG10: 已婚 | AH10: - | AI10: C1 | AJ10: O | AK10: - | AL10: - | AM10: 大专 | AN10: 40969 | AO10: 河北机电学院 | AP10: 工业经济管理 | AV10: 40313 | AW10: 40374 | AX10: 劳动合同 | AY10: 力量煤业 | AZ10: 41408 | BA10: 无固定期限 | BB10: 2 | BC10: √ | BD10: √ | BE10: √ | BF10: × | BG10: 1 | BH10: 1 | BN10: √ | BR10: LM-01-01 | BS10: √ | CC10: √ | CG10: 社保扣款及收费凭证*8
A11: =IF(B11="","",ROW()-1) -> 10 | B11: =IF(AB11="","",AB11) -> 152723198509184812 | C11: 力量煤业 | D11: 公司人员 | E11: M10010 | F11: 王震 | G11: 3445.2 | H11: 0 | I11: =G11+H11 -> 3445.2 | J11: 公司领导 | K11: 副总经理 | M11: 任命文件报销 | Q11: 2021-10-27兼任内蒙古量蕴牧业发展有限公司副总经理 | R11: 管理岗 | S11: 副总级 | T11: 正式工 | U11: 40392 | V11: =IF(U11="","",ROUND(YEARFRAC(U11,TODAY(),1),1)) -> 15.9 | W11: 无固定期限 | X11: =IF(MOD(RIGHT(LEFT(AB11,17)),2),"男","女") -> 男 | Y11: 汉 | Z11: =MID(AB11,7,4)&"-"&MID(AB11,11,2)&"-"&MID(AB11,13,2) -> 1985-09-18 | AA11: 内蒙古鄂尔多斯市准格尔旗大路镇乌兰不浪村小东社218号 | AB11: 152723198509184812 | AC11: - | AD11: - | AE11: =YEAR(TODAY())-MID(AB11,7,4) -> 41 | AF11: 群众 | AG11: 已婚 | AH11: - | AI11: C1 | AJ11: O | AK11: - | AL11: - | AM11: 大专 | AN11: / | AO11: - | AP11: 电气工程及其 自动化 | AV11: 40392 | AW11: 40756 | AX11: 劳动合同 | AY11: 力量煤业 | AZ11: 41518 | BA11: 无固定期限 | BB11: 2 | BC11: √ | BD11: × | BE11: √ | BF11: √ | BG11: 2 | BH11: 2 | BN11: √ | BR11: LM-01-01 | BS11: √ | BU11: √ | BZ11: √ | CC11: √ | CG11: 驾驶证扫描件
A12: =IF(B12="","",ROW()-1) -> 11 | B12: =IF(AB12="","",AB12) -> 362329198611264574 | C12: 力量煤业 | D12: 直接生产人员 | E12: M10111 | F12: 李秦生 | G12: 4861.83 | H12: 0 | I12: =G12+H12 -> 4861.83 | J12: 矿级领导 | K12: 总工程师 | M12: 任命文件报销 | Q12: 2022-2-26兼任力量煤业副总工程师； 2022-6-16兼任内蒙古准格尔旗力量煤业大饭铺煤矿常务副矿长 | R12: 管理岗 | S12: 高级经理级 | T12: 正式工 | U12: 40410 | V12: =IF(U12="","",ROUND(YEARFRAC(U12,TODAY(),1),1)) -> 15.9 | W12: 无固定期限 | X12: =IF(MOD(RIGHT(LEFT(AB12,17)),2),"男","女") -> 男 | Y12: 汉 | Z12: =MID(AB12,7,4)&"-"&MID(AB12,11,2)&"-"&MID(AB12,13,2) -> 1986-11-26 | AA12: 重庆市綦江区安稳镇松北路179号5单元 | AB12: 362329198611264574 | AC12: 重庆市公安局綦江分局 | AD12: 50546 | AE12: =YEAR(TODAY())-MID(AB12,7,4) -> 40 | AF12: 群众 | AG12: 已婚 | AH12: 162 | AI12: C1 | AJ12: AB | AK12: 15847702155 | AL12: 15134841667 | AM12: 本科 | AN12: 39627 | AO12: 中国矿业大学 | AP12: 采矿工程 | AQ12: 工程师（采矿工程/副高级）；注册安全工程师（中级） | AV12: 40410 | AW12: 40470 | AX12: 劳动合同 | AY12: 力量煤业 | AZ12: 41141 | BA12: 无固定期限 | BB12: 1 | BC12: √ | BD12: √ | BE12: √ | BF12: × | BG12: 1 | BH12: 1 | BL12: √ | BN12: √ | BR12: LM-01-01 | BS12: √ | BU12: √ | CA12: √ | CC12: √ | CE12: √ | CF12: 2018年 | CG12: 领取劳动合同说明
A13: =IF(B13="","",ROW()-1) -> 12 | B13: =IF(AB13="","",AB13) -> 340403197510102439 | C13: 力量煤业 | D13: 直接生产人员 | E13: M10294 | F13: 杨维海 | G13: 1738.02 | H13: 0 | I13: =G13+H13 -> 1738.02 | J13: 矿级领导 | K13: 副矿长 | M13: 任命文件报销 | R13: 管理岗 | S13: 正经理级/副矿级 | T13: 正式工 | U13: 41373 | V13: =IF(U13="","",ROUND(YEARFRAC(U13,TODAY(),1),1)) -> 13.2 | W13: 固定期限劳动合同 | X13: =IF(MOD(RIGHT(LEFT(AB13,17)),2),"男","女") -> 男 | Y13: 汉 | Z13: =MID(AB13,7,4)&"-"&MID(AB13,11,2)&"-"&MID(AB13,13,2) -> 1975-10-10 | AA13: 安徽省淮南市田家庵区安成镇石头埠村３７号 | AB13: 340403197510102439 | AC13: 淮南市公安局田家庵分局 | AD13: 46270 | AE13: =YEAR(TODAY())-MID(AB13,7,4) -> 51 | AF13: 群众 | AG13: 已婚 | AH13: 176 | AI13: C1 | AJ13: O | AK13: 15847076472 | AL13: 18248085396 | AM13: 大专（函授） | AN13: 44013 | AO13: 东北大学 | AP13: 煤矿开采技术 | AV13: 41373 | AW13: 41434 | AX13: 劳动合同 | AY13: 力量煤业 | AZ13: 44743 | BA13: 45838 | BB13: 2 | BC13: √ | BD13: √ | BE13: √ | BF13: √ | BG13: 2 | BH13: 4 | BR13: LM-01-03 | BS13: √ | BT13: √ | CB13: √ | CC13: √ | CG13: 特种作业证
A14: =IF(B14="","",ROW()-1) -> 13 | B14: =IF(AB14="","",AB14) -> 230303198407064239 | C14: 力量煤业 | D14: 直接生产人员 | E14: M10293 | F14: 郭洪亮 | G14: 2035.5 | H14: 0 | I14: =G14+H14 -> 2035.5 | J14: 矿级领导 | K14: 安全副矿长 | M14: 任命文件报销 | R14: 管理岗 | S14: 正经理级/副矿级 | T14: 正式工 | U14: 41371 | V14: =IF(U14="","",ROUND(YEARFRAC(U14,TODAY(),1),1)) -> 13.2 | W14: 固定期限劳动合同 | X14: =IF(MOD(RIGHT(LEFT(AB14,17)),2),"男","女") -> 男 | Y14: 汉 | Z14: =MID(AB14,7,4)&"-"&MID(AB14,11,2)&"-"&MID(AB14,13,2) -> 1984-07-06 | AA14: 黑龙江省鸡西市滴道区河北十四委10组 | AB14: 230303198407064239 | AC14: 鸡西市公安局滴道分局 | AD14: 49973 | AE14: =YEAR(TODAY())-MID(AB14,7,4) -> 42 | AF14: 中共党员 | AG14: 已婚 | AH14: 180 | AI14: - | AJ14: AB | AK14: 18646751172 | AL14: 15734773315 | AM14: 本科 | AN14: 39264 | AO14: 黑龙江科技学院 | AP14: 机电一体化、采矿工程 | AQ14: 工程师（）/助理工程师 | AV14: 41371 | AW14: 41432 | AX14: 劳动合同 | AY14: 力量煤业 | AZ14: 44743 | BA14: 45838 | BB14: 2 | BC14: √ | BD14: √ | BE14: √ | BF14: √ | BG14: 2 | BH14: 4 | BL14: √ | BN14: √ | BR14: LM-01-03 | BS14: √ | BT14: √ | CA14: √ | CB14: √ | CC14: √
A15: =IF(B15="","",ROW()-1) -> 14 | B15: =IF(AB15="","",AB15) -> 130521197011257013 | C15: 力量煤业 | D15: 直接生产人员 | E15: M10250 | F15: 刘栓柱 | G15: 1572.88 | H15: 0 | I15: =G15+H15 -> 1572.88 | J15: 矿级领导 | K15: 矿长助理 | M15: 任命文件报销 | R15: 管理岗 | S15: 正经理级/副矿级 | T15: 正式工 | U15: 41326 | V15: =IF(U15="","",ROUND(YEARFRAC(U15,TODAY(),1),1)) -> 13.4 | W15: 固定期限劳动合同 | X15: =IF(MOD(RIGHT(LEFT(AB15,17)),2),"男","女") -> 男 | Y15: 汉 | Z15: =MID(AB15,7,4)&"-"&MID(AB15,11,2)&"-"&MID(AB15,13,2) -> 1970-11-25 | AA15: 河北省邢台市邢台县路罗镇桃树坪村368号 | AB15: 130521197011257013 | AC15: 邢台县公安局 | AD15: 47502 | AE15: =YEAR(TODAY())-MID(AB15,7,4) -> 56 | AF15: 群众 | AG15: 已婚 | AH15: 175 | AI15: C1 | AJ15: O | AK15: 18647722268 | AL15: 15097965491 | AM15: 大专（函授） | AN15: 44022 | AO15: 东北大学 | AP15: 煤矿开采技术 | AV15: 41326 | AW15: 41385 | AX15: 劳动合同 | AY15: 力量煤业 | AZ15: 43922 | BA15: 46112 | BB15: 2 | BC15: √ | BD15: √ | BE15: √ | BF15: √ | BG15: 2 | BH15: 3 | BN15: √ | BR15: LM-01-03 | BS15: √ | BT15: √ | CB15: √ | CC15: √ | CG15: 谈话记录
A16: =IF(B16="","",ROW()-1) -> 15 | B16: =IF(AB16="","",AB16) -> 14010219810504601X | C16: 力量煤业 | D16: 直接生产人员 | E16: M11616 | F16: 高翔 | I16: =G16+H16 -> 0 | J16: 矿级领导 | K16: 生产副矿长 | R16: 管理岗 | S16: 正经理级/副矿级 | T16: 正式工 | U16: 45085 | V16: =IF(U16="","",ROUND(YEARFRAC(U16,TODAY(),1),1)) -> 3.1 | W16: 固定期限劳动合同 | X16: =IF(MOD(RIGHT(LEFT(AB16,17)),2),"男","女") -> 男 | Y16: 汉 | Z16: =MID(AB16,7,4)&"-"&MID(AB16,11,2)&"-"&MID(AB16,13,2) -> 1981-05-04 | AA16: 山西省阳泉市矿区立新区美丽家园1楼4门6号 | AB16: 14010219810504601X | AC16: 阳泉市公安局矿区分局 | AD16: 49923 | AE16: =YEAR(TODAY())-MID(AB16,7,4) -> 45 | AF16: 党员 | AG16: 已婚 | AH16: 167 | AJ16: A | AK16: 13834280786 | AL16: 13834280789 | AM16: 本科 | AN16: 2017年 | AO16: 太原理工大学 | AP16: 矿业工程 | AV16: 45085 | AW16: 45267 | AX16: 劳动合同 | AY16: 力量煤业 | AZ16: 45085 | BA16: 46203 | BB16: 2 | BC16: √ | BD16: √ | BE16: √ | BF16: √ | BG16: 0 | BH16: 0 | BK16: √ | BR16: LM-05-04 | BS16: √ | BT16: √ | BU16: √ | BV16: √ | BW16: √ | BX16: √ | BY16: √
A17: =IF(B17="","",ROW()-1) -> 16 | B17: =IF(AB17="","",AB17) -> 140581198801043215 | C17: 力量煤业 | D17: 直接生产人员 | E17: M11620 | F17: 王荣 | I17: =G17+H17 -> 0 | J17: 矿级领导 | K17: 生产副总工程师 | R17: 管理岗 | S17: 正经理级/副矿级 | T17: 正式工 | U17: 45087 | V17: =IF(U17="","",ROUND(YEARFRAC(U17,TODAY(),1),1)) -> 3.1 | W17: 固定期限劳动合同 | X17: =IF(MOD(RIGHT(LEFT(AB17,17)),2),"男","女") -> 男 | Y17: 汉 | Z17: =MID(AB17,7,4)&"-"&MID(AB17,11,2)&"-"&MID(AB17,13,2) -> 1988-01-04 | AA17: 山西省晋城市城区书院街1261号古矿单身2号楼 | AB17: 140581198801043215 | AC17: 晋城市公安局城区分局 | AD17: 50511 | AE17: =YEAR(TODAY())-MID(AB17,7,4) -> 38 | AF17: 党员 | AG17: 已婚 | AH17: 178 | AJ17: A | AK17: 13834939720 | AM17: 本科 | AN17: 2010年 | AO17: 太原理工大学 | AP17: 电气工程及其自动化 | AV17: 45087 | AW17: 45269 | AX17: 劳动合同 | AY17: 力量煤业 | AZ17: 45087 | BA17: 46203 | BB17: 2 | BC17: √ | BD17: √ | BE17: √ | BF17: √ | BG17: 0 | BH17: 0 | BK17: √ | BR17: LM-05-05 | BS17: √ | BT17: √ | BU17: √ | BV17: √ | BW17: √ | BX17: √ | BY17: √
A18: =IF(B18="","",ROW()-1) -> 17 | B18: =IF(AB18="","",AB18) -> 230321197809105011 | C18: 力量煤业 | D18: 直接生产人员 | E18: M11621 | F18: 陈永清 | I18: =G18+H18 -> 0 | J18: 矿级领导 | K18: 机电副矿长 | R18: 管理岗 | S18: 正经理级/副矿级 | T18: 正式工 | U18: 45087 | V18: =IF(U18="","",ROUND(YEARFRAC(U18,TODAY(),1),1)) -> 3.1 | W18: 固定期限劳动合同 | X18: =IF(MOD(RIGHT(LEFT(AB18,17)),2),"男","女") -> 男 | Y18: 汉 | Z18: =MID(AB18,7,4)&"-"&MID(AB18,11,2)&"-"&MID(AB18,13,2) -> 1978-09-10 | AA18: 黑龙江省鸡西市鸡冠区红楼委3组58号 | AB18: 230321197809105011 | AC18: 鸡西市公安局鸡冠分局 | AD18: 50324 | AE18: =YEAR(TODAY())-MID(AB18,7,4) -> 48 | AF18: 党员 | AG18: 已婚 | AH18: 168 | AJ18: B | AK18: 13834494335 | AL18: 13836577418 | AM18: 本科 | AN18: 41091 | AO18: 长春工业大学 | AP18: 机械电子工程 | AV18: 45087 | AW18: 45269 | AX18: 劳动合同 | AY18: 力量煤业 | AZ18: 45087 | BA18: 46203 | BB18: 2 | BC18: √ | BD18: √ | BE18: √ | BF18: √ | BG18: 0 | BH18: 0 | BK18: √ | BR18: LM-05-05 | BS18: √ | BT18: √ | BU18: √ | BV18: √ | BW18: √ | BX18: √ | BY18: √
A19: =IF(B19="","",ROW()-1) -> 18 | B19: =IF(AB19="","",AB19) -> 150428198903200159 | C19: 力量煤业 | D19: 直接生产人员 | E19: M11627 | F19: 孙启明 | I19: =G19+H19 -> 0 | J19: 综采队 | K19: 队长 | R19: 管理岗 | S19: 副经理级/正科级 | T19: 正式工 | U19: 45090 | V19: =IF(U19="","",ROUND(YEARFRAC(U19,TODAY(),1),1)) -> 3.1 | W19: 固定期限劳动合同 | X19: =IF(MOD(RIGHT(LEFT(AB19,17)),2),"男","女") -> 男 | Y19: 蒙古族 | Z19: =MID(AB19,7,4)&"-"&MID(AB19,11,2)&"-"&MID(AB19,13,2) -> 1989-03-20 | AA19: 内蒙古鄂尔多斯市东胜区泊江海子镇泊江海子村马家村15号 | AB19: 150428198903200159 | AC19: 东胜区公安分局 | AD19: 52317 | AE19: =YEAR(TODAY())-MID(AB19,7,4) -> 37 | AF19: 群众 | AG19: 已婚 | AH19: 172 | AK19: 15149739502 | AL19: 15149739543 | AM19: 本科 | AP19: 机械电子工程 | AV19: 45090 | AW19: 45272 | AX19: 劳动合同 | AY19: 力量煤业 | AZ19: 45090 | BA19: 46203 | BB19: 2 | BC19: √ | BD19: √ | BE19: √ | BF19: √ | BG19: 0 | BH19: 0 | BK19: √ | BR19: LM-05-05 | BS19: √ | BT19: √ | BU19: √ | BV19: √ | BW19: √ | BX19: √ | BY19: √ | CF19: 2023年
A20: =IF(B20="","",ROW()-1) -> 19 | B20: =IF(AB20="","",AB20) -> 370881198111304835 | C20: 力量煤业 | D20: 直接生产人员 | E20: M11530 | F20: 张广振 | I20: =G20+H20 -> 0 | J20: 综采队 | K20: 常务副队长 | R20: 管理岗 | S20: 副经理级/正科级 | T20: 正式工 | U20: 45039 | V20: =IF(U20="","",ROUND(YEARFRAC(U20,TODAY(),1),1)) -> 3.2 | W20: 固定期限劳动合同 | X20: =IF(MOD(RIGHT(LEFT(AB20,17)),2),"男","女") -> 男 | Y20: 汉 | Z20: =MID(AB20,7,4)&"-"&MID(AB20,11,2)&"-"&MID(AB20,13,2) -> 1981-11-30 | AA20: 山东省曲阜市陵城镇苑庄村中心街40号 | AB20: 370881198111304835 | AC20: 曲阜市公安局 | AD20: 47341 | AE20: =YEAR(TODAY())-MID(AB20,7,4) -> 45 | AF20: 群众 | AG20: 已婚 | AH20: 182 | AI20: A2 | AJ20: A | AK20: 18754751818 | AL20: 18264713389 | AM20: 大专 | AN20: 2019年 | AO20: 济宁职业技术学院 | AP20: 机电一体化 | AV20: 45039 | AW20: 45221 | AX20: 劳动合同 | AY20: 力量煤业 | AZ20: 45039 | BA20: 46203 | BB20: 2 | BC20: √ | BD20: √ | BE20: √ | BF20: √ | BG20: 0 | BH20: 0 | BK20: √ | BR20: LM-05-03 | BS20: √ | BT20: √ | BU20: √ | BV20: √ | BW20: √ | BX20: √ | CF20: 2023年
A21: =IF(B21="","",ROW()-1) -> 20 | B21: =IF(AB21="","",AB21) -> 152723198804241517 | C21: 力量煤业 | D21: 直接生产人员 | E21: M10185 | F21: 任建龙 | G21: 1620.31 | H21: 0 | I21: =G21+H21 -> 1620.31 | J21: 综采队 | K21: 副队长 | M21: 任命文件报销 | R21: 专业技术岗 | S21: 副科级/经理助理/主管 | T21: 正式工 | U21: 41159 | V21: =IF(U21="","",ROUND(YEARFRAC(U21,TODAY(),1),1)) -> 13.8 | W21: 固定期限劳动合同 | X21: =IF(MOD(RIGHT(LEFT(AB21,17)),2),"男","女") -> 男 | Y21: 汉 | Z21: =MID(AB21,7,4)&"-"&MID(AB21,11,2)&"-"&MID(AB21,13,2) -> 1988-04-24 | AA21: 内蒙古鄂尔多斯市准格尔旗龙口镇红树梁村红树梁社303号 | AB21: 152723198804241517 | AC21: 准格尔旗公安局 | AD21: 50112 | AE21: =YEAR(TODAY())-MID(AB21,7,4) -> 38 | AF21: 群众 | AG21: 已婚 | AH21: 170 | AI21: C1 | AJ21: A | AK21: 13474888347 | AL21: 15894928906 | AM21: 本科 | AN21: 41090 | AO21: 中国矿业大学 | AP21: 采矿工程 | AQ21: 工程师（采矿/中级）；助理工程师（采矿/初级） | AR21: 计算机辅助设计绘图员 | AS21: A类 | AV21: 41159 | AW21: 41220 | AX21: 劳动合同 | AY21: 力量煤业 | AZ21: 44470 | BA21: 45565 | BB21: 2 | BC21: √ | BD21: √ | BE21: √ | BF21: √ | BG21: 3 | BH21: 5 | BL21: √ | BN21: √ | BR21: LM-01-02 | BS21: √ | BT21: √ | BU21: √ | CB21: √ | CC21: √
A22: =IF(B22="","",ROW()-1) -> 21 | B22: =IF(AB22="","",AB22) -> 15272319861209601X | C22: 力量煤业 | D22: 直接生产人员 | E22: M10145 | F22: 贺伟 | G22: 2400 | H22: 0 | I22: =G22+H22 -> 2400 | J22: 综采队 | K22: 副队长 | M22: 任命文件报销 | R22: 专业技术岗 | S22: 副科级/经理助理/主管 | T22: 正式工 | U22: 40948 | V22: =IF(U22="","",ROUND(YEARFRAC(U22,TODAY(),1),1)) -> 14.4 | W22: 固定期限劳动合同 | X22: =IF(MOD(RIGHT(LEFT(AB22,17)),2),"男","女") -> 男 | Y22: 汉 | Z22: =MID(AB22,7,4)&"-"&MID(AB22,11,2)&"-"&MID(AB22,13,2) -> 1986-12-09 | AA22: 内蒙古鄂尔多斯市准格尔旗沙圪堵镇寨子塔村德胜城社099号 | AB22: 15272319861209601X | AC22: 准格尔旗公安局 | AD22: 49904 | AE22: =YEAR(TODAY())-MID(AB22,7,4) -> 40 | AF22: 群众 | AG22: 已婚 | AH22: 168 | AI22: C1 | AJ22: A | AK22: 15248412504 | AL22: 14747782580 | AM22: 大专 | AN22: 43647 | AO22: 北京科技大学 | AP22: 煤矿开采技术 | AQ22: 工程师（采矿工程/中级） | AV22: 40948 | AW22: 41008 | AX22: 劳动合同 | AY22: 力量煤业 | AZ22: 44652 | BA22: 45747 | BB22: 2 | BC22: √ | BD22: √ | BE22: √ | BF22: √ | BG22: 3 | BH22: 6 | BN22: √ | BR22: LM-01-01 | BS22: √ | BU22: √ | CA22: √ | CB22: √ | CC22: √ | CE22: √
A23: =IF(B23="","",ROW()-1) -> 22 | B23: =IF(AB23="","",AB23) -> 152723198612071517 | C23: 力量煤业 | D23: 直接生产人员 | E23: F10487 | F23: 杨培 | G23: 0 | H23: 0 | I23: =G23+H23 -> 0 | J23: 综采队 | K23: 副队长 | R23: 专业技术岗 | S23: 副科级/经理助理/主管 | T23: 正式工 | U23: 42978 | V23: =IF(U23="","",ROUND(YEARFRAC(U23,TODAY(),1),1)) -> 8.8 | W23: 固定期限劳动合同 | X23: =IF(MOD(RIGHT(LEFT(AB23,17)),2),"男","女") -> 男 | Y23: 汉 | Z23: =MID(AB23,7,4)&"-"&MID(AB23,11,2)&"-"&MID(AB23,13,2) -> 1986-12-07 | AA23: 鄂尔多斯市准格尔旗龙口镇红树梁村壕川社008号 | AB23: 152723198612071517 | AC23: 准格尔旗公安局 | AD23: 49910 | AE23: =YEAR(TODAY())-MID(AB23,7,4) -> 40 | AF23: 中共党员 | AG23: 已婚 | AH23: 173 | AI23: C1 | AJ23: O | AK23: 15947364973 | AL23: 15947364903 | AM23: 本科 | AN23: 44688 | AO23: 中国地质大学 | AP23: 机电一体化 | AQ23: 助理工程师（机电初级） | AS23: C类 | AT23: 高级工 | AV23: 42978 | AW23: 43038 | AX23: 劳动合同 | AY23: 力量煤业 | AZ23: 44835 | BA23: 45565 | BB23: 2 | BC23: √ | BD23: √ | BE23: √ | BF23: √ | BG23: 1 | BH23: 2 | BK23: √ | BN23: √ | BR23: LM-02-02 | BS23: √ | BT23: √ | BW23: √ | CC23: √ | CG23: 高中毕业证
A24: =IF(B24="","",ROW()-1) -> 23 | B24: =IF(AB24="","",AB24) -> 370826197111153732 | C24: 力量煤业 | D24: 直接生产人员 | E24: F10230 | F24: 商好学 | G24: 0 | H24: 0 | I24: =G24+H24 -> 0 | J24: 综采队 | K24: 副队长 | R24: 专业技术岗 | S24: 副科级/经理助理/主管 | T24: 正式工 | U24: 41323 | V24: =IF(U24="","",ROUND(YEARFRAC(U24,TODAY(),1),1)) -> 13.4 | W24: 固定期限劳动合同 | X24: =IF(MOD(RIGHT(LEFT(AB24,17)),2),"男","女") -> 男 | Y24: 汉 | Z24: =MID(AB24,7,4)&"-"&MID(AB24,11,2)&"-"&MID(AB24,13,2) -> 1971-11-15 | AA24: 山东省微山县张楼乡陶官屯村平安路西五巷003号 | AB24: 370826197111153732 | AC24: 微山县公安局 | AD24: 45942 | AE24: =YEAR(TODAY())-MID(AB24,7,4) -> 55 | AF24: 群众 | AG24: 已婚 | AH24: 175 | AI24: C1 | AJ24: B | AK24: 15054887907 | AL24: 13954737712 | AM24: 大专（函授） | AN24: 44022 | AO24: 东北大学 | AP24: 煤矿开采技术 | AR24: 液压支架工（五级） | AT24: 高级工 | AV24: 41323 | AW24: 41382 | AX24: 劳动合同 | AY24: 力量煤业 | AZ24: 44743 | BA24: 45473 | BB24: 2 | BC24: √ | BD24: √ | BE24: √ | BF24: √ | BG24: 2 | BH24: 4 | BK24: √ | BM24: √ | BN24: √ | BR24: LM-01-02 | BS24: √ | BT24: √ | CC24: √ | CD24: √
A25: =IF(B25="","",ROW()-1) -> 24 | B25: =IF(AB25="","",AB25) -> 320322198908010811 | C25: 力量煤业 | D25: 直接生产人员 | E25: M30017 | F25: 杨肖 | I25: =G25+H25 -> 0 | J25: 综采队 | K25: 综采安装材料主管 | R25: 专业技术岗 | S25: 副科级/经理助理/主管 | T25: 正式工 | U25: 45078 | V25: =IF(U25="","",ROUND(YEARFRAC(U25,TODAY(),1),1)) -> 3.1 | W25: 固定期限劳动合同 | X25: =IF(MOD(RIGHT(LEFT(AB25,17)),2),"男","女") -> 男 | Y25: 汉 | Z25: =MID(AB25,7,4)&"-"&MID(AB25,11,2)&"-"&MID(AB25,13,2) -> 1989-08-01 | AA25: 江苏省沛县大屯镇丰乐521号 | AB25: 320322198908010811 | AC25: 沛县公安局 | AD25: 49981 | AE25: =YEAR(TODAY())-MID(AB25,7,4) -> 37 | AK25: 13734830459
A26: =IF(B26="","",ROW()-1) -> 25 | B26: =IF(AB26="","",AB26) -> 152128199611050910 | C26: 力量煤业 | D26: 直接生产人员 | E26: P10731 | F26: 蔡庆鑫 | G26: 0 | H26: 0 | I26: =G26+H26 -> 0 | J26: 综采队 | K26: 技术员 | R26: 专业技术岗 | T26: 正式工 | U26: 44099 | V26: =IF(U26="","",ROUND(YEARFRAC(U26,TODAY(),1),1)) -> 5.8 | W26: 固定期限劳动合同 | X26: =IF(MOD(RIGHT(LEFT(AB26,17)),2),"男","女") -> 男 | Y26: 汉 | Z26: =MID(AB26,7,4)&"-"&MID(AB26,11,2)&"-"&MID(AB26,13,2) -> 1996-11-05 | AA26: 内蒙古呼伦贝尔市鄂温克族自治旗大雁镇矿东街二胡同57号 | AB26: 152128199611050910 | AC26: 鄂温克族自治旗公安局 | AD26: 46336 | AE26: =YEAR(TODAY())-MID(AB26,7,4) -> 30 | AF26: 共青团员 | AG26: 未婚 | AH26: 174 | AI26: C1 | AJ26: B | AK26: 15848627873 | AL26: 13722008240 | AM26: 本科 | AN26: 44022 | AO26: 内蒙古科技大学 | AP26: 安全工程 | AQ26: 助理工程师（采矿/初级） | AV26: 44099 | AW26: 44159 | AX26: 劳动合同 | AY26: 力量煤业 | AZ26: 44470 | BA26: 45199 | BB26: 2 | BC26: √ | BD26: √ | BE26: √ | BF26: √ | BG26: 0 | BH26: 0 | BL26: √ | BN26: √ | BR26: LM-03-02 | BV26: √ | BW26: √ | BY26: √ | CB26: √
A27: =IF(B27="","",ROW()-1) -> 26 | B27: =IF(AB27="","",AB27) -> 140428199405043261 | C27: 力量煤业 | D27: 直接生产人员 | E27: P10583 | F27: 贾云云 | G27: 787.29 | H27: 0 | I27: =G27+H27 -> 787.29 | J27: 综采队 | K27: 办事员 | L27: 44409 | M27: 请示审批报销 | P27: 无 | R27: 专业技术岗 | T27: 正式工 | U27: 43386 | V27: =IF(U27="","",ROUND(YEARFRAC(U27,TODAY(),1),1)) -> 7.7 | W27: 固定期限劳动合同 | X27: =IF(MOD(RIGHT(LEFT(AB27,17)),2),"男","女") -> 女 | Y27: 汉 | Z27: =MID(AB27,7,4)&"-"&MID(AB27,11,2)&"-"&MID(AB27,13,2) -> 1994-05-04 | AA27: 山西省长子县石哲镇西河庄村037号 | AB27: 140428199405043261 | AC27: 长子县公安局 | AD27: 45743 | AE27: =YEAR(TODAY())-MID(AB27,7,4) -> 32 | AF27: 群众 | AG27: 已婚 | AH27: 160 | AI27: - | AJ27: B | AK27: 15698615326 | AL27: 18698528316 | AM27: 中专 | AN27: 40422 | AO27: 山西雁北煤炭职业技术学院 | AP27: 机电一体化 | AR27: 企业人力资源管理师（四级）；矿井维修电工（四级） | AV27: 43386 | AW27: 43446 | AX27: 劳动合同 | AY27: 力量煤业 | AZ27: 44562 | BA27: 45291 | BB27: 2 | BC27: √ | BD27: √ | BE27: √ | BF27: √ | BG27: 1 | BH27: 2 | BM27: √ | BN27: √ | BR27: LM-02-04 | BS27: √ | BT27: √ | BU27: √ | BV27: √ | BW27: √ | CB27: √ | CC27: √ | CF27: 2022年
A28: =IF(B28="","",ROW()-1) -> 27 | B28: =IF(AB28="","",AB28) -> 220881197811216011 | C28: 力量煤业 | D28: 直接生产人员 | E28: F10219 | F28: 张向辉 | G28: 0 | H28: 0 | I28: =G28+H28 -> 0 | J28: 综采队 | K28: 安检员 | R28: 工人岗 | T28: 正式工 | U28: 41302 | V28: =IF(U28="","",ROUND(YEARFRAC(U28,TODAY(),1),1)) -> 13.4 | W28: 固定期限劳动合同 | X28: =IF(MOD(RIGHT(LEFT(AB28,17)),2),"男","女") -> 男 | Y28: 汉 | Z28: =MID(AB28,7,4)&"-"&MID(AB28,11,2)&"-"&MID(AB28,13,2) -> 1978-11-21 | AA28: 吉林省洮南市万宝镇新丰村鄢家窝棚屯 | AB28: 220881197811216011 | AC28: 洮南市公安局 | AD28: 46216 | AE28: =YEAR(TODAY())-MID(AB28,7,4) -> 48 | AF28: 群众 | AG28: 已婚 | AH28: 177 | AI28: A2 | AJ28: AB | AK28: 15947177929 | AL28: 15804795880 | AM28: 中专 | AN28: 44270 | AO28: 中央广播电视中等专业学 | AP28: 机电技术应用 | AV28: 41302 | AW28: 41361 | AX28: 劳动合同 | AY28: 力量煤业 | AZ28: 44743 | BA28: 45473 | BB28: 2 | BC28: √ | BD28: √ | BE28: √ | BF28: √ | BG28: 3 | BH28: 6 | BK28: √ | BN28: √ | BR28: LM-01-02 | BS28: √ | BT28: √ | CC28: √ | CF28: 2013年
A29: =IF(B29="","",ROW()-1) -> 28 | B29: =IF(AB29="","",AB29) -> 320322198604162517 | C29: 力量煤业 | D29: 直接生产人员 | E29: F10233 | F29: 薛宪伟 | G29: 0 | H29: 0 | I29: =G29+H29 -> 0 | J29: 综采队 | K29: 采煤机司机 | R29: 工人岗 | T29: 正式工 | U29: 41323 | V29: =IF(U29="","",ROUND(YEARFRAC(U29,TODAY(),1),1)) -> 13.4 | W29: 固定期限劳动合同 | X29: =IF(MOD(RIGHT(LEFT(AB29,17)),2),"男","女") -> 男 | Y29: 汉 | Z29: =MID(AB29,7,4)&"-"&MID(AB29,11,2)&"-"&MID(AB29,13,2) -> 1986-04-16 | AA29: 江苏省沛县杨屯镇东姚桥村546号 | AB29: 320322198604162517 | AC29: 沛县公安局 | AD29: 49962 | AE29: =YEAR(TODAY())-MID(AB29,7,4) -> 40 | AF29: 群众 | AG29: 已婚 | AH29: 183 | AI29: - | AJ29: - | AK29: 18247708003 | AL29: 15262100939 | AM29: 大专（函授） | AN29: 44197 | AO29: 国家开放大学 | AP29: 机电一体化 | AR29: 装配式高级工程师（三级） | AT29: 初级工 | AV29: 41323 | AW29: 41382 | AX29: 劳动合同 | AY29: 力量煤业 | AZ29: 44743 | BA29: 45473 | BB29: 2 | BC29: √ | BD29: √ | BE29: √ | BF29: √ | BG29: 2 | BH29: 4 | BK29: √ | BN29: √ | BR29: LM-01-03 | BS29: √ | BT29: √ | CC29: √ | CG29: 特种作业证
A30: =IF(B30="","",ROW()-1) -> 29 | B30: =IF(AB30="","",AB30) -> 132202198001264632 | C30: 力量煤业 | D30: 直接生产人员 | E30: F10528 | F30: 张延朝 | G30: 0 | H30: 0 | I30: =G30+H30 -> 0 | J30: 综采队 | K30: 采煤机司机 | R30: 工人岗 | T30: 正式工 | U30: 43164 | V30: =IF(U30="","",ROUND(YEARFRAC(U30,TODAY(),1),1)) -> 8.3 | W30: 固定期限劳动合同 | X30: =IF(MOD(RIGHT(LEFT(AB30,17)),2),"男","女") -> 男 | Y30: 汉 | Z30: =MID(AB30,7,4)&"-"&MID(AB30,11,2)&"-"&MID(AB30,13,2) -> 1980-01-26 | AA30: 河北省沙河市蝉房乡温家沟村4号 | AB30: 132202198001264632 | AC30: 沙河市公安局 | AD30: 46601 | AE30: =YEAR(TODAY())-MID(AB30,7,4) -> 46 | AF30: 群众 | AG30: 已婚 | AH30: 175 | AI30: C1 | AJ30: O | AK30: 15028919688 | AL30: 13463196896 | AM30: 中专 | AN30: 36678 | AO30: 邢台县浆水中学 | AP30: - | AV30: 43164 | AW30: 43224 | AX30: 劳动合同 | AY30: 力量煤业 | AZ30: 44287 | BA30: 45747 | BB30: 2 | BC30: √ | BD30: √ | BE30: √ | BF30: √ | BG30: 1 | BH30: 2 | BK30: √ | BN30: √ | BR30: LM-02-03 | BS30: √ | BT30: √ | BW30: √ | CC30: √ | CG30: 初中毕业证
A31: =IF(B31="","",ROW()-1) -> 30 | B31: =IF(AB31="","",AB31) -> 132224197605111657 | C31: 力量煤业 | D31: 直接生产人员 | E31: F10530 | F31: 韩志发 | G31: 0 | H31: 0 | I31: =G31+H31 -> 0 | J31: 综采队 | K31: 采煤机司机 | R31: 工人岗 | T31: 正式工 | U31: 43165 | V31: =IF(U31="","",ROUND(YEARFRAC(U31,TODAY(),1),1)) -> 8.3 | W31: 固定期限劳动合同 | X31: =IF(MOD(RIGHT(LEFT(AB31,17)),2),"男","女") -> 男 | Y31: 汉 | Z31: =MID(AB31,7,4)&"-"&MID(AB31,11,2)&"-"&MID(AB31,13,2) -> 1976-05-11 | AA31: 河北省邢台市内丘县金店镇韩郝庄村374号 | AB31: 132224197605111657 | AC31: 内丘县公安局 | AD31: 47218 | AE31: =YEAR(TODAY())-MID(AB31,7,4) -> 50 | AF31: 群众 | AG31: 已婚 | AH31: 170 | AI31: - | AJ31: B | AK31: 15289211913 | AL31: 13172673595 | AM31: 中专 | AN31: 34860 | AO31: 河北省内丘中学 | AP31: - | AR31: 井下采煤机司机（五级） | AV31: 43165 | AW31: 43225 | AX31: 劳动合同 | AY31: 力量煤业 | AZ31: 44287 | BA31: 45747 | BB31: 2 | BC31: √ | BD31: √ | BE31: √ | BF31: √ | BG31: 1 | BH31: 2 | BK31: √ | BM31: √ | BN31: √ | BR31: LM-02-03 | BS31: √ | BT31: √ | BW31: √ | CC31: √
A32: =IF(B32="","",ROW()-1) -> 31 | B32: =IF(AB32="","",AB32) -> 230221197506184212 | C32: 力量煤业 | D32: 直接生产人员 | E32: F10579 | F32: 宋云河 | G32: 0 | H32: 0 | I32: =G32+H32 -> 0 | J32: 综采队 | K32: 采煤机司机 | R32: 工人岗 | T32: 正式工 | U32: 43360 | V32: =IF(U32="","",ROUND(YEARFRAC(U32,TODAY(),1),1)) -> 7.8 | W32: 固定期限劳动合同 | X32: =IF(MOD(RIGHT(LEFT(AB32,17)),2),"男","女") -> 男 | Y32: 汉 | Z32: =MID(AB32,7,4)&"-"&MID(AB32,11,2)&"-"&MID(AB32,13,2) -> 1975-06-18 | AA32: 内蒙古呼伦贝尔市鄂温克族自治旗伊敏河镇翻斗连街45号 | AB32: 230221197506184212 | AC32: 鄂温克族自治旗公安局 | AD32: 46826 | AE32: =YEAR(TODAY())-MID(AB32,7,4) -> 51 | AF32: 群众 | AG32: 已婚 | AH32: 170 | AI32: C1 | AJ32: O | AK32: 18947574241 | AL32: 15149524628 | AM32: 中专 | AN32: 34486 | AO32: 河北城建职工中专学校 | AP32: 采矿技术 | AR32: 井下采煤机司机（五级） | AT32: 初级工 | AV32: 43360 | AW32: 43420 | AX32: 劳动合同 | AY32: 力量煤业 | AZ32: 44470 | BA32: 45199 | BB32: 2 | BC32: √ | BD32: √ | BE32: √ | BF32: √ | BG32: 1 | BH32: 2 | BK32: √ | BM32: √ | BN32: √ | BR32: LM-02-03 | BS32: √ | BT32: √ | BV32: √ | BW32: √ | CB32: √ | CC32: √
A33: =IF(B33="","",ROW()-1) -> 32 | B33: =IF(AB33="","",AB33) -> 130822197805036231 | C33: 力量煤业 | D33: 直接生产人员 | E33: F10767 | F33: 雷铁柱 | G33: 0 | H33: 0 | I33: =G33+H33 -> 0 | J33: 综采队 | K33: 采煤机司机 | R33: 工人岗 | T33: 正式工 | U33: 44254 | V33: =IF(U33="","",ROUND(YEARFRAC(U33,TODAY(),1),1)) -> 5.4 | W33: 固定期限劳动合同 | X33: =IF(MOD(RIGHT(LEFT(AB33,17)),2),"男","女") -> 男 | Y33: 汉 | Z33: =MID(AB33,7,4)&"-"&MID(AB33,11,2)&"-"&MID(AB33,13,2) -> 1978-05-03 | AA33: 河北省遵化市侯家寨乡前后杖子村后杖路28号 | AB33: 130822197805036231 | AC33: 遵化市公安局 | AD33: 48272 | AE33: =YEAR(TODAY())-MID(AB33,7,4) -> 48 | AF33: 群众 | AG33: 已婚 | AH33: 170 | AI33: C1 | AJ33: AB | AK33: 15233372187 | AL33: 13673156131 | AM33: 高中 | AN33: 35948 | AO33: 遵化市第二中学 | AP33: - | AR33: 井下采煤机司机（五级） | AV33: 44254 | AW33: 44312 | AX33: 劳动合同 | AY33: 力量煤业 | AZ33: 44652 | BA33: 45382 | BB33: 2 | BC33: √ | BD33: √ | BE33: √ | BF33: √ | BG33: 0 | BH33: 0 | BK33: √ | BM33: √ | BN33: √ | BR33: LM-03-02 | BS33: √ | BT33: √ | BV33: √ | BW33: √ | CC33: √
A34: =IF(B34="","",ROW()-1) -> 33 | B34: =IF(AB34="","",AB34) -> 130582198710143012 | C34: 力量煤业 | D34: 直接生产人员 | E34: F11221 | F34: 张庆元 | I34: =G34+H34 -> 0 | J34: 综采队 | K34: 采煤机司机 | R34: 工人岗 | T34: 正式工 | U34: 44833 | V34: =IF(U34="","",ROUND(YEARFRAC(U34,TODAY(),1),1)) -> 3.8 | W34: 固定期限劳动合同 | X34: =IF(MOD(RIGHT(LEFT(AB34,17)),2),"男","女") -> 男 | Y34: 汉 | Z34: =MID(AB34,7,4)&"-"&MID(AB34,11,2)&"-"&MID(AB34,13,2) -> 1987-10-14 | AA34: 河北省沙河市白塔镇张下曹村115号 | AB34: 130582198710143012 | AC34: 沙河市公安局 | AD34: 51941 | AE34: =YEAR(TODAY())-MID(AB34,7,4) -> 39 | AF34: 群众 | AG34: 已婚 | AH34: 176 | AJ34: O | AK34: 15127978070 | AL34: 13403399931 | AM34: 中专 | AN34: 42186 | AO34: 忻州市工业学校 | AP34: 煤矿综采技术 | AV34: 44833 | AW34: 44893 | AX34: 劳动合同 | AY34: 力量煤业 | AZ34: 44833 | BA34: 45199 | BB34: 2 | BC34: √ | BD34: √ | BE34: √ | BF34: √ | BG34: 0 | BH34: 0 | BK34: √ | BR34: LM-04-04 | BS34: √ | BT34: √ | BU34: √ | BV34: √ | BW34: √ | BX34: √ | CF34: 2022年
A35: =IF(B35="","",ROW()-1) -> 34 | B35: =IF(AB35="","",AB35) -> 370811198803025037 | C35: 力量煤业 | D35: 直接生产人员 | E35: F11523 | F35: 杨兴国 | I35: =G35+H35 -> 0 | J35: 综采队 | K35: 采煤机司机 | R35: 工人岗 | T35: 正式工 | U35: 45035 | V35: =IF(U35="","",ROUND(YEARFRAC(U35,TODAY(),1),1)) -> 3.2 | W35: 固定期限劳动合同 | X35: =IF(MOD(RIGHT(LEFT(AB35,17)),2),"男","女") -> 男 | Y35: 汉 | Z35: =MID(AB35,7,4)&"-"&MID(AB35,11,2)&"-"&MID(AB35,13,2) -> 1988-03-02 | AA35: 山东省济宁市任城区石桥镇张桥东村济张路32号 | AB35: 370811198803025037 | AC35: 济宁市公安局任城区分局 | AD35: 49646 | AE35: =YEAR(TODAY())-MID(AB35,7,4) -> 38 | AF35: 群众 | AG35: 已婚 | AH35: 175 | AI35: B2 | AJ35: AB | AK35: 15154716771 | AL35: 18254758008 | AM35: 大专 | AN35: 2022年 | AO35: 国家开放大学 | AP35: 机电一体化 | AV35: 45035 | AW35: 45095 | AX35: 劳动合同 | AY35: 力量煤业 | AZ35: 45035 | BA35: 45473 | BB35: 2 | BC35: √ | BD35: √ | BE35: √ | BF35: √ | BG35: 0 | BH35: 0 | BK35: √ | BR35: LM-05-03 | BS35: √ | BT35: √ | BU35: √ | BV35: √ | BW35: √ | BX35: √ | BZ35: √ | CF35: 2023年
A36: =IF(B36="","",ROW()-1) -> 35 | B36: =IF(AB36="","",AB36) -> 130926198808150836 | C36: 力量煤业 | D36: 直接生产人员 | E36: F10367 | F36: 李光辉 | G36: 0 | H36: 0 | I36: =G36+H36 -> 0 | J36: 综采队 | K36: 车间 | R36: 工人岗 | T36: 正式工 | U36: 41991 | V36: =IF(U36="","",ROUND(YEARFRAC(U36,TODAY(),1),1)) -> 11.6 | W36: 固定期限劳动合同 | X36: =IF(MOD(RIGHT(LEFT(AB36,17)),2),"男","女") -> 男 | Y36: 汉 | Z36: =MID(AB36,7,4)&"-"&MID(AB36,11,2)&"-"&MID(AB36,13,2) -> 1988-08-15 | AA36: 河北省沧州市肃宁县窝北镇雪村085号 | AB36: 130926198808150836 | AC36: 肃宁县公安局 | AD36: 50458 | AE36: =YEAR(TODAY())-MID(AB36,7,4) -> 38 | AF36: 群众 | AG36: 已婚 | AH36: 170 | AI36: B2 | AJ36: AB | AK36: 18847710968 | AL36: 18232794309 | AM36: 中专 | AN36: 39278 | AO36: 肃宁指教中心 | AP36: - | AV36: 41991 | AW36: 42053 | AX36: 劳动合同 | AY36: 力量煤业 | AZ36: 44562 | BA36: 45291 | BB36: 2 | BC36: √ | BD36: √ | BE36: √ | BF36: √ | BG36: 2 | BH36: 4 | BK36: √ | BN36: √ | BR36: LM-01-04 | BS36: √ | BT36: √ | CC36: √ | CG36: 村委会无犯罪证明
A37: =IF(B37="","",ROW()-1) -> 36 | B37: =IF(AB37="","",AB37) -> 152723198307031535 | C37: 力量煤业 | D37: 直接生产人员 | E37: F10220 | F37: 全向前 | G37: 0 | H37: 0 | I37: =G37+H37 -> 0 | J37: 综采队 | K37: 电工 | R37: 工人岗 | T37: 正式工 | U37: 41304 | V37: =IF(U37="","",ROUND(YEARFRAC(U37,TODAY(),1),1)) -> 13.4 | W37: 固定期限劳动合同 | X37: =IF(MOD(RIGHT(LEFT(AB37,17)),2),"男","女") -> 男 | Y37: 汉 | Z37: =MID(AB37,7,4)&"-"&MID(AB37,11,2)&"-"&MID(AB37,13,2) -> 1983-07-03 | AA37: 内蒙古鄂尔多斯市准格尔旗龙口镇麻地梁村庄瓦焉社374 | AB37: 152723198307031535 | AC37: 准格尔旗公安局 | AD37: 50778 | AE37: =YEAR(TODAY())-MID(AB37,7,4) -> 43 | AF37: 群众 | AG37: 已婚 | AH37: 178 | AI37: C1 | AJ37: B | AK37: 13848678498 | AL37: 15134928605 | AM37: 高中 | AN37: 37412 | AO37: 山西省府谷县第二中学 | AP37: - | AT37: 初级工 | AV37: 41304 | AW37: 已转正 | AX37: 劳动合同 | AY37: 力量煤业 | AZ37: 44743 | BA37: 45473 | BB37: 2 | BC37: √ | BD37: √ | BE37: √ | BF37: √ | BG37: 0 | BH37: 0 | BK37: √ | BN37: √ | BR37: LM-01-02
A38: =IF(B38="","",ROW()-1) -> 37 | B38: =IF(AB38="","",AB38) -> 150429197811273635 | C38: 力量煤业 | D38: 直接生产人员 | E38: F10232 | F38: 夏玉臣 | G38: 0 | H38: 0 | I38: =G38+H38 -> 0 | J38: 综采队 | K38: 电工 | R38: 工人岗 | T38: 正式工 | U38: 41323 | V38: =IF(U38="","",ROUND(YEARFRAC(U38,TODAY(),1),1)) -> 13.4 | W38: 固定期限劳动合同 | X38: =IF(MOD(RIGHT(LEFT(AB38,17)),2),"男","女") -> 男 | Y38: 汉 | Z38: =MID(AB38,7,4)&"-"&MID(AB38,11,2)&"-"&MID(AB38,13,2) -> 1978-11-27 | AA38: 内蒙古赤峰市宁城县大城子镇四龙头沟村2组 | AB38: 150429197811273635 | AC38: 宁城县公安局 | AD38: 46181 | AE38: =YEAR(TODAY())-MID(AB38,7,4) -> 48 | AF38: 群众 | AG38: 已婚 | AH38: 169 | AI38: - | AJ38: A | AK38: 15934986163 | AL38: 15947169628 | AM38: 高中 | AN38: 37803 | AO38: 四龙中学 | AP38: - | AR38: 综采维修电工（五级） | AT38: 中级工 | AV38: 41323 | AW38: 41382 | AX38: 劳动合同 | AY38: 力量煤业 | AZ38: 44743 | BA38: 45473 | BB38: 2 | BC38: √ | BD38: √ | BE38: √ | BF38: √ | BG38: 2 | BH38: 4 | BK38: √ | BM38: √ | BN38: √ | BR38: LM-01-03 | BS38: √ | BT38: √ | BZ38: √ | CC38: √
A39: =IF(B39="","",ROW()-1) -> 38 | B39: =IF(AB39="","",AB39) -> 152627198903193119 | C39: 力量煤业 | D39: 直接生产人员 | E39: F10561 | F39: 任小龙 | G39: 0 | H39: 0 | I39: =G39+H39 -> 0 | J39: 综采队 | K39: 电工 | R39: 工人岗 | T39: 正式工 | U39: 43252 | V39: =IF(U39="","",ROUND(YEARFRAC(U39,TODAY(),1),1)) -> 8.1 | W39: 固定期限劳动合同 | X39: =IF(MOD(RIGHT(LEFT(AB39,17)),2),"男","女") -> 男 | Y39: 汉 | Z39: =MID(AB39,7,4)&"-"&MID(AB39,11,2)&"-"&MID(AB39,13,2) -> 1989-03-19 | AA39: 内蒙古乌兰察布市兴和县团结乡大五号村委会康家村 | AB39: 152627198903193119 | AC39: 兴和县公安局 | AD39: 49881 | AE39: =YEAR(TODAY())-MID(AB39,7,4) -> 37 | AF39: 群众 | AG39: 未婚 | AH39: 175 | AI39: C1 | AJ39: B | AK39: 15124712528 | AL39: 13948948951 | AM39: 大专（函授） | AN39: 41097 | AO39: 内蒙古工业大学 | AP39: 煤矿开采技术 | AQ39: 助理工程师（采矿/初级） | AS39: C类 | AT39: 初级工 | AV39: 43252 | AW39: 43312 | AX39: 劳动合同 | AY39: 力量煤业 | AZ39: 44378 | BA39: 45107 | BB39: 2 | BC39: √ | BD39: √ | BE39: √ | BF39: √ | BG39: 1 | BH39: 2 | BK39: √ | BL39: √ | BN39: √ | BR39: LM-02-03 | BS39: √ | BT39: √ | BW39: √ | CC39: √
A40: =IF(B40="","",ROW()-1) -> 39 | B40: =IF(AB40="","",AB40) -> 370902197702021218 | C40: 力量煤业 | D40: 直接生产人员 | E40: F10706 | F40: 尹彦明 | G40: 0 | H40: 0 | I40: =G40+H40 -> 0 | J40: 综采队 | K40: 电工 | R40: 工人岗 | T40: 正式工 | U40: 44044 | V40: =IF(U40="","",ROUND(YEARFRAC(U40,TODAY(),1),1)) -> 5.9 | W40: 固定期限劳动合同 | X40: =IF(MOD(RIGHT(LEFT(AB40,17)),2),"男","女") -> 男 | Y40: 汉 | Z40: =MID(AB40,7,4)&"-"&MID(AB40,11,2)&"-"&MID(AB40,13,2) -> 1977-02-02 | AA40: 山东省新泰市东都镇南山路438号3排5号 | AB40: 370902197702021218 | AC40: 新泰市公安局 | AD40: 47260 | AE40: =YEAR(TODAY())-MID(AB40,7,4) -> 49 | AF40: 群众 | AG40: 已婚 | AH40: 172 | AI40: C1 | AJ40: B | AK40: 15048763229 | AL40: 13583885223 | AM40: 中专 | AN40: 35247 | AO40: 山东省泰安化工学校 | AP40: 无机化工工艺 | AR40: 注浆注水工（一级/二级/三级）；采掘电钳工（三级） | AT40: 中级工 | AV40: 44044 | AW40: 44104 | AX40: 劳动合同 | AY40: 力量煤业 | AZ40: 44470 | BA40: 45199 | BB40: 2 | BC40: √ | BD40: √ | BE40: √ | BF40: √ | BG40: 0 | BH40: 0 | BK40: √ | BM40: √ | BN40: √ | BR40: LM-03-01 | BS40: √ | BT40: √ | BV40: √ | BW40: √ | CC40: √ | CG40: 班组长证件/煤矿班组长应急救援培训证
A41: =IF(B41="","",ROW()-1) -> 40 | B41: =IF(AB41="","",AB41) -> 150121200101028317 | C41: 力量煤业 | D41: 直接生产人员 | E41: S11119 | F41: 王鑫 | I41: =G41+H41 -> 0 | J41: 综采队 | K41: 电工 | R41: 工人岗 | T41: 正式工 | U41: 44755 | V41: =IF(U41="","",ROUND(YEARFRAC(U41,TODAY(),1),1)) -> 4 | W41: 固定期限劳动合同 | X41: =IF(MOD(RIGHT(LEFT(AB41,17)),2),"男","女") -> 男 | Y41: 汉 | Z41: =MID(AB41,7,4)&"-"&MID(AB41,11,2)&"-"&MID(AB41,13,2) -> 2001-01-02 | AA41: 内蒙古土默特左旗察素齐镇什兵地村21号 | AB41: 150121200101028317 | AC41: 土默特左旗公安局 | AD41: 47328 | AE41: =YEAR(TODAY())-MID(AB41,7,4) -> 25 | AF41: 共青团员 | AG41: 未婚 | AH41: 175 | AI41: C1 | AJ41: O | AK41: 15248126640 | AL41: 18947161997 | AM41: 本科 | AN41: 44743 | AO41: 内蒙古科技大学 | AP41: 机电一体化 | AV41: 44755 | AW41: 44816 | AX41: 劳动合同 | AY41: 力量煤业 | AZ41: 44755 | BA41: 45199 | BB41: 2 | BC41: √ | BD41: √ | BE41: √ | BF41: √ | BG41: 0 | BH41: 0 | BN41: √ | BR41: LM-04-02 | BS41: √ | BT41: √ | BU41: √ | BV41: √ | BW41: √ | BX41: √ | BY41: √ | CF41: 2022年
A42: =IF(B42="","",ROW()-1) -> 41 | B42: =IF(AB42="","",AB42) -> 152103199304041857 | C42: 力量煤业 | D42: 直接生产人员 | E42: F11313 | F42: 黄金涛 | I42: =G42+H42 -> 0 | J42: 综采队 | K42: 电工 | R42: 工人岗 | T42: 正式工 | U42: 44961 | V42: 0 | W42: 固定期限劳动合同 | X42: 男 | Y42: 汉 | Z42: 1993-04-04 | AA42: 内蒙古扎兰屯市成吉思汗镇大甸子村三组 | AB42: 152103199304041857 | AC42: 扎兰屯市公安局 | AD42: 51954 | AE42: 30 | AF42: 群众 | AG42: 未婚 | AH42: 175 | AJ42: A | AK42: 15147087353 | AL42: 15148788168 | AM42: 中专 | AN42: 41791 | AO42: 呼伦贝尔市高级技工学校 | AP42: 电气自动化设备安装与维修 | AV42: 44961 | AW42: 45019 | AX42: 劳动合同 | AY42: 力量煤业 | AZ42: 44961 | BA42: 45382 | BB42: 2 | BC42: √ | BD42: √ | BE42: √ | BF42: √ | BG42: 0 | BH42: 0 | BK42: √ | BR42: LM-04-04 | BS42: √ | BT42: √ | BU42: √ | BV42: √ | BW42: √ | BX42: √ | CF42: 2022年
A43: =IF(B43="","",ROW()-1) -> 42 | B43: =IF(AB43="","",AB43) -> 13052119890719729X | C43: 力量煤业 | D43: 直接生产人员 | E43: F11361 | F43: 甄晓杰 | I43: =G43+H43 -> 0 | J43: 安装队 | K43: 支架工 | R43: 工人岗 | T43: 正式工 | U43: 44967 | V43: 0 | W43: 固定期限劳动合同 | X43: 男 | Y43: 汉 | Z43: 1989-07-19 | AA43: 河北省邢台市邢台县白岸乡麦条沟村047号 | AB43: 13052119890719729X | AC43: 邢台县公安局 | AD43: 44902 | AE43: 34 | AF43: 群众 | AG43: 已婚 | AH43: 178 | AJ43: AB | AK43: 18833481268 | AL43: 18732995605 | AM43: 中专 | AN43: 43282 | AO43: 山西省煤炭职业中等专业学校 | AP43: 采煤 | AV43: =U43 -> 44967 | AW43: 45025 | AX43: 劳动合同 | AY43: 力量煤业 | AZ43: 44967 | BA43: 45382 | BB43: 2 | BC43: √ | BD43: √ | BE43: √ | BF43: √ | BG43: 0 | BH43: 0 | BK43: √ | BR43: LM-04-04 | BS43: √ | BT43: √ | BU43: √ | BV43: √ | BW43: √ | BX43: √ | CF43: 2023年
A44: =IF(B44="","",ROW()-1) -> 43 | B44: =IF(AB44="","",AB44) -> 152104198606012519 | C44: 力量煤业 | D44: 直接生产人员 | E44: F11552 | F44: 张宗伟 | I44: =G44+H44 -> 0 | J44: 综采队 | K44: 电钳工 | R44: 工人岗 | T44: 正式工 | U44: 45056 | V44: =IF(U44="","",ROUND(YEARFRAC(U44,TODAY(),1),1)) -> 3.2 | W44: 固定期限劳动合同 | X44: =IF(MOD(RIGHT(LEFT(AB44,17)),2),"男","女") -> 男 | Y44: 汉 | Z44: =MID(AB44,7,4)&"-"&MID(AB44,11,2)&"-"&MID(AB44,13,2) -> 1986-06-01 | AA44: 内蒙古牙克石市乌奴耳镇伊列克得35号 | AB44: 152104198606012519 | AC44: 牙克石市公安局 | AD44: 49932 | AE44: =YEAR(TODAY())-MID(AB44,7,4) -> 40 | AF44: 群众 | AG44: 已婚 | AH44: 179 | AJ44: A | AK44: 13474945153 | AL44: 15947206607 | AM44: 大专 | AN44: 41821 | AO44: 黑龙江科技大学 | AP44: 矿山机电 | AV44: 45056 | AW44: 45116 | AX44: 劳动合同 | AY44: 力量煤业 | AZ44: 45056 | BA44: 45473 | BB44: 2 | BC44: √ | BD44: √ | BE44: √ | BF44: √ | BG44: 0 | BH44: 0 | BK44: √ | BR44: LM-05-03 | BS44: √ | BT44: √ | BU44: √ | BV44: √ | BW44: √ | BX44: √ | BZ44: √ | CF44: 2023年
A45: =IF(B45="","",ROW()-1) -> 44 | B45: =IF(AB45="","",AB45) -> 21122119770210183X | C45: 力量煤业 | D45: 直接生产人员 | E45: F10211 | F45: 张永大 | G45: 0 | H45: 0 | I45: =G45+H45 -> 0 | J45: 综采队 | K45: 端头支护工 | R45: 工人岗 | T45: 正式工 | U45: 41294 | V45: =IF(U45="","",ROUND(YEARFRAC(U45,TODAY(),1),1)) -> 13.5 | W45: 固定期限劳动合同 | X45: =IF(MOD(RIGHT(LEFT(AB45,17)),2),"男","女") -> 男 | Y45: 汉 | Z45: =MID(AB45,7,4)&"-"&MID(AB45,11,2)&"-"&MID(AB45,13,2) -> 1977-02-10 | AA45: 辽宁省铁岭县双井子乡高家店村五组58号 | AB45: 21122119770210183X | AC45: 铁岭县公安局 | AD45: 46500 | AE45: =YEAR(TODAY())-MID(AB45,7,4) -> 49 | AF45: 群众 | AG45: 已婚 | AH45: 176 | AI45: A2 | AJ45: AB | AK45: 14747969346 | AL45: 14747969341 | AM45: 大专（函授） | AN45: 44408 | AO45: 国家开放大学 | AP45: 机电一体化技术 | AV45: 41294 | AW45: 已转正 | AX45: 劳动合同 | AY45: 力量煤业 | AZ45: 44743 | BA45: 45473 | BB45: 2 | BC45: √ | BD45: √ | BE45: √ | BF45: √ | BG45: 0 | BH45: 0 | BK45: √ | BN45: √ | BR45: LM-01-02
A46: =IF(B46="","",ROW()-1) -> 45 | B46: =IF(AB46="","",AB46) -> 130521197406287516 | C46: 力量煤业 | D46: 直接生产人员 | E46: F10362 | F46: 乔海臣 | G46: 0 | H46: 0 | I46: =G46+H46 -> 0 | J46: 综采队 | K46: 端头支护工 | R46: 工人岗 | T46: 正式工 | U46: 41981 | V46: =IF(U46="","",ROUND(YEARFRAC(U46,TODAY(),1),1)) -> 11.6 | W46: 固定期限劳动合同 | X46: =IF(MOD(RIGHT(LEFT(AB46,17)),2),"男","女") -> 男 | Y46: 汉 | Z46: =MID(AB46,7,4)&"-"&MID(AB46,11,2)&"-"&MID(AB46,13,2) -> 1974-06-28 | AA46: 河北省邢台市邢台县路罗镇桃树坪村429号 | AB46: 130521197406287516 | AC46: 邢台县公安局 | AD46: 50322 | AE46: =YEAR(TODAY())-MID(AB46,7,4) -> 52 | AF46: 群众 | AG46: 已婚 | AH46: 171 | AI46: B2 | AJ46: O | AK46: 18832992590 | AL46: 15030950564 | AM46: 中专 | AN46: 34212 | AO46: 河北省邢台县浆水中学 | AP46: - | AT46: 中级工 | AV46: 41981 | AW46: 42043 | AX46: 劳动合同 | AY46: 力量煤业 | AZ46: 44562 | BA46: 45291 | BB46: 2 | BC46: √ | BD46: √ | BE46: √ | BF46: √ | BG46: 2 | BH46: 4 | BK46: √ | BN46: √ | BR46: LM-01-04 | BS46: √ | CC46: √ | CG46: 村委会无犯罪证明
A47: =IF(B47="","",ROW()-1) -> 46 | B47: =IF(AB47="","",AB47) -> 21070419740507621X | C47: 力量煤业 | D47: 直接生产人员 | E47: F10365 | F47: 杨树宇 | G47: 0 | H47: 0 | I47: =G47+H47 -> 0 | J47: 综采队 | K47: 端头支护工 | R47: 工人岗 | T47: 正式工 | U47: 41981 | V47: =IF(U47="","",ROUND(YEARFRAC(U47,TODAY(),1),1)) -> 11.6 | W47: 固定期限劳动合同 | X47: =IF(MOD(RIGHT(LEFT(AB47,17)),2),"男","女") -> 男 | Y47: 汉 | Z47: =MID(AB47,7,4)&"-"&MID(AB47,11,2)&"-"&MID(AB47,13,2) -> 1974-05-07 | AA47: 辽宁省葫芦岛市南票区文明路33栋1号 | AB47: 21070419740507621X | AC47: 葫芦岛公安局 | AD47: 47995 | AE47: =YEAR(TODAY())-MID(AB47,7,4) -> 52 | AF47: 群众 | AG47: 已婚 | AH47: 178 | AI47: C1 | AJ47: B | AK47: 18647769689 | AL47: 13842985220 | AM47: 中专 | AN47: 44193 | AO47: 中央广播电视中等专业学校 | AP47: 机电技术应用 | AR47: 胶带/转载机操作工（五级） | AV47: 41981 | AW47: 42043 | AX47: 劳动合同 | AY47: 力量煤业 | AZ47: 44562 | BA47: 45291 | BB47: 2 | BC47: √ | BD47: √ | BE47: √ | BF47: √ | BG47: 2 | BH47: 4 | BK47: √ | BM47: √ | BN47: √ | BR47: LM-01-04 | BS47: √ | BT47: √ | CC47: √ | CG47: 村委会无犯罪证明/特种作业操作证
A48: =IF(B48="","",ROW()-1) -> 47 | B48: =IF(AB48="","",AB48) -> 150429197412163615 | C48: 力量煤业 | D48: 直接生产人员 | E48: F10430 | F48: 蒋国成 | G48: 0 | H48: 0 | I48: =G48+H48 -> 0 | J48: 综采队 | K48: 端头支护工 | R48: 工人岗 | T48: 正式工 | U48: 42688 | V48: =IF(U48="","",ROUND(YEARFRAC(U48,TODAY(),1),1)) -> 9.6 | W48: 固定期限劳动合同 | X48: =IF(MOD(RIGHT(LEFT(AB48,17)),2),"男","女") -> 男 | Y48: 汉 | Z48: =MID(AB48,7,4)&"-"&MID(AB48,11,2)&"-"&MID(AB48,13,2) -> 1974-12-16 | AA48: 内蒙古赤峰市宁城县大城子镇四龙头沟村4组 | AB48: 150429197412163615 | AC48: 宁城县公安局 | AD48: 46180 | AE48: =YEAR(TODAY())-MID(AB48,7,4) -> 52 | AF48: 群众 | AG48: 已婚 | AH48: 165 | AI48: - | AJ48: O | AK48: 15947551297 | AL48: 13789792972 | AM48: 高中 | AN48: 33390 | AO48: 宁城中学 | AP48: - | AV48: 42688 | AW48: 42748 | AX48: 劳动合同 | AY48: 力量煤业 | AZ48: 44562 | BA48: 45291 | BB48: 2 | BC48: √ | BD48: √ | BE48: √ | BF48: √ | BG48: 1 | BH48: 2 | BK48: √ | BN48: √ | BR48: LM-02-01 | BS48: √ | BW48: √ | CC48: √
A49: =IF(B49="","",ROW()-1) -> 48 | B49: =IF(AB49="","",AB49) -> 210124197404192617 | C49: 力量煤业 | D49: 直接生产人员 | E49: F10453 | F49: 刘新 | G49: 0 | H49: 0 | I49: =G49+H49 -> 0 | J49: 综采队 | K49: 端头支护工 | R49: 工人岗 | T49: 正式工 | U49: 42808 | V49: =IF(U49="","",ROUND(YEARFRAC(U49,TODAY(),1),1)) -> 9.3 | W49: 固定期限劳动合同 | X49: =IF(MOD(RIGHT(LEFT(AB49,17)),2),"男","女") -> 男 | Y49: 汉 | Z49: =MID(AB49,7,4)&"-"&MID(AB49,11,2)&"-"&MID(AB49,13,2) -> 1974-04-19 | AA49: 辽宁省法库县和平乡鲍家屯村10组30号 | AB49: 210124197404192617 | AC49: 法库县公安局 | AD49: 46008 | AE49: =YEAR(TODAY())-MID(AB49,7,4) -> 52 | AF49: 群众 | AG49: 已婚 | AH49: 177 | AI49: C1 | AJ49: AB | AK49: 17097446118 | AL49: 13478207499 | AM49: 大专（函授） | AN49: 33420 | AO49: 和平中学 | AP49: - | AR49: 液压支架工（五级） | AV49: 42808 | AW49: 42868 | AX49: 劳动合同 | AY49: 力量煤业 | AZ49: 44652 | BA49: 45382 | BB49: 2 | BC49: √ | BD49: √ | BE49: √ | BF49: √ | BG49: 1 | BH49: 2 | BK49: √ | BM49: √ | BN49: √ | BR49: LM-02-02 | BS49: √ | BT49: √ | BW49: √ | CC49: √
A50: =IF(B50="","",ROW()-1) -> 49 | B50: =IF(AB50="","",AB50) -> 370826198403242838 | C50: 力量煤业 | D50: 直接生产人员 | E50: F10379 | F50: 杨纪仓 | G50: 0 | H50: 0 | I50: =G50+H50 -> 0 | J50: 综采队 | K50: 副班长 | R50: 工人岗 | T50: 正式工 | U50: 42438 | V50: =IF(U50="","",ROUND(YEARFRAC(U50,TODAY(),1),1)) -> 10.3 | W50: 固定期限劳动合同 | X50: =IF(MOD(RIGHT(LEFT(AB50,17)),2),"男","女") -> 男 | Y50: 汉 | Z50: =MID(AB50,7,4)&"-"&MID(AB50,11,2)&"-"&MID(AB50,13,2) -> 1984-03-24 | AA50: 山东省微山县赵庙镇佀楼村中心路北1巷010号 | AB50: 370826198403242838 | AC50: 微山县公安局 | AD50: 50231 | AE50: =YEAR(TODAY())-MID(AB50,7,4) -> 42 | AF50: 群众 | AG50: 已婚 | AH50: 178 | AI50: C1 | AJ50: B | AK50: 15149436941 | AL50: 18052207900 | AM50: 大专（函授） | AN50: 38898 | AO50: 湖北职业技术学院 | AP50: 会计电算化 | AS50: C类 | AT50: 初级工 | AV50: 42438 | AW50: 42499 | AX50: 劳动合同 | AY50: 力量煤业 | AZ50: 44287 | BA50: 45747 | BB50: 2 | BC50: √ | BD50: √ | BE50: √ | BF50: √ | BG50: 1 | BH50: 2 | BK50: √ | BN50: √ | BR50: LM-02-01 | BS50: √ | BT50: √ | CC50: √
A51: =IF(B51="","",ROW()-1) -> 50 | B51: =IF(AB51="","",AB51) -> 130521198210167015 | C51: 力量煤业 | D51: 直接生产人员 | E51: F10531 | F51: 马小东 | G51: 0 | H51: 0 | I51: =G51+H51 -> 0 | J51: 综采队 | K51: 副班长 | R51: 工人岗 | T51: 正式工 | U51: 43167 | V51: =IF(U51="","",ROUND(YEARFRAC(U51,TODAY(),1),1)) -> 8.3 | W51: 固定期限劳动合同 | X51: =IF(MOD(RIGHT(LEFT(AB51,17)),2),"男","女") -> 男 | Y51: 汉 | Z51: =MID(AB51,7,4)&"-"&MID(AB51,11,2)&"-"&MID(AB51,13,2) -> 1982-10-16 | AA51: 河北省邢台市邢台县路罗镇桃树坪村979号 | AB51: 130521198210167015 | AC51: 邢台县公安局 | AD51: 50442 | AE51: =YEAR(TODAY())-MID(AB51,7,4) -> 44 | AF51: 群众 | AG51: 已婚 | AH51: 173 | AI51: - | AJ51: O | AK51: 15134905646 | AL51: 18231928750 | AM51: 中专 | AN51: 43586 | AO51: 路罗中学 | AP51: - | AT51: 高级工 | AV51: 43167 | AW51: 43227 | AX51: 劳动合同 | AY51: 力量煤业 | AZ51: 44287 | BA51: 45747 | BB51: 2 | BC51: √ | BD51: √ | BE51: √ | BF51: √ | BG51: 1 | BH51: 2 | BK51: √ | BN51: √ | BR51: LM-02-03 | BS51: √ | BT51: √ | BW51: √ | CC51: √
A52: =IF(B52="","",ROW()-1) -> 51 | B52: =IF(AB52="","",AB52) -> 150426197806080397 | C52: 力量煤业 | D52: 直接生产人员 | E52: F10550 | F52: 从晓岭 | G52: 0 | H52: 0 | I52: =G52+H52 -> 0 | J52: 综采队 | K52: 副班长 | R52: 工人岗 | T52: 正式工 | U52: 43209 | V52: =IF(U52="","",ROUND(YEARFRAC(U52,TODAY(),1),1)) -> 8.2 | W52: 固定期限劳动合同 | X52: =IF(MOD(RIGHT(LEFT(AB52,17)),2),"男","女") -> 男 | Y52: 汉 | Z52: =MID(AB52,7,4)&"-"&MID(AB52,11,2)&"-"&MID(AB52,13,2) -> 1978-06-08 | AA52: 内蒙古赤峰市翁牛特旗乌敦套海镇新城居委会一巷 | AB52: 150426197806080397 | AC52: 翁牛特旗公安局 | AD52: 49980 | AE52: =YEAR(TODAY())-MID(AB52,7,4) -> 48 | AF52: 群众 | AG52: 已婚 | AH52: 172 | AI52: A2 | AJ52: O | AK52: 18748018119 | AL52: 15048663313 | AM52: 中专 | AN52: 44646 | AO52: 中央广播电视中等专业学院 | AP52: - | AR52: 液压支架工（五级） | AV52: 43209 | AW52: 43269 | AX52: 劳动合同 | AY52: 力量煤业 | AZ52: 44378 | BA52: 45107 | BB52: 2 | BC52: √ | BD52: √ | BE52: √ | BF52: √ | BG52: 1 | BH52: 2 | BK52: √ | BM52: √ | BN52: √ | BR52: LM-02-03 | BS52: √ | BT52: √ | BW52: √ | CC52: √
A53: =IF(B53="","",ROW()-1) -> 52 | B53: =IF(AB53="","",AB53) -> 130523198310251698 | C53: 力量煤业 | D53: 直接生产人员 | E53: F11368 | F53: 郝云石 | I53: =G53+H53 -> 0 | J53: 综采队 | K53: 检修电工 | R53: 工人岗 | T53: 正式工 | U53: 44968 | V53: 0 | W53: 固定期限劳动合同 | X53: 男 | Y53: 汉 | Z53: 1983-10-25 | AA53: 河北省邢台市内丘县金店镇大辛庄村101号 | AB53: 130523198310251698 | AC53: 内丘县公安局 | AD53: 50639 | AE53: 40 | AF53: 群众 | AG53: 已婚 | AH53: 168 | AI53: C1 | AK53: 13111206735 | AL53: 15031928763 | AM53: 高中 | AN53: 2004年 | AO53: 内丘中学 | AV53: 44968 | AW53: 45026 | AX53: 劳动合同 | AY53: 力量煤业 | AZ53: 44968 | BA53: 45382 | BB53: 2 | BC53: √ | BD53: √ | BE53: √ | BF53: √ | BG53: 0 | BH53: 0 | BK53: √ | BR53: LM-04-04 | BS53: √ | BT53: √ | BU53: √ | BV53: √ | BW53: √ | BX53: √ | CF53: 2023年
A54: =IF(B54="","",ROW()-1) -> 53 | B54: =IF(AB54="","",AB54) -> 370829199012251730 | C54: 力量煤业 | D54: 直接生产人员 | E54: F10609 | F54: 付相红 | G54: 0 | H54: 0 | I54: =G54+H54 -> 0 | J54: 综采队 | K54: 库房管理员 | R54: 工人岗 | T54: 正式工 | U54: 43537 | V54: =IF(U54="","",ROUND(YEARFRAC(U54,TODAY(),1),1)) -> 7.3 | W54: 固定期限劳动合同 | X54: =IF(MOD(RIGHT(LEFT(AB54,17)),2),"男","女") -> 男 | Y54: 汉 | Z54: =MID(AB54,7,4)&"-"&MID(AB54,11,2)&"-"&MID(AB54,13,2) -> 1990-12-25 | AA54: 山东省嘉祥县满硐乡上吴村16号 | AB54: 370829199012251730 | AC54: 嘉祥县公安局 | AD54: 51859 | AE54: =YEAR(TODAY())-MID(AB54,7,4) -> 36 | AF54: 群众 | AG54: 未婚 | AH54: 170 | AI54: C1 | AJ54: O | AK54: 17560748497 | AL54: 17560748437 | AM54: 中专 | AN54: 41426 | AO54: 潍坊交通职业学院 | AP54: 轮机维修 | AT54: 初级工 | AV54: 43537 | AW54: 43597 | AX54: 劳动合同 | AY54: 力量煤业 | AZ54: 44652 | BA54: 45383 | BB54: 2 | BC54: √ | BD54: √ | BE54: √ | BF54: √ | BG54: 1 | BH54: 2 | BK54: √ | BN54: √ | BR54: LM-02-04 | BS54: √ | BT54: √ | BV54: √ | BW54: √ | CC54: √
A55: =IF(B55="","",ROW()-1) -> 54 | B55: =IF(AB55="","",AB55) -> 320322197303160812 | C55: 力量煤业 | D55: 直接生产人员 | E55: F10227 | F55: 葛兵祥 | G55: 0 | H55: 0 | I55: =G55+H55 -> 0 | J55: 综采队 | K55: 拉架工 | R55: 工人岗 | T55: 正式工 | U55: 41323 | V55: =IF(U55="","",ROUND(YEARFRAC(U55,TODAY(),1),1)) -> 13.4 | W55: 固定期限劳动合同 | X55: =IF(MOD(RIGHT(LEFT(AB55,17)),2),"男","女") -> 男 | Y55: 汉 | Z55: =MID(AB55,7,4)&"-"&MID(AB55,11,2)&"-"&MID(AB55,13,2) -> 1973-03-16 | AA55: 江苏省沛县大屯镇后西关庄25号 | AB55: 320322197303160812 | AC55: 沛县公安局 | AD55: 46413 | AE55: =YEAR(TODAY())-MID(AB55,7,4) -> 53 | AF55: 群众 | AG55: 已婚 | AH55: 172 | AI55: - | AJ55: - | AK55: 15149676232 | AL55: 15852337176 | AM55: 高中 | AN55: 33756 | AO55: 湖西中学 | AP55: - | AR55: 液压支架工（五级） | AV55: 41323 | AW55: 41382 | AX55: 劳动合同 | AY55: 力量煤业 | AZ55: 44743 | BA55: 45473 | BB55: 2 | BC55: √ | BD55: √ | BE55: √ | BF55: √ | BG55: 2 | BH55: 4 | BK55: √ | BM55: √ | BN55: √ | BR55: LM-01-02 | BS55: √ | BT55: √ | CC55: √
A56: =IF(B56="","",ROW()-1) -> 55 | B56: =IF(AB56="","",AB56) -> 411081197212076857 | C56: 力量煤业 | D56: 直接生产人员 | E56: F10228 | F56: 卢志远 | G56: 0 | H56: 0 | I56: =G56+H56 -> 0 | J56: 综采队 | K56: 拉架工 | R56: 工人岗 | T56: 正式工 | U56: 41323 | V56: =IF(U56="","",ROUND(YEARFRAC(U56,TODAY(),1),1)) -> 13.4 | W56: 固定期限劳动合同 | X56: =IF(MOD(RIGHT(LEFT(AB56,17)),2),"男","女") -> 男 | Y56: 汉 | Z56: =MID(AB56,7,4)&"-"&MID(AB56,11,2)&"-"&MID(AB56,13,2) -> 1972-12-07 | AA56: 河南省禹州市文殊镇文殊村8组 | AB56: 411081197212076857 | AC56: 禹州市公安局 | AD56: 45998 | AE56: =YEAR(TODAY())-MID(AB56,7,4) -> 54 | AF56: 群众 | AG56: 已婚 | AH56: 171 | AI56: - | AJ56: - | AK56: 18204773370 | AL56: 13460523722 | AM56: 高中 | AN56: 33756 | AO56: 禹州市第一高级中学 | AP56: - | AV56: 41323 | AW56: 41382 | AX56: 劳动合同 | AY56: 力量煤业 | AZ56: 44743 | BA56: 45473 | BB56: 2 | BC56: √ | BD56: √ | BE56: √ | BF56: √ | BG56: 2 | BH56: 4 | BK56: √ | BN56: √ | BR56: LM-01-02 | BS56: √ | BT56: √ | CC56: √ | CG56: 自愿放弃缴纳住房公积金说明
A57: =IF(B57="","",ROW()-1) -> 56 | B57: =IF(AB57="","",AB57) -> 411081197207251278 | C57: 力量煤业 | D57: 直接生产人员 | E57: F10234 | F57: 殷俊红 | G57: 0 | H57: 0 | I57: =G57+H57 -> 0 | J57: 综采队 | K57: 拉架工 | R57: 工人岗 | T57: 正式工 | U57: 41323 | V57: =IF(U57="","",ROUND(YEARFRAC(U57,TODAY(),1),1)) -> 13.4 | W57: 固定期限劳动合同 | X57: =IF(MOD(RIGHT(LEFT(AB57,17)),2),"男","女") -> 男 | Y57: 汉 | Z57: =MID(AB57,7,4)&"-"&MID(AB57,11,2)&"-"&MID(AB57,13,2) -> 1972-07-25 | AA57: 河南省禹州市方山镇付家村１组 | AB57: 411081197207251278 | AC57: 禹州市公安局 | AD57: 46006 | AE57: =YEAR(TODAY())-MID(AB57,7,4) -> 54 | AF57: 群众 | AG57: 已婚 | AH57: 167 | AI57: - | AJ57: O | AK57: 15147737964 | AL57: 15836522784 | AM57: 高中 | AN57: 33025 | AO57: 禹州市第三高级中学 | AP57: - | AR57: 液压支架工（五级） | AV57: 41323 | AW57: 41382 | AX57: 劳动合同 | AY57: 力量煤业 | AZ57: 44743 | BA57: 45473 | BB57: 2 | BC57: √ | BD57: √ | BE57: √ | BF57: √ | BG57: 2 | BH57: 4 | BK57: √ | BM57: √ | BN57: √ | BR57: LM-01-03 | BS57: √ | BT57: √ | CC57: √ | CE57: √ | CG57: 自愿放弃缴纳住房公积金说明
A58: =IF(B58="","",ROW()-1) -> 57 | B58: =IF(AB58="","",AB58) -> 130226197212015251 | C58: 力量煤业 | D58: 直接生产人员 | E58: F10257 | F58: 陈春余 | G58: 0 | H58: 0 | I58: =G58+H58 -> 0 | J58: 综采队 | K58: 拉架工 | R58: 工人岗 | T58: 正式工 | U58: 41327 | V58: =IF(U58="","",ROUND(YEARFRAC(U58,TODAY(),1),1)) -> 13.4 | W58: 固定期限劳动合同 | X58: =IF(MOD(RIGHT(LEFT(AB58,17)),2),"男","女") -> 男 | Y58: 汉 | Z58: =MID(AB58,7,4)&"-"&MID(AB58,11,2)&"-"&MID(AB58,13,2) -> 1972-12-01 | AA58: 河北省迁安市五重安乡黄金寨村503号 | AB58: 130226197212015251 | AC58: 迁安市公安局 | AD58: 46686 | AE58: =YEAR(TODAY())-MID(AB58,7,4) -> 54 | AF58: 中共党员 | AG58: 已婚 | AH58: 175 | AI58: - | AJ58: - | AK58: 15147790535 | AL58: 18732584174 | AM58: 中专 | AN58: 33420 | AO58: 迁安县大崔庄高中 | AP58: - | AV58: 41327 | AW58: 41386 | AX58: 劳动合同 | AY58: 力量煤业 | AZ58: 44743 | BA58: 45473 | BB58: 2 | BC58: √ | BD58: √ | BE58: √ | BF58: √ | BG58: 2 | BH58: 4 | BK58: √ | BN58: √ | BR58: LM-01-03 | BS58: √ | BT58: √ | CC58: √ | CG58: 农村缴纳医疗证明
A59: =IF(B59="","",ROW()-1) -> 58 | B59: =IF(AB59="","",AB59) -> 130227197205263616 | C59: 力量煤业 | D59: 直接生产人员 | E59: F10290 | F59: 李艳奎 | G59: 0 | H59: 0 | I59: =G59+H59 -> 0 | J59: 综采队 | K59: 拉架工 | R59: 工人岗 | T59: 正式工 | U59: 41362 | V59: =IF(U59="","",ROUND(YEARFRAC(U59,TODAY(),1),1)) -> 13.3 | W59: 固定期限劳动合同 | X59: =IF(MOD(RIGHT(LEFT(AB59,17)),2),"男","女") -> 男 | Y59: 汉 | Z59: =MID(AB59,7,4)&"-"&MID(AB59,11,2)&"-"&MID(AB59,13,2) -> 1972-05-26 | AA59: 河北省唐山市迁西县罗家屯镇沙涧村522号 | AB59: 130227197205263616 | AC59: 迁西县公安局 | AD59: 46384 | AE59: =YEAR(TODAY())-MID(AB59,7,4) -> 54 | AF59: 群众 | AG59: 已婚 | AH59: 173 | AI59: C1 | AJ59: O | AK59: 15147521056 | AL59: 15102571832 | AM59: 高中 | AN59: 33756 | AO59: 迁西罗家屯高中 | AP59: - | AR59: 液压支架工（五级） | AV59: 41362 | AW59: 41423 | AX59: 劳动合同 | AY59: 力量煤业 | AZ59: 44743 | BA59: 45473 | BB59: 2 | BC59: √ | BD59: √ | BE59: √ | BF59: √ | BG59: 2 | BH59: 4 | BK59: √ | BM59: √ | BN59: √ | BR59: LM-01-03 | BS59: √ | BT59: √ | BZ59: √ | CC59: √ | CG59: 高中毕业证
A60: =IF(B60="","",ROW()-1) -> 59 | B60: =IF(AB60="","",AB60) -> 32032219760714087X | C60: 力量煤业 | D60: 直接生产人员 | E60: F10364 | F60: 徐建岗 | G60: 0 | H60: 0 | I60: =G60+H60 -> 0 | J60: 综采队 | K60: 拉架工 | R60: 工人岗 | T60: 正式工 | U60: 41981 | V60: =IF(U60="","",ROUND(YEARFRAC(U60,TODAY(),1),1)) -> 11.6 | W60: 固定期限劳动合同 | X60: =IF(MOD(RIGHT(LEFT(AB60,17)),2),"男","女") -> 男 | Y60: 汉 | Z60: =MID(AB60,7,4)&"-"&MID(AB60,11,2)&"-"&MID(AB60,13,2) -> 1976-07-14 | AA60: 江苏省沛县大屯镇徐庄398号 | AB60: 32032219760714087X | AC60: 沛县公安局 | AD60: 46229 | AE60: =YEAR(TODAY())-MID(AB60,7,4) -> 50 | AF60: 群众 | AG60: 已婚 | AH60: 178 | AI60: - | AJ60: O | AK60: 18648373361 | AL60: 13585489854 | AM60: 中专 | AN60: 44193 | AO60: 中央广播电视中等专业学校 | AP60: 机电一体化 | AV60: 41981 | AW60: 42043 | AX60: 劳动合同 | AY60: 力量煤业 | AZ60: 44562 | BA60: 45291 | BB60: 2 | BC60: √ | BD60: √ | BE60: √ | BF60: √ | BG60: 2 | BH60: 4 | BK60: √ | BN60: √ | BR60: LM-01-04 | BS60: √ | BT60: √ | CC60: √ | CG60: 村委会无犯罪证明/特种作业操作证
A61: =IF(B61="","",ROW()-1) -> 60 | B61: =IF(AB61="","",AB61) -> 150429197608174834 | C61: 力量煤业 | D61: 直接生产人员 | E61: F10403 | F61: 王得祥 | G61: 0 | H61: 0 | I61: =G61+H61 -> 0 | J61: 安装队 | K61: 绞车司机 | R61: 工人岗 | T61: 正式工 | U61: 42548 | V61: =IF(U61="","",ROUND(YEARFRAC(U61,TODAY(),1),1)) -> 10 | W61: 固定期限劳动合同 | X61: =IF(MOD(RIGHT(LEFT(AB61,17)),2),"男","女") -> 男 | Y61: 汉 | Z61: =MID(AB61,7,4)&"-"&MID(AB61,11,2)&"-"&MID(AB61,13,2) -> 1976-08-17 | AA61: 内蒙古赤峰市宁城县大明镇纪家店村7组 | AB61: 150429197608174834 | AC61: 宁城县公安局 | AD61: 47187 | AE61: =YEAR(TODAY())-MID(AB61,7,4) -> 50 | AF61: 群众 | AG61: 已婚 | AH61: 178 | AI61: - | AJ61: - | AK61: 13624870469 | AL61: 13514861034 | AM61: 高中 | AN61: 33756 | AO61: 中诚高中 | AP61: - | AR61: 液压支架工（五级） | AV61: 42548 | AW61: 42608 | AX61: 劳动合同 | AY61: 力量煤业 | AZ61: 44378 | BA61: 45107 | BB61: 2 | BC61: √ | BD61: √ | BE61: √ | BF61: √ | BG61: 1 | BH61: 2 | BK61: √ | BM61: √ | BN61: √ | BR61: LM-02-01 | BS61: √ | BT61: √ | CC61: √ | CG61: 特种作业操作证
A62: =IF(B62="","",ROW()-1) -> 61 | B62: =IF(AB62="","",AB62) -> 13052119770220157X | C62: 力量煤业 | D62: 直接生产人员 | E62: F10409 | F62: 董少尉 | G62: 0 | H62: 0 | I62: =G62+H62 -> 0 | J62: 综采队 | K62: 拉架工 | R62: 工人岗 | T62: 正式工 | U62: 42576 | V62: =IF(U62="","",ROUND(YEARFRAC(U62,TODAY(),1),1)) -> 9.9 | W62: 固定期限劳动合同 | X62: =IF(MOD(RIGHT(LEFT(AB62,17)),2),"男","女") -> 男 | Y62: 汉 | Z62: =MID(AB62,7,4)&"-"&MID(AB62,11,2)&"-"&MID(AB62,13,2) -> 1977-02-20 | AA62: 河北省邢台市邢台县会宁镇董家沟村065号 | AB62: 13052119770220157X | AC62: 邢台县公安局 | AD62: 46173 | AE62: =YEAR(TODAY())-MID(AB62,7,4) -> 49 | AF62: 群众 | AG62: 已婚 | AH62: 170 | AI62: - | AJ62: B | AK62: 15049897592 | AL62: 13172691731 | AM62: 中专 | AN62: 44256 | AO62: 中央广播电视中等专业学校 | AP62: 机电技术应用 | AR62: 液压支架工（五级） | AT62: 初级工 | AV62: 42576 | AW62: 42637 | AX62: 劳动合同 | AY62: 力量煤业 | AZ62: 44470 | BA62: 45199 | BB62: 2 | BC62: √ | BD62: √ | BE62: √ | BF62: √ | BG62: 2 | BH62: 4 | BK62: √ | BM62: √ | BN62: √ | BR62: LM-02-01 | BS62: √ | BT62: √ | CC62: √
A63: =IF(B63="","",ROW()-1) -> 62 | B63: =IF(AB63="","",AB63) -> 150428198604030110 | C63: 力量煤业 | D63: 直接生产人员 | E63: F10447 | F63: 王杰 | G63: 0 | I63: =G63+H63 -> 0 | J63: 综采队 | K63: 拉架工 | R63: 工人岗 | T63: 正式工 | U63: 42788 | V63: =IF(U63="","",ROUND(YEARFRAC(U63,TODAY(),1),1)) -> 9.4 | W63: 固定期限劳动合同 | X63: =IF(MOD(RIGHT(LEFT(AB63,17)),2),"男","女") -> 男 | Y63: 蒙古 | Z63: =MID(AB63,7,4)&"-"&MID(AB63,11,2)&"-"&MID(AB63,13,2) -> 1986-04-03 | AA63: 内蒙古赤峰市喀喇沁旗十家满族乡三道营子村八组 | AB63: 150428198604030110 | AC63: 喀喇沁旗公安局 | AD63: 51752 | AE63: =YEAR(TODAY())-MID(AB63,7,4) -> 40 | AF63: 群众 | AG63: 已婚 | AH63: 170 | AI63: C1 | AJ63: B | AK63: 13191375855 | AL63: 15104812320 | AM63: 中专 | AN63: 38898 | AO63: 楼子店联中 | AP63: - | AR63: 液压支架工（五级） | AV63: 42788 | AW63: 42846 | AX63: 劳动合同 | AY63: 力量煤业 | AZ63: 44652 | BA63: 45382 | BB63: 2 | BC63: √ | BD63: √ | BE63: √ | BF63: √ | BG63: 1 | BH63: 2 | BK63: √ | BM63: √ | BN63: √ | BR63: LM-02-02 | BS63: √ | CC63: √
A64: =IF(B64="","",ROW()-1) -> 63 | B64: =IF(AB64="","",AB64) -> 130521198510127015 | C64: 力量煤业 | D64: 直接生产人员 | E64: F11295 | F64: 陈肖铮 | I64: =G64+H64 -> 0 | J64: 综采队 | K64: 拉架工 | R64: 工人岗 | T64: 正式工 | U64: 44957 | V64: 0 | W64: 固定期限劳动合同 | X64: 男 | Y64: 汉 | Z64: 1985-10-12 | AA64: 河北省邢台市邢台县路罗镇社旮旯村 | AB64: 130521198510127015 | AC64: 邢台县公安局 | AD64: 51225 | AE64: 38 | AF64: 群众 | AG64: 已婚 | AH64: 175 | AI64: C1 | AJ64: A | AK64: 18931935281 | AL64: 15231949665 | AM64: 高中 | AN64: 38139 | AO64: 路罗镇中学 | AV64: 44957 | AW64: 45015 | AX64: 劳动合同 | AY64: 力量煤业 | AZ64: 44957 | BA64: 45382 | BB64: 2 | BC64: √ | BD64: √ | BE64: √ | BF64: √ | BG64: 0 | BH64: 0 | BK64: √ | BR64: LM-04-04 | BS64: √ | BT64: √ | BU64: √ | BV64: √ | BW64: √ | BX64: √ | CF64: 2022年
A65: =IF(B65="","",ROW()-1) -> 64 | B65: =IF(AB65="","",AB65) -> 511304198312232011 | C65: 力量煤业 | D65: 直接生产人员 | E65: F11513 | F65: 赵新春 | I65: =G65+H65 -> 0 | J65: 综采队 | K65: 拉架工 | R65: 工人岗 | T65: 正式工 | U65: 45030 | V65: =IF(U65="","",ROUND(YEARFRAC(U65,TODAY(),1),1)) -> 3.2 | W65: 固定期限劳动合同 | X65: =IF(MOD(RIGHT(LEFT(AB65,17)),2),"男","女") -> 男 | Y65: 汉 | Z65: =MID(AB65,7,4)&"-"&MID(AB65,11,2)&"-"&MID(AB65,13,2) -> 1983-12-23 | AA65: 四川省南充市嘉陵区金凤镇守塘湾村5组33号 | AB65: 511304198312232011 | AC65: 南充市公安局嘉陵分局 | AD65: 50207 | AE65: =YEAR(TODAY())-MID(AB65,7,4) -> 43 | AF65: 群众 | AG65: 已婚 | AH65: 171 | AJ65: B | AK65: 18875760907 | AL65: 18230196609 | AM65: 高中 | AN65: 2002年 | AO65: 四川普高 | AV65: 45030 | AW65: 45090 | AX65: 劳动合同 | AY65: 力量煤业 | AZ65: 45030 | BA65: 45473 | BB65: 2 | BC65: √ | BD65: √ | BE65: √ | BF65: √ | BG65: 0 | BH65: 0 | BK65: √ | BR65: LM-05-03 | BS65: √ | BT65: √ | BU65: √ | BV65: √ | BW65: √ | BX65: √ | BZ65: √ | CF65: 2023年
A66: =IF(B66="","",ROW()-1) -> 65 | B66: =IF(AB66="","",AB66) -> 610523198301139076 | C66: 力量煤业 | D66: 直接生产人员 | E66: F11515 | F66: 程永平 | I66: =G66+H66 -> 0 | J66: 综采队 | K66: 拉架工 | R66: 工人岗 | T66: 正式工 | U66: 45030 | V66: =IF(U66="","",ROUND(YEARFRAC(U66,TODAY(),1),1)) -> 3.2 | W66: 固定期限劳动合同 | X66: =IF(MOD(RIGHT(LEFT(AB66,17)),2),"男","女") -> 男 | Y66: 汉 | Z66: =MID(AB66,7,4)&"-"&MID(AB66,11,2)&"-"&MID(AB66,13,2) -> 1983-01-13 | AA66: 陕西省渭南市大荔县韦林镇迪东村一组120号 | AB66: 610523198301139076 | AC66: 大荔县公安局 | AD66: 50487 | AE66: =YEAR(TODAY())-MID(AB66,7,4) -> 43 | AF66: 群众 | AG66: 已婚 | AH66: 168 | AI66: B2 | AJ66: B | AK66: 13379448163 | AL66: 13325336190 | AM66: 中专 | AN66: 37803 | AO66: 陕西省大荔县官池镇电子专业学校 | AP66: 电子专业 | AV66: 45030 | AW66: 45090 | AX66: 劳动合同 | AY66: 力量煤业 | AZ66: 45030 | BA66: 45473 | BB66: 2 | BC66: √ | BD66: √ | BE66: √ | BF66: √ | BG66: 0 | BH66: 0 | BK66: √ | BR66: LM-05-03 | BS66: √ | BT66: √ | BU66: √ | BV66: √ | BW66: √ | BX66: √ | BZ66: √ | CF66: 2023年
A67: =IF(B67="","",ROW()-1) -> 66 | B67: =IF(AB67="","",AB67) -> 410125198012025519 | C67: 力量煤业 | D67: 直接生产人员 | E67: F11516 | F67: 范淑伟 | I67: =G67+H67 -> 0 | J67: 综采队 | K67: 拉架工 | R67: 工人岗 | T67: 正式工 | U67: 45030 | V67: =IF(U67="","",ROUND(YEARFRAC(U67,TODAY(),1),1)) -> 3.2 | W67: 固定期限劳动合同 | X67: =IF(MOD(RIGHT(LEFT(AB67,17)),2),"男","女") -> 男 | Y67: 汉 | Z67: =MID(AB67,7,4)&"-"&MID(AB67,11,2)&"-"&MID(AB67,13,2) -> 1980-12-02 | AA67: 河南省登封市石道乡东范爻村４５号 | AB67: 410125198012025519 | AC67: 登封市公安局 | AD67: 49076 | AE67: =YEAR(TODAY())-MID(AB67,7,4) -> 46 | AF67: 群众 | AG67: 已婚 | AH67: 180 | AI67: C1 | AJ67: B | AK67: 13203818678 | AL67: 19139962818 | AM67: 高中 | AN67: 1997年 | AO67: 登封五中 | AV67: 45030 | AW67: 45090 | AX67: 劳动合同 | AY67: 力量煤业 | AZ67: 45030 | BA67: 45473 | BB67: 2 | BC67: √ | BD67: √ | BE67: √ | BF67: √ | BG67: 0 | BH67: 0 | BK67: √ | BR67: LM-05-03 | BS67: √ | BT67: √ | BU67: √ | BV67: √ | BW67: √ | BX67: √ | BZ67: √ | CF67: 2023年
A68: =IF(B68="","",ROW()-1) -> 67 | B68: =IF(AB68="","",AB68) -> 371326198207072417 | C68: 力量煤业 | D68: 直接生产人员 | E68: F11622 | F68: 郭澍林 | I68: =G68+H68 -> 0 | J68: 综采队 | K68: 支架工 | R68: 工人岗 | T68: 正式工 | U68: 45089 | V68: =IF(U68="","",ROUND(YEARFRAC(U68,TODAY(),1),1)) -> 3.1 | W68: 固定期限劳动合同 | X68: =IF(MOD(RIGHT(LEFT(AB68,17)),2),"男","女") -> 男 | Y68: 汉 | Z68: =MID(AB68,7,4)&"-"&MID(AB68,11,2)&"-"&MID(AB68,13,2) -> 1982-07-07 | AA68: 山东省邹城市太平路1018号1号楼2单元602室 | AB68: 371326198207072417 | AC68: 邹城市公安局 | AD68: 52148 | AE68: =YEAR(TODAY())-MID(AB68,7,4) -> 44 | AF68: 群众 | AG68: 已婚 | AH68: 183 | AJ68: B | AK68: 13156101856 | AL68: 17115158999 | AM68: 中专 | AN68: 2009年 | AO68: 山东煤炭高级技工学校 | AP68: 采掘 | AV68: 45089 | AW68: 45149 | AX68: 劳动合同 | AY68: 力量煤业 | AZ68: 45089 | BA68: 45473 | BB68: 2 | BC68: √ | BD68: √ | BE68: √ | BF68: √ | BG68: 0 | BH68: 0 | BK68: √ | BR68: LM-05-05 | BS68: √ | BT68: √ | BU68: √ | BV68: √ | BW68: √ | BX68: √ | CF68: 2023年
A69: =IF(B69="","",ROW()-1) -> 68 | B69: =IF(AB69="","",AB69) -> 370811198202114018 | C69: 力量煤业 | D69: 直接生产人员 | E69: F11623 | F69: 张德利 | I69: =G69+H69 -> 0 | J69: 综采队 | K69: 拉架工 | R69: 工人岗 | T69: 正式工 | U69: 45089 | V69: =IF(U69="","",ROUND(YEARFRAC(U69,TODAY(),1),1)) -> 3.1 | W69: 固定期限劳动合同 | X69: =IF(MOD(RIGHT(LEFT(AB69,17)),2),"男","女") -> 男 | Y69: 汉 | Z69: =MID(AB69,7,4)&"-"&MID(AB69,11,2)&"-"&MID(AB69,13,2) -> 1982-02-11 | AA69: 山东省济宁市任城区唐口街道办事处张寨村第2巷09号 | AB69: 370811198202114018 | AC69: 济宁市公安局市中分局 | AD69: 51233 | AE69: =YEAR(TODAY())-MID(AB69,7,4) -> 44 | AF69: 党员 | AG69: 已婚 | AH69: 172 | AJ69: O | AK69: 15244049277 | AL69: 15169702521 | AM69: 大专 | AN69: 42248 | AO69: 山东科技大学 | AP69: 煤矿开采技术 | AV69: 45089 | AW69: 45149 | AX69: 劳动合同 | AY69: 力量煤业 | AZ69: 45089 | BA69: 45473 | BB69: 2 | BC69: √ | BD69: √ | BE69: √ | BF69: √ | BG69: 0 | BH69: 0 | BK69: √ | BR69: LM-05-05 | BS69: √ | BT69: √ | BU69: √ | BV69: √ | BW69: √ | BX69: √ | CF69: 2023年
A70: =IF(B70="","",ROW()-1) -> 69 | B70: =IF(AB70="","",AB70) -> 370883199008144850 | C70: 力量煤业 | D70: 直接生产人员 | E70: F11624 | F70: 王玉法 | I70: =G70+H70 -> 0 | J70: 综采队 | K70: 支护工 | R70: 工人岗 | T70: 正式工 | U70: 45089 | V70: =IF(U70="","",ROUND(YEARFRAC(U70,TODAY(),1),1)) -> 3.1 | W70: 固定期限劳动合同 | X70: =IF(MOD(RIGHT(LEFT(AB70,17)),2),"男","女") -> 男 | Y70: 汉 | Z70: =MID(AB70,7,4)&"-"&MID(AB70,11,2)&"-"&MID(AB70,13,2) -> 1990-08-14 | AA70: 山东省邹城市北宿镇东贾村387号 | AB70: 370883199008144850 | AC70: 邹城市公安局 | AD70: 51554 | AE70: =YEAR(TODAY())-MID(AB70,7,4) -> 36 | AF70: 群众 | AG70: 已婚 | AH70: 173 | AJ70: AB | AK70: 13583738685 | AL70: 15965737765 | AM70: 中专 | AN70: 2016年 | AO70: 兖矿技校 | AP70: 支护 | AV70: 45089 | AW70: 45149 | AX70: 劳动合同 | AY70: 力量煤业 | AZ70: 45089 | BA70: 45473 | BB70: 2 | BC70: √ | BD70: √ | BE70: √ | BF70: √ | BG70: 0 | BH70: 0 | BK70: √ | BR70: LM-05-05 | BS70: √ | BT70: √ | BU70: √ | BV70: √ | BW70: √ | BX70: √ | CF70: 2023年
A71: =IF(B71="","",ROW()-1) -> 70 | B71: =IF(AB71="","",AB71) -> 152104198709182836 | C71: 力量煤业 | D71: 直接生产人员 | E71: F11625 | F71: 宋欣雨 | I71: =G71+H71 -> 0 | J71: 综采队 | K71: 支护工 | R71: 工人岗 | T71: 正式工 | U71: 45089 | V71: =IF(U71="","",ROUND(YEARFRAC(U71,TODAY(),1),1)) -> 3.1 | W71: 固定期限劳动合同 | X71: =IF(MOD(RIGHT(LEFT(AB71,17)),2),"男","女") -> 男 | Y71: 汉 | Z71: =MID(AB71,7,4)&"-"&MID(AB71,11,2)&"-"&MID(AB71,13,2) -> 1987-09-18 | AA71: 内蒙古牙克石市博克图镇西沟路东52号 | AB71: 152104198709182836 | AC71: 牙克石市公安局 | AD71: 49911 | AE71: =YEAR(TODAY())-MID(AB71,7,4) -> 39 | AF71: 群众 | AG71: 已婚 | AH71: 172 | AJ71: B | AK71: 15598822108 | AL71: 15947731334 | AM71: 高中 | AN71: 2003年 | AO71: 内蒙古牙克石市第二中学 | AV71: 45089 | AW71: 45149 | AX71: 劳动合同 | AY71: 力量煤业 | AZ71: 45089 | BA71: 45473 | BB71: 2 | BC71: √ | BD71: √ | BE71: √ | BF71: √ | BG71: 0 | BH71: 0 | BK71: √ | BR71: LM-05-05 | BS71: √ | BT71: √ | BU71: √ | BV71: √ | BW71: √ | BX71: √ | CF71: 2023年
A72: =IF(B72="","",ROW()-1) -> 71 | B72: =IF(AB72="","",AB72) -> 152224198902162539 | C72: 力量煤业 | D72: 直接生产人员 | E72: F10588 | F72: 张青微 | G72: 0 | H72: 0 | I72: =G72+H72 -> 0 | J72: 综采队 | K72: 煤机司机 | R72: 工人岗 | T72: 正式工 | U72: 43388 | V72: =IF(U72="","",ROUND(YEARFRAC(U72,TODAY(),1),1)) -> 7.7 | W72: 固定期限劳动合同 | X72: =IF(MOD(RIGHT(LEFT(AB72,17)),2),"男","女") -> 男 | Y72: 蒙古 | Z72: =MID(AB72,7,4)&"-"&MID(AB72,11,2)&"-"&MID(AB72,13,2) -> 1989-02-16 | AA72: 内蒙古兴安盟突泉县溪柳乡平原村029号 | AB72: 152224198902162539 | AC72: 突泉县公安局 | AD72: 51009 | AE72: =YEAR(TODAY())-MID(AB72,7,4) -> 37 | AF72: 群众 | AG72: 已婚 | AH72: 180 | AI72: C1 | AJ72: B | AK72: 15049485361 | AL72: 15248555273 | AM72: 中专 | AN72: 44378 | AO72: 国家开放大学 | AP72: 机电一体化技术 | AT72: 初级工 | AV72: 43388 | AW72: 43448 | AX72: 劳动合同 | AY72: 力量煤业 | AZ72: 44562 | BA72: 45291 | BB72: 2 | BC72: √ | BD72: √ | BE72: √ | BF72: √ | BG72: 1 | BH72: 2 | BK72: √ | BN72: √ | BR72: LM-02-04 | BS72: √ | BT72: √ | BV72: √ | BW72: √ | CB72: √ | CC72: √
A73: =IF(B73="","",ROW()-1) -> 72 | B73: =IF(AB73="","",AB73) -> 612729199301233316 | C73: 力量煤业 | D73: 直接生产人员 | E73: P10468 | F73: 徐波波 | G73: 0 | H73: 0 | I73: =G73+H73 -> 0 | J73: 综采队 | K73: 清煤工 | R73: 工人岗 | T73: 正式工 | U73: 42863 | V73: =IF(U73="","",ROUND(YEARFRAC(U73,TODAY(),1),1)) -> 9.2 | W73: 固定期限劳动合同 | X73: =IF(MOD(RIGHT(LEFT(AB73,17)),2),"男","女") -> 男 | Y73: 汉 | Z73: =MID(AB73,7,4)&"-"&MID(AB73,11,2)&"-"&MID(AB73,13,2) -> 1993-01-23 | AA73: 陕西省佳县上高家寨乡徐家峁上村37号 | AB73: 612729199301233316 | AC73: 佳县公安局 | AD73: 45234 | AE73: =YEAR(TODAY())-MID(AB73,7,4) -> 33 | AF73: 共青团员 | AG73: 已婚 | AH73: 178 | AI73: C1 | AJ73: O | AK73: 15647767656 | AL73: 15547735670 | AM73: 中专 | AN73: 40725 | AO73: 陕西职业技术学院西北工业学校 | AP73: 化工机械 | AR73: 化工检修钳工 | AV73: 42863 | AW73: 42923 | AX73: 劳动合同 | AY73: 力量煤业 | AZ73: 44743 | BA73: 45473 | BB73: 2 | BC73: √ | BD73: √ | BE73: √ | BF73: √ | BG73: 1 | BH73: 2 | BM73: √ | BN73: √ | BR73: LM-02-02 | BS73: √ | BT73: √ | BW73: √ | CC73: √ | CF73: 2017年
A74: =IF(B74="","",ROW()-1) -> 73 | B74: =IF(AB74="","",AB74) -> 140511198006113131 | C74: 力量煤业 | D74: 直接生产人员 | E74: F10276 | F74: 崔建军 | G74: 0 | H74: 0 | I74: =G74+H74 -> 0 | J74: 综采队 | K74: 乳化泵检修工 | R74: 工人岗 | T74: 正式工 | U74: 41339 | V74: =IF(U74="","",ROUND(YEARFRAC(U74,TODAY(),1),1)) -> 13.3 | W74: 固定期限劳动合同 | X74: =IF(MOD(RIGHT(LEFT(AB74,17)),2),"男","女") -> 男 | Y74: 汉 | Z74: =MID(AB74,7,4)&"-"&MID(AB74,11,2)&"-"&MID(AB74,13,2) -> 1980-06-11 | AA74: 山西省泽州县高都镇泊村北庙街4号 | AB74: 140511198006113131 | AC74: 泽州县公安局 | AD74: 46538 | AE74: =YEAR(TODAY())-MID(AB74,7,4) -> 46 | AF74: 群众 | AG74: 已婚 | AH74: 174 | AI74: C1 | AJ74: O | AK74: 15047747248 | AL74: 18035610139 | AM74: 中专 | AN74: 44012 | AO74: 中央广播电视中等专业学校 | AP74: 机电一体化 | AR74: 胶带/转载机操作工（五级） | AT74: 初级工 | AV74: 41339 | AW74: 41400 | AX74: 劳动合同 | AY74: 力量煤业 | AZ74: 44743 | BA74: 45473 | BB74: 2 | BC74: √ | BD74: √ | BE74: √ | BF74: √ | BG74: 2 | BH74: 4 | BK74: √ | BM74: √ | BN74: √ | BR74: LM-01-03 | BS74: √ | BT74: √ | BZ74: √ | CC74: √ | CG74: 特种作业操作证
A75: =IF(B75="","",ROW()-1) -> 74 | B75: =IF(AB75="","",AB75) -> 150428198606072058 | C75: 力量煤业 | D75: 直接生产人员 | E75: F10539 | F75: 韩顺 | G75: 0 | H75: 0 | I75: =G75+H75 -> 0 | J75: 综采队 | K75: 乳化泵检修工 | R75: 工人岗 | T75: 正式工 | U75: 43181 | V75: =IF(U75="","",ROUND(YEARFRAC(U75,TODAY(),1),1)) -> 8.3 | W75: 固定期限劳动合同 | X75: =IF(MOD(RIGHT(LEFT(AB75,17)),2),"男","女") -> 男 | Y75: 蒙古 | Z75: =MID(AB75,7,4)&"-"&MID(AB75,11,2)&"-"&MID(AB75,13,2) -> 1986-06-07 | AA75: 内蒙古赤峰市喀喇沁旗西桥镇西桥村一组 | AB75: 150428198606072058 | AC75: 赤峰市公安局 | AD75: 49979 | AE75: =YEAR(TODAY())-MID(AB75,7,4) -> 40 | AF75: 群众 | AG75: 已婚 | AH75: 165 | AI75: C1 | AJ75: B | AK75: 13734850386 | AL75: 18747683785 | AM75: 中专 | AN75: 44012 | AO75: 中央广播电视中等专业学校 | AP75: 采矿技术 | AT75: 初级工 | AV75: 43179 | AW75: 43240 | AX75: 劳动合同 | AY75: 力量煤业 | AZ75: 44287 | BA75: 45747 | BB75: 2 | BC75: √ | BD75: √ | BE75: √ | BF75: √ | BG75: 1 | BH75: 2 | BK75: √ | BN75: √ | BR75: LM-02-03 | BS75: √ | BT75: √ | BW75: √ | CC75: √
A76: =IF(B76="","",ROW()-1) -> 75 | B76: =IF(AB76="","",AB76) -> 142703196904292411 | C76: 力量煤业 | D76: 直接生产人员 | E76: F10260 | F76: 张立民 | G76: 0 | H76: 0 | I76: =G76+H76 -> 0 | J76: 综采队 | K76: 三机检修工 | R76: 工人岗 | T76: 正式工 | U76: 41331 | V76: =IF(U76="","",ROUND(YEARFRAC(U76,TODAY(),1),1)) -> 13.4 | W76: 固定期限劳动合同 | X76: =IF(MOD(RIGHT(LEFT(AB76,17)),2),"男","女") -> 男 | Y76: 汉 | Z76: =MID(AB76,7,4)&"-"&MID(AB76,11,2)&"-"&MID(AB76,13,2) -> 1969-04-29 | AA76: 山西省河津市城区办事处修村 | AB76: 142703196904292411 | AC76: 河津市公安局 | AD76: 46180 | AE76: =YEAR(TODAY())-MID(AB76,7,4) -> 57 | AF76: 群众 | AG76: 已婚 | AH76: 168 | AI76: - | AJ76: O | AK76: 15804818356 | AL76: 13294679311 | AM76: 高中 | AN76: 31656 | AO76: 河津中学 | AP76: - | AV76: 41451 | AW76: 41390 | AX76: 劳动合同 | AY76: 力量煤业 | AZ76: 44743 | BA76: 45411 | BB76: 2 | BC76: √ | BD76: √ | BE76: √ | BF76: √ | BG76: 2 | BH76: 4 | BK76: √ | BN76: √ | BR76: LM-01-03 | BS76: √ | BT76: √ | BZ76: √ | CC76: √ | CG76: 高中毕业证
A77: =IF(B77="","",ROW()-1) -> 76 | B77: =IF(AB77="","",AB77) -> 370922197101062474 | C77: 力量煤业 | D77: 直接生产人员 | E77: F10269 | F77: 丁庆荣 | G77: 0 | H77: 0 | I77: =G77+H77 -> 0 | J77: 综采队 | K77: 三机检修工 | R77: 工人岗 | T77: 正式工 | U77: 41338 | V77: =IF(U77="","",ROUND(YEARFRAC(U77,TODAY(),1),1)) -> 13.3 | W77: 固定期限劳动合同 | X77: =IF(MOD(RIGHT(LEFT(AB77,17)),2),"男","女") -> 男 | Y77: 汉 | Z77: =MID(AB77,7,4)&"-"&MID(AB77,11,2)&"-"&MID(AB77,13,2) -> 1971-01-06 | AA77: 山东省肥城市石横镇道口村251号 | AB77: 370922197101062474 | AC77: 肥城市公安局 | AD77: 46333 | AE77: =YEAR(TODAY())-MID(AB77,7,4) -> 55 | AF77: 群众 | AG77: 已婚 | AH77: 170 | AI77: - | AJ77: - | AK77: 15147530669 | AL77: 15552804544 | AM77: 高中 | AN77: 33055 | AO77: 肥城市第五中学 | AP77: - | AR77: 胶带/转载机操作工（五级） | AT77: 中级工 | AV77: 41338 | AW77: 41399 | AX77: 劳动合同 | AY77: 力量煤业 | AZ77: 44743 | BA77: 45473 | BB77: 2 | BC77: √ | BD77: √ | BE77: √ | BF77: √ | BG77: 2 | BH77: 4 | BK77: √ | BM77: √ | BN77: √ | BR77: LM-01-03 | BS77: √ | BT77: √ | CA77: √ | CC77: √ | CG77: 高中毕业证
A78: =IF(B78="","",ROW()-1) -> 77 | B78: =IF(AB78="","",AB78) -> 370983197601161834 | C78: 力量煤业 | D78: 直接生产人员 | E78: F10270 | F78: 朱绪经 | G78: 0 | H78: 0 | I78: =G78+H78 -> 0 | J78: 综采队 | K78: 三机检修工 | R78: 工人岗 | T78: 正式工 | U78: 41338 | V78: =IF(U78="","",ROUND(YEARFRAC(U78,TODAY(),1),1)) -> 13.3 | W78: 固定期限劳动合同 | X78: =IF(MOD(RIGHT(LEFT(AB78,17)),2),"男","女") -> 男 | Y78: 汉 | Z78: =MID(AB78,7,4)&"-"&MID(AB78,11,2)&"-"&MID(AB78,13,2) -> 1976-01-16 | AA78: 山东省肥城市湖屯镇西湖西村152号 | AB78: 370983197601161834 | AC78: 肥城市公安局 | AD78: 46189 | AE78: =YEAR(TODAY())-MID(AB78,7,4) -> 50 | AF78: 群众 | AG78: 已婚 | AH78: 169 | AI78: C1 | AJ78: O | AK78: 15044736579 | AL78: 15615386026 | AM78: 高中 | AN78: 34516 | AO78: 肥城五中 | AP78: - | AR78: 胶带/转载机操作工（五级） | AT78: 初级工 | AV78: 41338 | AW78: 41399 | AX78: 劳动合同 | AY78: 力量煤业 | AZ78: 44743 | BA78: 45473 | BB78: 2 | BC78: √ | BD78: √ | BE78: √ | BF78: √ | BG78: 2 | BH78: 4 | BK78: √ | BM78: √ | BN78: √ | BR78: LM-01-03 | BS78: √ | BT78: √ | CC78: √ | CG78: 高中毕业证
A79: =IF(B79="","",ROW()-1) -> 78 | B79: =IF(AB79="","",AB79) -> 370826197409153719 | C79: 力量煤业 | D79: 直接生产人员 | E79: F10291 | F79: 欧广季 | G79: 0 | H79: 0 | I79: =G79+H79 -> 0 | J79: 综采队 | K79: 三机检修工 | R79: 工人岗 | T79: 正式工 | U79: 41363 | V79: =IF(U79="","",ROUND(YEARFRAC(U79,TODAY(),1),1)) -> 13.3 | W79: 固定期限劳动合同 | X79: =IF(MOD(RIGHT(LEFT(AB79,17)),2),"男","女") -> 男 | Y79: 汉 | Z79: =MID(AB79,7,4)&"-"&MID(AB79,11,2)&"-"&MID(AB79,13,2) -> 1974-09-15 | AA79: 山东省微山县张楼乡陶官屯村平安路004号 | AB79: 370826197409153719 | AC79: 微山县公安局 | AD79: 45907 | AE79: =YEAR(TODAY())-MID(AB79,7,4) -> 52 | AF79: 群众 | AG79: 已婚 | AH79: 170 | AI79: - | AJ79: - | AK79: 15588796782 | AL79: 13615473818 | AM79: 高中 | AN79: 34151 | AO79: 微山县第一中学 | AP79: - | AR79: 胶带/转载机操作工（五级） | AT79: 初级工 | AV79: 41363 | AW79: 41424 | AX79: 劳动合同 | AY79: 力量煤业 | AZ79: 44743 | BA79: 45473 | BB79: 2 | BC79: √ | BD79: √ | BE79: √ | BF79: √ | BG79: 2 | BH79: 4 | BK79: √ | BM79: √ | BN79: √ | BR79: LM-01-03 | BS79: √ | BT79: √ | CC79: √ | CG79: 高中毕业证
A80: =IF(B80="","",ROW()-1) -> 79 | B80: =IF(AB80="","",AB80) -> 130926197012100812 | C80: 力量煤业 | D80: 直接生产人员 | E80: F10329 | F80: 王东京 | G80: 0 | H80: 0 | I80: =G80+H80 -> 0 | J80: 综采队 | K80: 三机检修工 | R80: 工人岗 | T80: 正式工 | U80: 41621 | V80: =IF(U80="","",ROUND(YEARFRAC(U80,TODAY(),1),1)) -> 12.6 | W80: 固定期限劳动合同 | X80: =IF(MOD(RIGHT(LEFT(AB80,17)),2),"男","女") -> 男 | Y80: 汉 | Z80: =MID(AB80,7,4)&"-"&MID(AB80,11,2)&"-"&MID(AB80,13,2) -> 1970-12-10 | AA80: 河北省沧州市肃宁县窝北镇顶汪村257号 | AB80: 130926197012100812 | AC80: 肃宁县公安局 | AD80: 47073 | AE80: =YEAR(TODAY())-MID(AB80,7,4) -> 56 | AF80: 群众 | AG80: 已婚 | AH80: 185 | AI80: - | AJ80: - | AK80: 15833365409 | AL80: 18730738153 | AM80: 高中 | AN80: 32690 | AO80: 肃宁县梁村一中 | AP80: - | AT80: 初级工 | AV80: 41621 | AW80: 41683 | AX80: 劳动合同 | AY80: 力量煤业 | AZ80: 44287 | BA80: 45747 | BB80: 2 | BC80: √ | BD80: √ | BE80: √ | BF80: √ | BG80: 2 | BH80: 4 | BK80: √ | BN80: √ | BR80: LM-01-04 | BS80: √ | BT80: √ | CC80: √ | CG80: 村委会无犯罪证明
A81: =IF(B81="","",ROW()-1) -> 80 | B81: =IF(AB81="","",AB81) -> 130521197410067014 | C81: 力量煤业 | D81: 直接生产人员 | E81: F10363 | F81: 王建兵 | G81: 0 | H81: 0 | I81: =G81+H81 -> 0 | J81: 综采队 | K81: 三机检修工 | R81: 工人岗 | T81: 正式工 | U81: 41981 | V81: =IF(U81="","",ROUND(YEARFRAC(U81,TODAY(),1),1)) -> 11.6 | W81: 固定期限劳动合同 | X81: =IF(MOD(RIGHT(LEFT(AB81,17)),2),"男","女") -> 男 | Y81: 汉 | Z81: =MID(AB81,7,4)&"-"&MID(AB81,11,2)&"-"&MID(AB81,13,2) -> 1974-10-06 | AA81: 河北省邢台市桥西区中兴路214号集体户 | AB81: 130521197410067014 | AC81: 邢台市公安局桥西分局 | AD81: 46651 | AE81: =YEAR(TODAY())-MID(AB81,7,4) -> 52 | AF81: 群众 | AG81: 已婚 | AH81: 185 | AI81: - | AJ81: - | AK81: 18686230228 | AL81: 15132904271 | AM81: 中专 | AN81: 35125 | AO81: 河北省邢台市职业教育中心 | AP81: 微机 | AV81: 41981 | AW81: 42043 | AX81: 劳动合同 | AY81: 力量煤业 | AZ81: 44562 | BA81: 45291 | BB81: 2 | BC81: √ | BD81: √ | BE81: √ | BF81: √ | BG81: 2 | BH81: 4 | BK81: √ | BN81: √ | BR81: LM-01-04 | BS81: √ | BT81: √ | CC81: √ | CG81: 村委会无犯罪证明/特种作业操作证
A82: =IF(B82="","",ROW()-1) -> 81 | B82: =IF(AB82="","",AB82) -> 15212819940323095X | C82: 力量煤业 | D82: 直接生产人员 | E82: F11346 | F82: 单斌 | I82: =G82+H82 -> 0 | J82: 综采队 | K82: 三机检修工 | R82: 工人岗 | T82: 正式工 | U82: 44965 | V82: 0 | W82: 固定期限劳动合同 | X82: 男 | Y82: 汉 | Z82: 1994-03-23 | AA82: 内蒙古呼伦贝尔市鄂温克族自治旗大雁镇雁煤新村北小区30栋2单元503号 | AB82: 15212819940323095X | AC82: 鄂温克族自治旗公安局 | AD82: 51435 | AE82: 29 | AF82: 群众 | AG82: 已婚 | AH82: 171 | AI82: C1 | AJ82: B | AK82: 18548035191 | AL82: 15582007776 | AM82: 中专 | AO82: 呼伦贝尔技术学院 | AP82: 药剂 | AV82: 44965 | AW82: 45023 | AX82: 劳动合同 | AY82: 力量煤业 | AZ82: 44965 | BA82: 45382 | BB82: 2 | BC82: √ | BD82: √ | BE82: √ | BF82: √ | BG82: 0 | BH82: 0 | BK82: √ | BR82: LM-04-04 | BS82: √ | BT82: √ | BU82: √ | BV82: √ | BW82: √ | BX82: √ | CF82: 2023年
A83: =IF(B83="","",ROW()-1) -> 82 | B83: =IF(AB83="","",AB83) -> 130521199009157012 | C83: 力量煤业 | D83: 直接生产人员 | E83: F11432 | F83: 赵瑞青 | I83: =G83+H83 -> 0 | J83: 综采队 | K83: 三机检修工 | R83: 工人岗 | T83: 正式工 | U83: 44995 | V83: 0 | W83: 固定期限劳动合同 | X83: 男 | Y83: 汉 | Z83: 1990-09-15 | AA83: 河北省邢台市邢台县路罗镇桃树坪村070号 | AB83: 130521199009157012 | AC83: 邢台县公安局 | AD83: 51395 | AE83: 33 | AF83: 群众 | AG83: 已婚 | AH83: 173 | AJ83: AB | AK83: 13833918303 | AL83: 15227605286 | AM83: 高中 | AN83: 2006年 | AO83: 路罗中学 | AV83: 44995 | AW83: 45055 | AX83: 劳动合同 | AY83: 力量煤业 | AZ83: 44995 | BA83: 45382 | BB83: 2 | BC83: √ | BD83: √ | BE83: √ | BF83: √ | BG83: 0 | BH83: 0 | BK83: √ | BR83: LM-05-01 | BS83: √ | BT83: √ | BU83: √ | BV83: √ | BW83: √ | BX83: √ | CF83: 2023年
A84: =IF(B84="","",ROW()-1) -> 83 | B84: =IF(AB84="","",AB84) -> 14022619780218003X | C84: 力量煤业 | D84: 直接生产人员 | E84: F11438 | F84: 邓培元 | I84: =G84+H84 -> 0 | J84: 综采队 | K84: 三机检修工 | R84: 工人岗 | T84: 正式工 | U84: 44998 | V84: 0 | W84: 固定期限劳动合同 | X84: 男 | Y84: 满 | Z84: 1978-02-18 | AA84: 山西省左云县管家堡乡平川村255号 | AB84: 14022619780218003X | AC84: 左云县公安局 | AD84: 46318 | AE84: 45 | AF84: 群众 | AG84: 已婚 | AH84: 170 | AJ84: B | AK84: 13947775261 | AL84: 18347756297 | AM84: 高中 | AN84: 1995年 | AO84: 左云县第一中学 | AV84: 44998 | AW84: 45058 | AX84: 劳动合同 | AY84: 力量煤业 | AZ84: 44998 | BA84: 45382 | BB84: 2 | BC84: √ | BD84: √ | BE84: √ | BF84: √ | BG84: 0 | BH84: 0 | BK84: √ | BR84: LM-05-01 | BS84: √ | BT84: √ | BU84: √ | BV84: √ | BW84: √ | BX84: √ | BZ84: √ | CF84: 2023年
A85: =IF(B85="","",ROW()-1) -> 84 | B85: =IF(AB85="","",AB85) -> 150426197906270315 | C85: 力量煤业 | D85: 直接生产人员 | E85: F11463 | F85: 刘伟东 | I85: =G85+H85 -> 0 | J85: 综采队 | K85: 三级检修工 | R85: 工人岗 | T85: 正式工 | U85: 45008 | V85: =IF(U85="","",ROUND(YEARFRAC(U85,TODAY(),1),1)) -> 3.3 | W85: 固定期限劳动合同 | X85: =IF(MOD(RIGHT(LEFT(AB85,17)),2),"男","女") -> 男 | Y85: 汉 | Z85: =MID(AB85,7,4)&"-"&MID(AB85,11,2)&"-"&MID(AB85,13,2) -> 1979-06-27 | AA85: 内蒙古赤峰市翁牛特旗乌敦套海镇新府村一组 | AB85: 150426197906270315 | AC85: 翁牛特旗公安局 | AD85: 50140 | AE85: =YEAR(TODAY())-MID(AB85,7,4) -> 47 | AF85: 群众 | AG85: 已婚 | AH85: 172 | AI85: C1 | AJ85: O | AK85: 17308443170 | AL85: 18204873170 | AM85: 高中 | AN85: 1986年 | AO85: 内蒙古自治区赤峰市平煤高中 | AV85: 45008 | AW85: 45068 | AX85: 劳动合同 | AY85: 力量煤业 | AZ85: 45008 | BA85: 45382 | BB85: 2 | BC85: √ | BD85: √ | BE85: √ | BF85: √ | BG85: 0 | BH85: 0 | BK85: √ | BR85: LM-05-01 | BS85: √ | BT85: √ | BU85: √ | BV85: √ | BW85: √ | BX85: √ | CF85: 2023年
A86: =IF(B86="","",ROW()-1) -> 85 | B86: =IF(AB86="","",AB86) -> 410185198208283516 | C86: 力量煤业 | D86: 直接生产人员 | E86: F11544 | F86: 王国标 | I86: =G86+H86 -> 0 | J86: 综采队 | K86: 三级检修工 | R86: 工人岗 | T86: 正式工 | U86: 45044 | V86: =IF(U86="","",ROUND(YEARFRAC(U86,TODAY(),1),1)) -> 3.2 | W86: 固定期限劳动合同 | X86: =IF(MOD(RIGHT(LEFT(AB86,17)),2),"男","女") -> 男 | Y86: 汉 | Z86: =MID(AB86,7,4)&"-"&MID(AB86,11,2)&"-"&MID(AB86,13,2) -> 1982-08-28 | AA86: 河南省登封市东华镇马塞沟村１７号 | AB86: 410185198208283516 | AC86: 登封市公安局 | AD86: 49681 | AE86: =YEAR(TODAY())-MID(AB86,7,4) -> 44 | AF86: 群众 | AG86: 已婚 | AH86: 176 | AK86: 18530001982 | AL86: 13838030121 | AM86: 高中 | AN86: 36708 | AO86: 登封市试验高中 | AV86: 45044 | AW86: 45104 | AX86: 劳动合同 | AY86: 力量煤业 | AZ86: 45044 | BA86: 45473 | BB86: 2 | BC86: √ | BD86: √ | BE86: √ | BF86: √ | BG86: 0 | BH86: 0 | BK86: √ | BR86: LM-05-03 | BS86: √ | BT86: √ | BU86: √ | BV86: √ | BW86: √ | BX86: √ | BZ86: √ | CF86: 2023年
A87: =IF(B87="","",ROW()-1) -> 86 | B87: =IF(AB87="","",AB87) -> 130523198209231211 | C87: 力量煤业 | D87: 直接生产人员 | E87: F10529 | F87: 陈立东 | G87: 0 | H87: 0 | I87: =G87+H87 -> 0 | J87: 综采队 | K87: 三机检修工 | R87: 工人岗 | T87: 正式工 | U87: 43165 | V87: =IF(U87="","",ROUND(YEARFRAC(U87,TODAY(),1),1)) -> 8.3 | W87: 固定期限劳动合同 | X87: =IF(MOD(RIGHT(LEFT(AB87,17)),2),"男","女") -> 男 | Y87: 汉 | Z87: =MID(AB87,7,4)&"-"&MID(AB87,11,2)&"-"&MID(AB87,13,2) -> 1982-09-23 | AA87: 河北省邢台市内丘县大孟村镇胡里村114号 | AB87: 130523198209231211 | AC87: 内丘县公安局 | AD87: 47194 | AE87: =YEAR(TODAY())-MID(AB87,7,4) -> 44 | AF87: 群众 | AG87: 已婚 | AH87: 170 | AI87: C1 | AJ87: B | AK87: 13015177693 | AL87: 18731960271 | AM87: 中专 | AN87: 44256 | AO87: 中央广播电视中等专业学校 | AP87: 机电技术应用 | AR87: 胶带/转载机操作工（五级） | AT87: 中级工 | AV87: 43165 | AW87: 43225 | AX87: 劳动合同 | AY87: 力量煤业 | AZ87: 44287 | BA87: 45747 | BB87: 2 | BC87: √ | BD87: √ | BE87: √ | BF87: √ | BG87: 1 | BH87: 2 | BK87: √ | BM87: √ | BN87: √ | BR87: LM-02-03 | BS87: √ | BT87: √ | BW87: √ | CC87: √
A88: =IF(B88="","",ROW()-1) -> 87 | B88: =IF(AB88="","",AB88) -> 15210419790211227X | C88: 力量煤业 | D88: 直接生产人员 | E88: F11599 | F88: 周超 | I88: =G88+H88 -> 0 | J88: 综采队 | K88: 设备检修工 | R88: 工人岗 | T88: 正式工 | U88: 45078 | V88: =IF(U88="","",ROUND(YEARFRAC(U88,TODAY(),1),1)) -> 3.1 | W88: 固定期限劳动合同 | X88: =IF(MOD(RIGHT(LEFT(AB88,17)),2),"男","女") -> 男 | Y88: 汉 | Z88: =MID(AB88,7,4)&"-"&MID(AB88,11,2)&"-"&MID(AB88,13,2) -> 1979-02-11 | AA88: 内蒙古牙克石市胜利西街阳光小区9号楼6单元601号 | AB88: 15210419790211227X | AC88: 牙克石市公安局 | AD88: 50449 | AE88: =YEAR(TODAY())-MID(AB88,7,4) -> 47 | AF88: 群众 | AG88: 已婚 | AH88: 174 | AI88: C1 | AJ88: B | AK88: 15147093757 | AL88: 15048038855 | AM88: 本科 | AN88: 42156 | AO88: 黑龙江科技大学 | AP88: 采矿工程 | AV88: 45078 | AW88: 45138 | AX88: 劳动合同 | AY88: 力量煤业 | AZ88: 45078 | BA88: 45473 | BB88: 2 | BC88: √ | BD88: √ | BE88: √ | BF88: √ | BG88: 0 | BH88: 0 | BK88: √ | BR88: LM-05-04 | BS88: √ | BT88: √ | BU88: √ | BV88: √ | BW88: √ | BX88: √ | CF88: 2023年
A89: =IF(B89="","",ROW()-1) -> 88 | B89: =IF(AB89="","",AB89) -> 220402197603045636 | C89: 力量煤业 | D89: 直接生产人员 | E89: F11660 | F89: 白永成 | I89: =G89+H89 -> 0 | J89: 综采队 | K89: 检修工 | R89: 工人岗 | T89: 正式工 | U89: 45105 | V89: =IF(U89="","",ROUND(YEARFRAC(U89,TODAY(),1),1)) -> 3 | W89: 固定期限劳动合同 | X89: =IF(MOD(RIGHT(LEFT(AB89,17)),2),"男","女") -> 男 | Y89: 汉 | Z89: =MID(AB89,7,4)&"-"&MID(AB89,11,2)&"-"&MID(AB89,13,2) -> 1976-03-04 | AA89: 吉林省辽源市龙山区工农乡红五星村小苇堂沟屯 | AB89: 220402197603045636 | AC89: 辽源市公安局向阳分局 | AD89: 46948 | AE89: =YEAR(TODAY())-MID(AB89,7,4) -> 50 | AF89: 群众 | AG89: 已婚 | AH89: 176 | AK89: 15004378488 | AL89: 13935383350 | AM89: 初中 | AV89: 45105 | AW89: 45165 | AX89: 劳动合同 | AY89: 力量煤业 | AZ89: 45105 | BA89: 45473 | BB89: 2 | BC89: √ | BD89: √ | BE89: √ | BF89: √ | BG89: 0 | BH89: 0 | BK89: √ | BR89: LM-06-01 | BS89: √ | BT89: √ | BU89: √ | BV89: √ | BW89: √ | BX89: √ | CF89: 2023年
A90: =IF(B90="","",ROW()-1) -> 89 | B90: =IF(AB90="","",AB90) -> 211322198904233271 | C90: 力量煤业 | D90: 直接生产人员 | E90: F10319 | F90: 卢林 | G90: 0 | H90: 0 | I90: =G90+H90 -> 0 | J90: 综采队 | K90: 生产二班副班长 | R90: 工人岗 | T90: 正式工 | U90: 41482 | V90: =IF(U90="","",ROUND(YEARFRAC(U90,TODAY(),1),1)) -> 12.9 | W90: 固定期限劳动合同 | X90: =IF(MOD(RIGHT(LEFT(AB90,17)),2),"男","女") -> 男 | Y90: 汉 | Z90: =MID(AB90,7,4)&"-"&MID(AB90,11,2)&"-"&MID(AB90,13,2) -> 1989-04-23 | AA90: 辽宁省建平县哈拉道口镇镇直家属院4-100号 | AB90: 211322198904233271 | AC90: 建平县公安局 | AD90: 50172 | AE90: =YEAR(TODAY())-MID(AB90,7,4) -> 37 | AF90: 共青团员 | AG90: 未婚 | AH90: 175 | AI90: B2 | AJ90: - | AK90: 18247729007 | AL90: 18804760421 | AM90: 中专 | AN90: 39629 | AO90: 平煤技校 | AP90: 综合机械化采煤 | AV90: 41482 | AW90: 41544 | AX90: 劳动合同 | AY90: 力量煤业 | AZ90: 44835 | BA90: 45565 | BB90: 2 | BC90: √ | BD90: √ | BE90: √ | BF90: √ | BG90: 2 | BH90: 4 | BK90: √ | BM90: √ | BN90: √ | BR90: LM-01-04 | BS90: √ | BT90: √ | CC90: √
A91: =IF(B91="","",ROW()-1) -> 90 | B91: =IF(AB91="","",AB91) -> 130521198210097010 | C91: 力量煤业 | D91: 直接生产人员 | E91: F10440 | F91: 乔田靖 | G91: 0 | H91: 0 | I91: =G91+H91 -> 0 | J91: 综采队 | K91: 生产一班班长 | R91: 工人岗 | T91: 正式工 | U91: 42717 | V91: =IF(U91="","",ROUND(YEARFRAC(U91,TODAY(),1),1)) -> 9.6 | W91: 固定期限劳动合同 | X91: =IF(MOD(RIGHT(LEFT(AB91,17)),2),"男","女") -> 男 | Y91: 汉 | Z91: =MID(AB91,7,4)&"-"&MID(AB91,11,2)&"-"&MID(AB91,13,2) -> 1982-10-09 | AA91: 河北省邢台市邢台县路罗镇桃树坪村791号 | AB91: 130521198210097010 | AC91: 邢台县公安局 | AD91: 50273 | AE91: =YEAR(TODAY())-MID(AB91,7,4) -> 44 | AF91: 群众 | AG91: 已婚 | AH91: 168 | AI91: C1 | AJ91: O | AK91: 15194937837 | AL91: 18803192402 | AM91: 大专（函授） | AN91: 44022 | AO91: 东北大学 | AP91: 煤矿开采技术 | AR91: 采煤机司机（五级） | AV91: 42717 | AW91: 42778 | AX91: 劳动合同 | AY91: 力量煤业 | AZ91: 44562 | BA91: 45291 | BB91: 2 | BC91: √ | BD91: √ | BE91: √ | BF91: √ | BG91: 1 | BH91: 2 | BK91: √ | BN91: √ | BR91: LM-02-01 | BS91: √ | CC91: √ | CG91: 特种作业操作证
A92: =IF(B92="","",ROW()-1) -> 91 | B92: =IF(AB92="","",AB92) -> 150428197305172077 | C92: 力量煤业 | D92: 直接生产人员 | E92: F10229 | F92: 齐学军 | G92: 0 | H92: 0 | I92: =G92+H92 -> 0 | J92: 综采队 | K92: 运输机司机 | R92: 工人岗 | T92: 正式工 | U92: 41323 | V92: =IF(U92="","",ROUND(YEARFRAC(U92,TODAY(),1),1)) -> 13.4 | W92: 固定期限劳动合同 | X92: =IF(MOD(RIGHT(LEFT(AB92,17)),2),"男","女") -> 男 | Y92: 汉 | Z92: =MID(AB92,7,4)&"-"&MID(AB92,11,2)&"-"&MID(AB92,13,2) -> 1973-05-17 | AA92: 内蒙古赤峰市喀喇沁旗十家满族乡楼子店村三组 | AB92: 150428197305172077 | AC92: 喀喇沁旗公安局 | AD92: 46150 | AE92: =YEAR(TODAY())-MID(AB92,7,4) -> 53 | AF92: 群众 | AG92: 已婚 | AH92: 175 | AI92: - | AJ92: O | AK92: 18248332383 | AL92: 18247633177 | AM92: 高中 | AN92: 33390 | AO92: 王爷府高中 | AP92: - | AT92: 初级工 | AV92: 41323 | AW92: 41382 | AX92: 劳动合同 | AY92: 力量煤业 | AZ92: 44743 | BA92: 45473 | BB92: 2 | BC92: √ | BD92: √ | BE92: √ | BF92: √ | BG92: 2 | BH92: 4 | BK92: √ | BN92: √ | BR92: LM-01-02 | BS92: √ | BT92: √ | CC92: √
A93: =IF(B93="","",ROW()-1) -> 92 | B93: =IF(AB93="","",AB93) -> 150428198109260111 | C93: 力量煤业 | D93: 直接生产人员 | E93: F10235 | F93: 于国富 | G93: 0 | H93: 0 | I93: =G93+H93 -> 0 | J93: 综采队 | K93: 运输机司机 | R93: 工人岗 | T93: 正式工 | U93: 41323 | V93: =IF(U93="","",ROUND(YEARFRAC(U93,TODAY(),1),1)) -> 13.4 | W93: 固定期限劳动合同 | X93: =IF(MOD(RIGHT(LEFT(AB93,17)),2),"男","女") -> 男 | Y93: 汉 | Z93: =MID(AB93,7,4)&"-"&MID(AB93,11,2)&"-"&MID(AB93,13,2) -> 1981-09-26 | AA93: 内蒙古赤峰市喀喇沁旗十家满族乡马架子村六组 | AB93: 150428198109260111 | AC93: 喀喇沁旗公安局 | AD93: 49806 | AE93: =YEAR(TODAY())-MID(AB93,7,4) -> 45 | AF93: 群众 | AG93: 已婚 | AH93: 182 | AI93: B2 | AJ93: O | AK93: 18204776286 | AL93: 13789467044 | AM93: 高中 | AN93: 36312 | AO93: 牛营子高中 | AP93: - | AV93: 41323 | AW93: 41382 | AX93: 劳动合同 | AY93: 力量煤业 | AZ93: 44743 | BA93: 45473 | BB93: 2 | BC93: √ | BD93: √ | BE93: √ | BF93: √ | BG93: 2 | BH93: 4 | BK93: √ | BN93: √ | BR93: LM-01-03 | BS93: √ | BT93: √ | CC93: √
A94: =IF(B94="","",ROW()-1) -> 93 | B94: =IF(AB94="","",AB94) -> 370404196911066237 | C94: 力量煤业 | D94: 直接生产人员 | E94: F10280 | F94: 张洪亮 | G94: 0 | H94: 0 | I94: =G94+H94 -> 0 | J94: 综采队 | K94: 运输机司机 | R94: 工人岗 | T94: 正式工 | U94: 41342 | V94: =IF(U94="","",ROUND(YEARFRAC(U94,TODAY(),1),1)) -> 13.3 | W94: 固定期限劳动合同 | X94: =IF(MOD(RIGHT(LEFT(AB94,17)),2),"男","女") -> 男 | Y94: 汉 | Z94: =MID(AB94,7,4)&"-"&MID(AB94,11,2)&"-"&MID(AB94,13,2) -> 1969-11-06 | AA94: 山东省枣庄市峄城区榴园镇颜村11号 | AB94: 370404196911066237 | AC94: 枣庄市公安局峄城分局 | AD94: 45926 | AE94: =YEAR(TODAY())-MID(AB94,7,4) -> 57 | AF94: 群众 | AG94: 已婚 | AH94: 166 | AI94: - | AJ94: - | AK94: 13336371106 | AL94: 15864347075 | AM94: 高中 | AN94: 28734 | AO94: 第八中学 | AP94: - | AV94: 41342 | AW94: 41403 | AX94: 劳动合同 | AY94: 力量煤业 | AZ94: 44743 | BA94: 45473 | BB94: 2 | BC94: √ | BD94: √ | BE94: √ | BF94: √ | BG94: 2 | BH94: 4 | BK94: √ | BN94: √ | BR94: LM-01-03 | BS94: √ | BT94: √ | BZ94: √ | CC94: √ | CG94: 特种作业操作证
A95: =IF(B95="","",ROW()-1) -> 94 | B95: =IF(AB95="","",AB95) -> 231026197510163117 | C95: 力量煤业 | D95: 直接生产人员 | E95: F10418 | F95: 纪文德 | G95: 0 | H95: 0 | I95: =G95+H95 -> 0 | J95: 综采队 | K95: 运输机司机 | R95: 工人岗 | T95: 正式工 | U95: 42597 | V95: =IF(U95="","",ROUND(YEARFRAC(U95,TODAY(),1),1)) -> 9.9 | W95: 固定期限劳动合同 | X95: =IF(MOD(RIGHT(LEFT(AB95,17)),2),"男","女") -> 男 | Y95: 汉 | Z95: =MID(AB95,7,4)&"-"&MID(AB95,11,2)&"-"&MID(AB95,13,2) -> 1975-10-16 | AA95: 黑龙江省密山市裴德镇中兴村委会北山组 | AB95: 231026197510163117 | AC95: 密山市公安局 | AD95: 50609 | AE95: =YEAR(TODAY())-MID(AB95,7,4) -> 51 | AF95: 群众 | AG95: 已婚 | AH95: 170 | AI95: C1 | AJ95: O | AK95: 15047727189 | AL95: 15894915866 | AM95: 中专 | AN95: 34851 | AO95: 黑台镇中学 | AP95: - | AV95: 42597 | AW95: 42657 | AX95: 劳动合同 | AY95: 力量煤业 | AZ95: 44470 | BA95: 45199 | BB95: 2 | BC95: √ | BD95: √ | BE95: √ | BF95: √ | BG95: 1 | BH95: 2 | BK95: √ | BN95: √ | BR95: LM-02-01 | BS95: √ | BT95: √ | CC95: √ | CF95: 2016年
A96: =IF(B96="","",ROW()-1) -> 95 | B96: =IF(AB96="","",AB96) -> 320305198203071511 | C96: 力量煤业 | D96: 直接生产人员 | E96: F10460 | F96: 孙磊 | G96: 0 | I96: =G96+H96 -> 0 | J96: 综采队 | K96: 运输机司机 | R96: 工人岗 | T96: 正式工 | U96: 45016 | V96: =IF(U96="","",ROUND(YEARFRAC(U96,TODAY(),1),1)) -> 3.3 | W96: 固定期限劳动合同 | X96: =IF(MOD(RIGHT(LEFT(AB96,17)),2),"男","女") -> 男 | Y96: 汉 | Z96: =MID(AB96,7,4)&"-"&MID(AB96,11,2)&"-"&MID(AB96,13,2) -> 1982-03-07 | AA96: 江苏省徐州市贾汪区紫庄镇北常庄村11组 | AB96: 320305198203071511 | AC96: 贾汪分局 | AD96: 51320 | AE96: =YEAR(TODAY())-MID(AB96,7,4) -> 44 | AF96: 群众 | AG96: 已婚 | AH96: 168 | AI96: C1 | AJ96: A | AK96: 14752261170 | AL96: 18252171382 | AM96: 高中 | AN96: 37043 | AO96: 徐州市农机职工中等专业学校 | AP96: 农机机械 | AV96: 42831 | AW96: 42891 | AX96: 劳动合同 | AY96: 力量煤业 | AZ96: 44743 | BA96: 45473 | BB96: 2 | BC96: √ | BD96: √ | BE96: √ | BF96: √ | BG96: 1 | BH96: 2 | BK96: √ | BN96: √ | BR96: LM-02-02 | BS96: √ | BT96: √ | BW96: √ | CC96: √
A97: =IF(B97="","",ROW()-1) -> 96 | B97: =IF(AB97="","",AB97) -> 130426198806072339 | C97: 力量煤业 | D97: 直接生产人员 | E97: F11323 | F97: 杨生龙 | I97: =G97+H97 -> 0 | J97: 综采队 | K97: 支护工 | R97: 工人岗 | T97: 正式工 | U97: 44963 | V97: 0 | W97: 固定期限劳动合同 | X97: 男 | Y97: 汉 | Z97: 1988-06-07 | AA97: 河北省邯郸市涉县龙虎乡石泊村14组13号 | AB97: 130426198806072339 | AC97: 涉县公安局 | AD97: 52109 | AE97: 35 | AF97: 群众 | AG97: 已婚 | AH97: 170 | AI97: C1 | AJ97: O | AK97: 15081073235 | AL97: 18931080363 | AM97: 中专 | AO97: 山西省煤炭学校 | AP97: 采煤机电一体化 | AV97: 44963 | AW97: 45021 | AX97: 劳动合同 | AY97: 力量煤业 | AZ97: 44963 | BA97: 45382 | BB97: 2 | BC97: √ | BD97: √ | BE97: √ | BF97: √ | BG97: 0 | BH97: 0 | BK97: √ | BR97: LM-04-04 | BS97: √ | BT97: √ | BU97: √ | BV97: √ | BW97: √ | BX97: √ | CF97: 2023年
A98: =IF(B98="","",ROW()-1) -> 97 | B98: =IF(AB98="","",AB98) -> 370982198510166515 | C98: 力量煤业 | D98: 直接生产人员 | E98: F11507 | F98: 张灿伟 | I98: =G98+H98 -> 0 | J98: 综采队 | K98: 支护工 | R98: 工人岗 | T98: 正式工 | U98: 45026 | V98: =IF(U98="","",ROUND(YEARFRAC(U98,TODAY(),1),1)) -> 3.2 | W98: 固定期限劳动合同 | X98: =IF(MOD(RIGHT(LEFT(AB98,17)),2),"男","女") -> 男 | Y98: 汉 | Z98: =MID(AB98,7,4)&"-"&MID(AB98,11,2)&"-"&MID(AB98,13,2) -> 1985-10-16 | AA98: 山东省新泰市刘杜镇清河村1号 | AB98: 370982198510166515 | AC98: 新泰市公安局 | AD98: 50248 | AE98: =YEAR(TODAY())-MID(AB98,7,4) -> 41 | AF98: 群众 | AG98: 已婚 | AH98: 175 | AJ98: O | AK98: 13562834110 | AL98: 18753862151 | AM98: 高中 | AN98: 2003年 | AO98: 新泰四中 | AP98: 机电 | AV98: 45026 | AW98: 45086 | AX98: 劳动合同 | AY98: 力量煤业 | AZ98: 45026 | BA98: 45473 | BB98: 2 | BC98: √ | BD98: √ | BE98: √ | BF98: √ | BG98: 0 | BH98: 0 | BK98: √ | BR98: LM-05-03 | BS98: √ | BT98: √ | BU98: √ | BV98: √ | BW98: √ | BX98: √ | CF98: 2023年
A99: =IF(B99="","",ROW()-1) -> 98 | B99: =IF(AB99="","",AB99) -> 372525198007101637 | C99: 力量煤业 | D99: 直接生产人员 | E99: F11511 | F99: 张大锋 | I99: =G99+H99 -> 0 | J99: 综采队 | K99: 支护工 | R99: 工人岗 | T99: 正式工 | U99: 45027 | V99: =IF(U99="","",ROUND(YEARFRAC(U99,TODAY(),1),1)) -> 3.2 | W99: 固定期限劳动合同 | X99: =IF(MOD(RIGHT(LEFT(AB99,17)),2),"男","女") -> 男 | Y99: 汉 | Z99: =MID(AB99,7,4)&"-"&MID(AB99,11,2)&"-"&MID(AB99,13,2) -> 1980-07-10 | AA99: 山东省东阿县姜楼镇后寺村112-1号 | AB99: 372525198007101637 | AC99: 东阿县公安局 | AD99: 48880 | AE99: =YEAR(TODAY())-MID(AB99,7,4) -> 46 | AF99: 群众 | AG99: 已婚 | AH99: 168 | AI99: B2 | AJ99: O | AK99: 13181092991 | AL99: 13181098061 | AM99: 高中 | AN99: 1997年 | AO99: 东阿一中 | AV99: 45027 | AW99: 45087 | AX99: 劳动合同 | AY99: 力量煤业 | AZ99: 45027 | BA99: 45473 | BB99: 2 | BC99: √ | BD99: √ | BE99: √ | BF99: √ | BG99: 0 | BH99: 0 | BK99: √ | BR99: LM-05-03 | BS99: √ | BT99: √ | BU99: √ | BV99: √ | BW99: √ | BX99: √ | CF99: 2023年
A100: =IF(B100="","",ROW()-1) -> 99 | B100: =IF(AB100="","",AB100) -> 610623197501181018 | C100: 力量煤业 | D100: 直接生产人员 | E100: F10545 | F100: 周红东 | G100: 0 | H100: 0 | I100: =G100+H100 -> 0 | J100: 综采队 | K100: 支架工 | R100: 工人岗 | T100: 正式工 | U100: 43202 | V100: =IF(U100="","",ROUND(YEARFRAC(U100,TODAY(),1),1)) -> 8.2 | W100: 固定期限劳动合同 | X100: =IF(MOD(RIGHT(LEFT(AB100,17)),2),"男","女") -> 男 | Y100: 汉 | Z100: =MID(AB100,7,4)&"-"&MID(AB100,11,2)&"-"&MID(AB100,13,2) -> 1975-01-18 | AA100: 陕西省子长县石家湾管委会贺家湾村民委员会105号 | AB100: 610623197501181018 | AC100: 子长县公安局 | AD100: 47314 | AE100: =YEAR(TODAY())-MID(AB100,7,4) -> 51 | AF100: 群众 | AG100: 已婚 | AH100: 175 | AI100: - | AJ100: AB | AK100: 18992151048 | AL100: 15991911535 | AM100: 高中 | AN100: 35246 | AO100: 子长高级中学 | AP100: - | AR100: 液压支架工（五级） | AV100: 43202 | AW100: 43262 | AX100: 劳动合同 | AY100: 力量煤业 | AZ100: 44378 | BA100: 45107 | BB100: 2 | BC100: √ | BD100: √ | BE100: √ | BF100: √ | BG100: 1 | BH100: 2 | BK100: √ | BM100: √ | BN100: √ | BR100: LM-02-03 | BS100: √ | BT100: √ | BW100: √ | BZ100: √ | CC100: √
...

Sheet 2023电话费、探亲费
A1: 内蒙古准格尔旗力量煤业有限公司人员2021年员工福利档案
A2: 截至2021年XX月XX日在职员工共计XXX人（本月新入职XX人，离职XX人，XX人内部调动，XX人外部调动）。
A3: 序号 | B3: 部门 | C3: 姓名 | D3: 职务 | F3: 身份证号 | H3: 联系电话
I4: 电话费 | W4: 第一次探亲 | Z4: 第二次探亲 | AC4: 第三次探亲 | AF4: 家属上矿 第一次探亲 | AI4: 家属上矿 第二次探亲 | AL4: 家属上矿 第一次探亲 | AO4: 探亲费 总金额 | AP4: 报销合计 金额 | AQ4: 备案日期 | AR4: 经办人 | AS4: 备注
I5: 1月 | J5: 2月 | K5: 3月 | L5: 4月 | M5: 5月 | N5: 6月 | O5: 7月 | P5: 8月 | Q5: 9月 | R5: 10月 | S5: 11月 | T5: 12月 | U5: 总金额 | V5: 报销人 | W5: 开始时间 | X5: 结束时间 | Y5: 金额 | Z5: 开始时间 | AA5: 结束时间 | AB5: 金额 | AC5: 开始时间 | AD5: 结束时间 | AE5: 金额 | AF5: 开始时间 | AG5: 结束时间 | AH5: 金额 | AI5: 开始时间 | AJ5: 结束时间 | AK5: 金额 | AL5: 开始时间 | AM5: 结束时间 | AN5: 金额
A6: M10000 | B6: 李波 | C6: 公司领导 | D6: 董事长 | E6: =VLOOKUP(B6,'在职人员信息表（2023年电话费全部人员情况）'!F:AB,23,0) -> 130522198205272415 | F6: 130522198205272415 | G6: =IF(E6=F6,"","cuo") | H6: - | O6: =I6+J6+K6+L6+M6+N6 -> 0 | U6: =SUM(I6:T6) -> 0
A7: M10002 | B7: 刘冠杰 | C7: 公司领导 | D7: 财务总监 | E7: =VLOOKUP(B7,'在职人员信息表（2023年电话费全部人员情况）'!F:AB,23,0) -> 152723196312021818 | F7: 152723196312021818 | G7: =IF(E7=F7,"","cuo") | H7: - | O7: =I7+J7+K7+L7+M7+N7 -> 0 | U7: =SUM(I7:T7) -> 0
A8: M10001 | B8: 李运成 | C8: 公司领导 | D8: 总经理 | E8: =VLOOKUP(B8,'在职人员信息表（2023年电话费全部人员情况）'!F:AB,23,0) -> 130503196610061234 | F8: 130503196610061234 | G8: =IF(E8=F8,"","cuo") | H8: - | I8: 201.1 | J8: 200 | K8: 201.2 | L8: 210.4 | M8: 209.5 | N8: 209.5 | O8: =I8+J8+K8+L8+M8+N8 -> 1231.7 | U8: =SUM(I8:T8) -> 2463.4 | V8: 李运成 | W8: 45070 | X8: 45075 | Y8: 1910.58
A9: M10003 | B9: 奚明 | C9: 公司领导 | D9: 常务副总经理 | E9: =VLOOKUP(B9,'在职人员信息表（2023年电话费全部人员情况）'!F:AB,23,0) -> 21128219830626081X | F9: 21128219830626081X | G9: =IF(E9=F9,"","cuo") | H9: - | O9: =I9+J9+K9+L9+M9+N9 -> 0 | U9: =SUM(I9:T9) -> 0
A10: M10005 | B10: 马天峰 | C10: 公司领导 | D10: 副总经理 | E10: =VLOOKUP(B10,'在职人员信息表（2023年电话费全部人员情况）'!F:AB,23,0) -> 640204196305152033 | F10: 640204196305152033 | G10: =IF(E10=F10,"","cuo") | H10: - | I10: 209.5 | J10: 210 | K10: 210.4 | O10: =I10+J10+K10+L10+M10+N10 -> 629.9 | U10: =SUM(I10:T10) -> 1259.8
A11: M10007 | B11: 宋云飞 | C11: 公司领导 | D11: 副总经理 | E11: =VLOOKUP(B11,'在职人员信息表（2023年电话费全部人员情况）'!F:AB,23,0) -> 230822198111094910 | F11: 230822198111094910 | G11: =IF(E11=F11,"","cuo") | H11: - | O11: =I11+J11+K11+L11+M11+N11 -> 0 | U11: =SUM(I11:T11) -> 0
A12: M10004 | B12: 窦发权 | C12: 公司领导 | D12: 副总经理 | E12: =VLOOKUP(B12,'在职人员信息表（2023年电话费全部人员情况）'!F:AB,23,0) -> 370902197109021292 | F12: 370902197109021292 | G12: =IF(E12=F12,"","cuo") | H12: - | I12: 309.7 | J12: 309.4 | K12: 309.6 | L12: 309.4 | M12: 309.2 | N12: 309.5 | O12: =I12+J12+K12+L12+M12+N12 -> 1856.8 | U12: =SUM(I12:T12) -> 3713.6 | W12: 45047 | X12: 45051 | Y12: 1271.18 | Z12: 45094 | AA12: 45103 | AB12: 1939.91
B13: 池永淳 | C13: 公司领导 | D13: 副总经理 | E13: =VLOOKUP(B13,'在职人员信息表（2023年电话费全部人员情况）'!F:AB,23,0) -> 130402198210271539 | F13: 130402198210271539 | G13: =IF(E13=F13,"","cuo") | K13: 99 | L13: 99 | M13: 99 | N13: 99 | O13: =I13+J13+K13+L13+M13+N13 -> 396 | U13: =SUM(I13:T13) -> 792 | W13: 45045 | X13: 45053 | Y13: 1084.1
A14: M10006 | B14: 李印楼 | C14: 公司领导 | D14: 副总经理兼矿长 | E14: =VLOOKUP(B14,'在职人员信息表（2023年电话费全部人员情况）'!F:AB,23,0) -> 320322197003037337 | F14: 320322197003037337 | G14: =IF(E14=F14,"","cuo") | H14: - | I14: 216.2 | J14: 268.9 | K14: 358.5 | O14: =I14+J14+K14+L14+M14+N14 -> 843.6 | U14: =SUM(I14:T14) -> 1687.2 | W14: 45020 | X14: 45030 | Y14: 1517.83
A15: M10008 | B15: 周洪刚 | C15: 公司领导 | D15: 总经理助理兼多种经营部经理 | E15: =VLOOKUP(B15,'在职人员信息表（2023年电话费全部人员情况）'!F:AB,23,0) -> 130403196411292114 | F15: 130403196411292114 | G15: =IF(E15=F15,"","cuo") | H15: - | I15: 138.3 | J15: 193.65 | K15: 229.9 | L15: 185.15 | M15: 172.65 | N15: 178.4 | O15: =I15+J15+K15+L15+M15+N15 -> 1098.05 | U15: =SUM(I15:T15) -> 2196.1 | W15: 44943 | X15: 44954 | Y15: 920 | AF15: 45011 | AG15: 45037 | AH15: 763
A16: M10010 | B16: 王震 | C16: 公司领导 | D16: 副总经理 | E16: =VLOOKUP(B16,'在职人员信息表（2023年电话费全部人员情况）'!F:AB,23,0) -> 152723198509184812 | F16: 152723198509184812 | G16: =IF(E16=F16,"","cuo") | H16: - | I16: 254.1 | J16: 259.6 | K16: 283.4 | O16: =I16+J16+K16+L16+M16+N16 -> 797.1 | U16: =SUM(I16:T16) -> 1594.2
A17: M10192 | B17: 白新江 | C17: 矿级领导 | D17: 安全副矿长 | E17: =VLOOKUP(B17,'在职人员信息表（2023年电话费全部人员情况）'!F:AB,23,0) -> 140224198001280630 | F17: 140224198001280630 | G17: =IF(E17=F17,"","cuo") | H17: 15134889255 | I17: 355.08 | J17: 304.91 | K17: 314.23 | L17: 327.96 | M17: 311.66 | N17: 343.48 | O17: =I17+J17+K17+L17+M17+N17 -> 1957.32 | U17: =SUM(I17:T17) -> 3914.64
A18: M10293 | B18: 郭洪亮 | C18: 矿级领导 | D18: 机电副矿长 | E18: =VLOOKUP(B18,'在职人员信息表（2023年电话费全部人员情况）'!F:AB,23,0) -> 230303198407064239 | F18: 230303198407064239 | G18: =IF(E18=F18,"","cuo") | H18: 15894923254 | I18: 176.4 | J18: 126.6 | K18: 148.65 | O18: =I18+J18+K18+L18+M18+N18 -> 451.65 | U18: =SUM(I18:T18) -> 903.3 | W18: 45018 | X18: 45028 | Y18: 1886
A19: M10294 | B19: 杨维海 | C19: 矿级领导 | D19: 生产副矿长 | E19: =VLOOKUP(B19,'在职人员信息表（2023年电话费全部人员情况）'!F:AB,23,0) -> 340403197510102439 | F19: 340403197510102439 | G19: =IF(E19=F19,"","cuo") | H19: 17701251277 | I19: 152.5 | J19: 142.6 | K19: 172.8 | O19: =I19+J19+K19+L19+M19+N19 -> 467.9 | U19: =SUM(I19:T19) -> 935.8 | W19: 44955 | X19: 44965 | Y19: 2586.76 | Z19: 45042 | AA19: 45052 | AB19: 2523.56
A20: M10111 | B20: 李秦生 | C20: 矿级领导 | D20: 总工程师 | E20: =VLOOKUP(B20,'在职人员信息表（2023年电话费全部人员情况）'!F:AB,23,0) -> 362329198611264574 | F20: 362329198611264574 | G20: =IF(E20=F20,"","cuo") | H20: 18947780150 | I20: 443.47 | J20: 463.76 | K20: 398.64 | O20: =I20+J20+K20+L20+M20+N20 -> 1305.87 | U20: =SUM(I20:T20) -> 2611.74 | AF20: 45043 | AG20: 45053 | AH20: 1430 | AI20: 45043 | AJ20: 45053 | AK20: 1430
A21: M10250 | B21: 刘栓柱 | C21: 矿级领导 | D21: 大饭铺煤矿副矿长 | E21: =VLOOKUP(B21,'在职人员信息表（2023年电话费全部人员情况）'!F:AB,23,0) -> 130521197011257013 | F21: 130521197011257013 | G21: =IF(E21=F21,"","cuo") | H21: 15149622032 | J21: 185.65 | K21: 162 | O21: =I21+J21+K21+L21+M21+N21 -> 347.65 | U21: =SUM(I21:T21) -> 695.3
A22: M10552 | B22: 乔孝军 | C22: 综采队 | D22: 矿长助理兼综采队队长 | E22: =VLOOKUP(B22,'在职人员信息表（2023年电话费全部人员情况）'!F:AB,23,0) -> #N/A | F22: #N/A | G22: =IF(E22=F22,"","cuo") -> #N/A | H22: 15149797534 | I22: 211.5 | O22: =I22+J22+K22+L22+M22+N22 -> 211.5 | U22: =SUM(I22:T22) -> 423
A23: M10145 | B23: 贺伟 | C23: 综采队 | D23: 副队长 | E23: =VLOOKUP(B23,'在职人员信息表（2023年电话费全部人员情况）'!F:AB,23,0) -> 15272319861209601X | F23: 15272319861209601X | G23: =IF(E23=F23,"","cuo") | H23: 17684871616 | O23: =I23+J23+K23+L23+M23+N23 -> 0 | U23: =SUM(I23:T23) -> 0
A24: M10185 | B24: 任建龙 | C24: 综采队 | D24: 副队长 | E24: =VLOOKUP(B24,'在职人员信息表（2023年电话费全部人员情况）'!F:AB,23,0) -> 152723198804241517 | F24: 152723198804241517 | G24: =IF(E24=F24,"","cuo") | H24: 18547159097 | O24: =I24+J24+K24+L24+M24+N24 -> 0 | U24: =SUM(I24:T24) -> 0
A25: F10487 | B25: 杨培 | C25: 综采队 | D25: 副队长 | E25: =VLOOKUP(B25,'在职人员信息表（2023年电话费全部人员情况）'!F:AB,23,0) -> 152723198612071517 | F25: 152723198612071517 | G25: =IF(E25=F25,"","cuo") | H25: 17614770811 | O25: =I25+J25+K25+L25+M25+N25 -> 0 | U25: =SUM(I25:T25) -> 0
A26: F10236 | B26: 张坤 | C26: 综采队 | D26: 副队长 | E26: =VLOOKUP(B26,'在职人员信息表（2023年电话费全部人员情况）'!F:AB,23,0) -> 211404198108276230 | F26: 211404198108276230 | G26: =IF(E26=F26,"","cuo") | H26: 15374943266 | O26: =I26+J26+K26+L26+M26+N26 -> 0 | U26: =SUM(I26:T26) -> 0
A27: P10634 | B27: 曹煜坤 | C27: 综采队 | D27: 办事员 | E27: =VLOOKUP(B27,'在职人员信息表（2023年电话费全部人员情况）'!F:AB,23,0) -> #N/A | F27: #N/A | G27: =IF(E27=F27,"","cuo") -> #N/A | H27: 15949407571 | O27: =I27+J27+K27+L27+M27+N27 -> 0 | U27: =SUM(I27:T27) -> 0
A28: P10731 | B28: 蔡庆鑫 | C28: 综采队 | D28: 技术员 | E28: =VLOOKUP(B28,'在职人员信息表（2023年电话费全部人员情况）'!F:AB,23,0) -> 152128199611050910 | F28: 152128199611050910 | G28: =IF(E28=F28,"","cuo") | H28: 15147725233 | O28: =I28+J28+K28+L28+M28+N28 -> 0 | U28: =SUM(I28:T28) -> 0
A29: F10219 | B29: 张向辉 | C29: 综采队 | D29: 安检员 | E29: =VLOOKUP(B29,'在职人员信息表（2023年电话费全部人员情况）'!F:AB,23,0) -> 220881197811216011 | F29: 220881197811216011 | G29: =IF(E29=F29,"","cuo") | H29: 15134876544 | O29: =I29+J29+K29+L29+M29+N29 -> 0 | U29: =SUM(I29:T29) -> 0
A30: F10233 | B30: 薛宪伟 | C30: 综采队 | D30: 采煤机司机 | E30: =VLOOKUP(B30,'在职人员信息表（2023年电话费全部人员情况）'!F:AB,23,0) -> 320322198604162517 | F30: 320322198604162517 | G30: =IF(E30=F30,"","cuo") | H30: 13947777059 | O30: =I30+J30+K30+L30+M30+N30 -> 0 | U30: =SUM(I30:T30) -> 0
A31: F10288 | B31: 刘瑞余 | C31: 综采队 | D31: 采煤机司机 | E31: =VLOOKUP(B31,'在职人员信息表（2023年电话费全部人员情况）'!F:AB,23,0) -> #N/A | F31: #N/A | G31: =IF(E31=F31,"","cuo") -> #N/A | H31: 15354891448 | O31: =I31+J31+K31+L31+M31+N31 -> 0 | U31: =SUM(I31:T31) -> 0
A32: F10457 | B32: 赵明武 | C32: 综采队 | D32: 采煤机司机 | E32: =VLOOKUP(B32,'在职人员信息表（2023年电话费全部人员情况）'!F:AB,23,0) -> #N/A | F32: #N/A | G32: =IF(E32=F32,"","cuo") -> #N/A | H32: 15149671949 | O32: =I32+J32+K32+L32+M32+N32 -> 0 | U32: =SUM(I32:T32) -> 0
